Workbook
Name AdICOS: Ref!$AJ$47
Name AdS: Ref!$AJ$3:$AJ$5
Name AdvFee: 'Inputs & Summary'!$C$98
Name AFR: 'Inputs & Summary'!$C$63
Name AICOPrFee: 'Inputs & Summary'!$C$87
Name AnnAge: 'Inputs & Summary'!$W$68
Name Category: 'Inputs & Summary'!$C$12
Name CDSCP: 'Inputs & Summary'!$C$16
Name CDSCPSel: 'Inputs & Summary'!$C$15
Name CGR: 'Inputs & Summary'!$C$62
Name CLPrem: 'Inputs & Summary'!$C$48
Name Compact: Ref!$AG$68:$AI$118
Name EICRInd: 'Inputs & Summary'!$C$84
Name EICRRate: 'Inputs & Summary'!$C$85
Name Election: 'Inputs & Summary'!$C$40
Name Focus: 'Inputs & Summary'!$C$54
Name FWD: 'Inputs & Summary'!$C$71
Name GIRM1: 'Inputs & Summary'!$C$93
Name GIRM2: 'Inputs & Summary'!$C$94
Name GMABC: 'Inputs & Summary'!$C$66
Name GMABR: 'Inputs & Summary'!$C$67
Name GMIR: 'Inputs & Summary'!$C$64
Name GMWBFee: 'Inputs & Summary'!$C$70
Name ICP: 'Inputs & Summary'!$C$92
Name ICR: 'Inputs & Summary'!$C$91
Name IED: 'Inputs & Summary'!$C$57
Name InPrem: 'Inputs & Summary'!$C$49
Name InS: Ref!$AJ$6:$AJ$25
Name IPI: 'Inputs & Summary'!$C$101
Name ISD: 'Inputs & Summary'!$C$53
Name IssAge1: 'Inputs & Summary'!$C$34
Name IssAge2: 'Inputs & Summary'!$C$35
Name LBInd: 'Inputs & Summary'!$C$69
Name LIADur: 'Inputs & Summary'!$C$73
Name LIB: Ref!$AH$54
Name LIC: Ref!$AI$54
Name LIMLIPMF: Ref!$AJ$54:$AJ$55
Name LIPFLIPMF: Ref!$AK$54:$AK$55
Name LivBen: 'Inputs & Summary'!$C$17
Name MatAge: 'Inputs & Summary'!$C$36
Name MaxIGP: 'Inputs & Summary'!$C$102
Name MCIR: 'Inputs & Summary'!$C$21
Name MCIRInd: 'Inputs & Summary'!$C$20
Name ModReg: Ref!$AG$68:$AJ$118
Name MWVBasis: 'Inputs & Summary'!$C$59
Name MWVRate: 'Inputs & Summary'!$C$60
Name NIRM1: 'Inputs & Summary'!$C$95
Name NIRM2: 'Inputs & Summary'!$C$96
Name None: Ref!$AG$54
Name OMaxR: 'Inputs & Summary'!$C$89
Name OMR: 'Inputs & Summary'!$C$88
Name PFED: 'Inputs & Summary'!$C$55
Name PoI5N: Ref!$AJ$26:$AJ$27
Name PoIPN: Ref!$AJ$28:$AJ$29
Name PoSS: Ref!$AJ$30:$AJ$34
Name PremEnh: 'Inputs & Summary'!$C$51
Name Product: 'Inputs & Summary'!$C$14
Name Projection: 'Inputs & Summary'!$C$56
Name PTab: 'Inputs & Summary'!$C$13
Name ResetDur: 'Inputs & Summary'!$C$100

Sheet Report
B2: ="Corebridge "&Product&" ‒ Hypothetical Illustration for "&$C$10 -> Corebridge Power Index Plus ‒ Hypothetical Illustration for Valued Client | P2: ="Corebridge "&Product&" ‒ Hypothetical Illustration for "&$C$10 -> Corebridge Power Index Plus ‒ Hypothetical Illustration for Valued Client
B4: Profile & Income Details | E4: Interest Crediting Strategies | P4: =IF(OR(Summary="Favorable",Summary="Unfavorable"),"Interest Crediting Strategy Level Summary","Contract Level Summary") -> Contract Level Summary
F5: Fixed Rate | G5: Cap | H5: ParRate | I5: Triggered Rate | J5: Spread | K5: EPRS Fee | L5: Allocation | S5: 1 | T5: 2 | U5: 3 | V5: 4 | W5: 5
S6: =IF(OR(Summary="Favorable",Summary="Unfavorable"),IF(IFERROR(VLOOKUP(INDEX([1]STRTG!$D$68:$D$321,MATCH(S$5,[1]STRTG!$C$68:$C$321,0),1),[1]STRTG!$N$14:$Q$303,4,FALSE),"")<>'Inputs & Summary'!$R$7,"",IFERROR(VLOOKUP(INDEX([1]STRTG!$D$68:$D$321,MATCH(S$5,[1]STRTG!$C$68:$C$321,0),1),[1]STRTG!$N$14:$Q$303,4,FALSE),"")),IFERROR(VLOOKUP(INDEX([1]STRTG!$D$68:$D$321,MATCH(S$5,[1]STRTG!$C$68:$C$321,0),1),[1]STRTG!$N$14:$Q$303,4,FALSE),"")) -> GSPC | T6: =IF(OR(Summary="Favorable",Summary="Unfavorable"),IF(IFERROR(VLOOKUP(INDEX([1]STRTG!$D$68:$D$321,MATCH(T$5,[1]STRTG!$C$68:$C$321,0),1),[1]STRTG!$N$14:$Q$303,4,FALSE),"")<>'Inputs & Summary'!$R$7,"",IFERROR(VLOOKUP(INDEX([1]STRTG!$D$68:$D$321,MATCH(T$5,[1]STRTG!$C$68:$C$321,0),1),[1]STRTG!$N$14:$Q$303,4,FALSE),"")),IFERROR(VLOOKUP(INDEX([1]STRTG!$D$68:$D$321,MATCH(T$5,[1]STRTG!$C$68:$C$321,0),1),[1]STRTG!$N$14:$Q$303,4,FALSE),"")) -> PIMGOPT | U6: =IF(OR(Summary="Favorable",Summary="Unfavorable"),IF(IFERROR(VLOOKUP(INDEX([1]STRTG!$D$68:$D$321,MATCH(U$5,[1]STRTG!$C$68:$C$321,0),1),[1]STRTG!$N$14:$Q$303,4,FALSE),"")<>'Inputs & Summary'!$R$7,"",IFERROR(VLOOKUP(INDEX([1]STRTG!$D$68:$D$321,MATCH(U$5,[1]STRTG!$C$68:$C$321,0),1),[1]STRTG!$N$14:$Q$303,4,FALSE),"")),IFERROR(VLOOKUP(INDEX([1]STRTG!$D$68:$D$321,MATCH(U$5,[1]STRTG!$C$68:$C$321,0),1),[1]STRTG!$N$14:$Q$303,4,FALSE),"")) -> MLSB | V6: =IF(OR(Summary="Favorable",Summary="Unfavorable"),IF(IFERROR(VLOOKUP(INDEX([1]STRTG!$D$68:$D$321,MATCH(V$5,[1]STRTG!$C$68:$C$321,0),1),[1]STRTG!$N$14:$Q$303,4,FALSE),"")<>'Inputs & Summary'!$R$7,"",IFERROR(VLOOKUP(INDEX([1]STRTG!$D$68:$D$321,MATCH(V$5,[1]STRTG!$C$68:$C$321,0),1),[1]STRTG!$N$14:$Q$303,4,FALSE),"")),IFERROR(VLOOKUP(INDEX([1]STRTG!$D$68:$D$321,MATCH(V$5,[1]STRTG!$C$68:$C$321,0),1),[1]STRTG!$N$14:$Q$303,4,FALSE),"")) | W6: =IF(OR(Summary="Favorable",Summary="Unfavorable"),IF(IFERROR(VLOOKUP(INDEX([1]STRTG!$D$68:$D$321,MATCH(W$5,[1]STRTG!$C$68:$C$321,0),1),[1]STRTG!$N$14:$Q$303,4,FALSE),"")<>'Inputs & Summary'!$R$7,"",IFERROR(VLOOKUP(INDEX([1]STRTG!$D$68:$D$321,MATCH(W$5,[1]STRTG!$C$68:$C$321,0),1),[1]STRTG!$N$14:$Q$303,4,FALSE),"")),IFERROR(VLOOKUP(INDEX([1]STRTG!$D$68:$D$321,MATCH(W$5,[1]STRTG!$C$68:$C$321,0),1),[1]STRTG!$N$14:$Q$303,4,FALSE),""))
E7: =IF(OR('Inputs & Summary'!$C$141="N",COUNTIFS('Inputs & Summary'!$B$142:$B$171,"<>",'Inputs & Summary'!$C$142:$C$171,">0")<>COUNTIF('Inputs & Summary'!$C$142:$C$171,">0")),"!!! Review Strategy Allocations and Make Appropriate Adjustments !!!","Illustrated Interest Crediting Strategies") -> Illustrated Interest Crediting Strategies | F7: Fixed Rate | G7: Cap Rate | H7: Participation Rate | I7: Trigger Rate | J7: Spread | K7: EPRS Fee % | L7: Allocation
G8: Cap Rate
P9: Year | Q9: Year | R9: Age | S9: Tenor Selectors | X9: Hypothetical Values | AK9: Legacy
B10: Owner | C10: ='Inputs & Summary'!C32 -> Valued Client | E10: {=_xlfn.UNIQUE(_xlfn._xlws.FILTER('Inputs & Summary'!$B$142:$B$171,'Inputs & Summary'!$C$142:$C$171>0))} -> 1-Year Fixed Rate, Fixed Account | F10: =IF($E10="","",INDEX([1]STRTG!$T$14:$AC$303,MATCH($E10,[1]STRTG!$P$14:$P$303,0),MATCH(F$5,[1]STRTG!$T$13:$AC$13,0))) -> 0.045 | G10: =IF($E10="","",INDEX([1]STRTG!$T$14:$AC$303,MATCH($E10,[1]STRTG!$P$14:$P$303,0),MATCH(G$5,[1]STRTG!$T$13:$AC$13,0))) -> N/A | H10: =IF($E10="","",INDEX([1]STRTG!$T$14:$AC$303,MATCH($E10,[1]STRTG!$P$14:$P$303,0),MATCH(H$5,[1]STRTG!$T$13:$AC$13,0))) -> N/A | I10: =IF($E10="","",INDEX([1]STRTG!$T$14:$AC$303,MATCH($E10,[1]STRTG!$P$14:$P$303,0),MATCH(I$5,[1]STRTG!$T$13:$AC$13,0))) -> N/A | J10: =IF($E10="","",INDEX([1]STRTG!$T$14:$AC$303,MATCH($E10,[1]STRTG!$P$14:$P$303,0),MATCH(J$5,[1]STRTG!$T$13:$AC$13,0))) -> N/A | K10: =IF($E10="","",IF(RIGHT(VLOOKUP($E10,[1]STRTG!$P$14:$S$303,4,FALSE),6)="EPRST1",Ref!$C$103,IF(RIGHT(VLOOKUP($E10,[1]STRTG!$P$14:$S$303,4,FALSE),6)="EPRST2",Ref!$C$104,"N/A"))) -> N/A | L10: =IF($E10="","",INDEX([1]STRTG!$T$14:$AC$303,MATCH($E10,[1]STRTG!$P$14:$P$303,0),MATCH(L$5,[1]STRTG!$T$13:$AC$13,0))) -> 0.1 | S10: 1-Year | T10: 1-Year | U10: 1-Year | V10: 1-Year | W10: 1-Year
B11: Election | C11: =Election -> Single Life | E11: 1-Year PTP with Secure Cap, S&P 500 | F11: =IF($E11="","",INDEX([1]STRTG!$T$14:$AC$303,MATCH($E11,[1]STRTG!$P$14:$P$303,0),MATCH(F$5,[1]STRTG!$T$13:$AC$13,0))) -> N/A | G11: =IF($E11="","",INDEX([1]STRTG!$T$14:$AC$303,MATCH($E11,[1]STRTG!$P$14:$P$303,0),MATCH(G$5,[1]STRTG!$T$13:$AC$13,0))) -> 0 | H11: =IF($E11="","",INDEX([1]STRTG!$T$14:$AC$303,MATCH($E11,[1]STRTG!$P$14:$P$303,0),MATCH(H$5,[1]STRTG!$T$13:$AC$13,0))) -> N/A | I11: =IF($E11="","",INDEX([1]STRTG!$T$14:$AC$303,MATCH($E11,[1]STRTG!$P$14:$P$303,0),MATCH(I$5,[1]STRTG!$T$13:$AC$13,0))) -> N/A | J11: =IF($E11="","",INDEX([1]STRTG!$T$14:$AC$303,MATCH($E11,[1]STRTG!$P$14:$P$303,0),MATCH(J$5,[1]STRTG!$T$13:$AC$13,0))) -> N/A | K11: =IF($E11="","",IF(RIGHT(VLOOKUP($E11,[1]STRTG!$P$14:$S$303,4,FALSE),6)="EPRST1",Ref!$C$103,IF(RIGHT(VLOOKUP($E11,[1]STRTG!$P$14:$S$303,4,FALSE),6)="EPRST2",Ref!$C$104,"N/A"))) -> N/A | L11: =IF($E11="","",INDEX([1]STRTG!$T$14:$AC$303,MATCH($E11,[1]STRTG!$P$14:$P$303,0),MATCH(L$5,[1]STRTG!$T$13:$AC$13,0))) -> 0.4 | S11: =IF(S$6="","",IF(INDEX([1]Allocated!$D$11:$AY$11,1,MATCH(S$5,[1]Allocated!$D$13:$AY$13,0))="","",INDEX([1]Allocated!$D$11:$AY$11,1,MATCH(S$5,[1]Allocated!$D$13:$AY$13,0))&" "&VLOOKUP(S$10,Ref!$Y$61:$AA$63,3,FALSE))) -> S&P 500 Index Annual Change | T11: =IF(T$6="","",IF(INDEX([1]Allocated!$D$11:$AY$11,1,MATCH(T$5,[1]Allocated!$D$13:$AY$13,0))="","",INDEX([1]Allocated!$D$11:$AY$11,1,MATCH(T$5,[1]Allocated!$D$13:$AY$13,0))&" "&VLOOKUP(T$10,Ref!$Y$61:$AA$63,3,FALSE))) -> PIMCO Global Optima Index Annual Change | U11: =IF(U$6="","",IF(INDEX([1]Allocated!$D$11:$AY$11,1,MATCH(U$5,[1]Allocated!$D$13:$AY$13,0))="","",INDEX([1]Allocated!$D$11:$AY$11,1,MATCH(U$5,[1]Allocated!$D$13:$AY$13,0))&" "&VLOOKUP(U$10,Ref!$Y$61:$AA$63,3,FALSE))) -> MLSB Index Annual Change | V11: =IF(V$6="","",IF(INDEX([1]Allocated!$D$11:$AY$11,1,MATCH(V$5,[1]Allocated!$D$13:$AY$13,0))="","",INDEX([1]Allocated!$D$11:$AY$11,1,MATCH(V$5,[1]Allocated!$D$13:$AY$13,0))&" "&VLOOKUP(V$10,Ref!$Y$61:$AA$63,3,FALSE))) | W11: =IF(W$6="","",IF(INDEX([1]Allocated!$D$11:$AY$11,1,MATCH(W$5,[1]Allocated!$D$13:$AY$13,0))="","",INDEX([1]Allocated!$D$11:$AY$11,1,MATCH(W$5,[1]Allocated!$D$13:$AY$13,0))&" "&VLOOKUP(W$10,Ref!$Y$61:$AA$63,3,FALSE))) | X11: Credited Interest Rate | Y11: =IF(OR(PTab="P7",AND(PTab="P2",Ref!$S$53="Y")),"Interest Earned including","Interest Earned") -> Interest Earned including | Z11: =IF(AND(LivBen<>"None",RIGHT(Category,2)<>"NY"),"Income Base","") | AA11: =IF(AND(LivBen<>"None",RIGHT(Category,2)<>"NY"),"Income Credit","") | AB11: =IF(AND(LivBen<>"None",RIGHT(Category,2)<>"NY"),"Annual Income for Life",IF(AND(LivBen<>"None",RIGHT(Category,2)="NY"),"Guaranteed Lifetime Income Amount","")) | AC11: Withdrawal Amount | AD11: Cumulative Withdrawals | AE11: Fees | AF11: Contract Anniversary Value | AG11: Cash Surrender Value | AH11: =IF(RIGHT(Category,2)="NY","Minimum Accumulation Value","Minimum Withdrawal Value") -> Minimum Withdrawal Value | AI11: =IF(PTab="P7","GROP Amount",IF(Ref!$S$53="Y","GMAB Value","")) -> GMAB Value | AJ11: =IF(PTab="P7","Overlay Credit",IF(Ref!$S$53="Y","GMAB Amount","")) -> GMAB Amount | AK11: Hypothetical Death Benefit
B12: Issue Age Original Annuitant | C12: =IssAge1 -> 73 | E12: 1-Year PTP with Cap, PIMCO Global Optima | F12: =IF($E12="","",INDEX([1]STRTG!$T$14:$AC$303,MATCH($E12,[1]STRTG!$P$14:$P$303,0),MATCH(F$5,[1]STRTG!$T$13:$AC$13,0))) -> N/A | G12: =IF($E12="","",INDEX([1]STRTG!$T$14:$AC$303,MATCH($E12,[1]STRTG!$P$14:$P$303,0),MATCH(G$5,[1]STRTG!$T$13:$AC$13,0))) -> 0.115 | H12: =IF($E12="","",INDEX([1]STRTG!$T$14:$AC$303,MATCH($E12,[1]STRTG!$P$14:$P$303,0),MATCH(H$5,[1]STRTG!$T$13:$AC$13,0))) -> N/A | I12: =IF($E12="","",INDEX([1]STRTG!$T$14:$AC$303,MATCH($E12,[1]STRTG!$P$14:$P$303,0),MATCH(I$5,[1]STRTG!$T$13:$AC$13,0))) -> N/A | J12: =IF($E12="","",INDEX([1]STRTG!$T$14:$AC$303,MATCH($E12,[1]STRTG!$P$14:$P$303,0),MATCH(J$5,[1]STRTG!$T$13:$AC$13,0))) -> N/A | K12: =IF($E12="","",IF(RIGHT(VLOOKUP($E12,[1]STRTG!$P$14:$S$303,4,FALSE),6)="EPRST1",Ref!$C$103,IF(RIGHT(VLOOKUP($E12,[1]STRTG!$P$14:$S$303,4,FALSE),6)="EPRST2",Ref!$C$104,"N/A"))) -> N/A | L12: =IF($E12="","",INDEX([1]STRTG!$T$14:$AC$303,MATCH($E12,[1]STRTG!$P$14:$P$303,0),MATCH(L$5,[1]STRTG!$T$13:$AC$13,0))) -> 0.1 | Y12: ='Inputs & Summary'!T10 -> #REF!
B13: Issue Age Second Annuitant if Joint | C13: =IF(Election = "Joint Life",IssAge2,"N/A") -> N/A | E13: 1-Year PTP with ParRate, MLSB | F13: =IF($E13="","",INDEX([1]STRTG!$T$14:$AC$303,MATCH($E13,[1]STRTG!$P$14:$P$303,0),MATCH(F$5,[1]STRTG!$T$13:$AC$13,0))) -> N/A | G13: =IF($E13="","",INDEX([1]STRTG!$T$14:$AC$303,MATCH($E13,[1]STRTG!$P$14:$P$303,0),MATCH(G$5,[1]STRTG!$T$13:$AC$13,0))) -> N/A | H13: =IF($E13="","",INDEX([1]STRTG!$T$14:$AC$303,MATCH($E13,[1]STRTG!$P$14:$P$303,0),MATCH(H$5,[1]STRTG!$T$13:$AC$13,0))) -> 0.97 | I13: =IF($E13="","",INDEX([1]STRTG!$T$14:$AC$303,MATCH($E13,[1]STRTG!$P$14:$P$303,0),MATCH(I$5,[1]STRTG!$T$13:$AC$13,0))) -> N/A | J13: =IF($E13="","",INDEX([1]STRTG!$T$14:$AC$303,MATCH($E13,[1]STRTG!$P$14:$P$303,0),MATCH(J$5,[1]STRTG!$T$13:$AC$13,0))) -> N/A | K13: =IF($E13="","",IF(RIGHT(VLOOKUP($E13,[1]STRTG!$P$14:$S$303,4,FALSE),6)="EPRST1",Ref!$C$103,IF(RIGHT(VLOOKUP($E13,[1]STRTG!$P$14:$S$303,4,FALSE),6)="EPRST2",Ref!$C$104,"N/A"))) -> N/A | L13: =IF($E13="","",INDEX([1]STRTG!$T$14:$AC$303,MATCH($E13,[1]STRTG!$P$14:$P$303,0),MATCH(L$5,[1]STRTG!$T$13:$AC$13,0))) -> 0.4 | P13: =IF('Inputs & Summary'!O11="","",IF('Inputs & Summary'!O11=0,"At Issue",'Inputs & Summary'!P11)) -> At Issue | Q13: =IF($P13="","",'Inputs & Summary'!O11) -> 0 | R13: =IF($P13="","",'Inputs & Summary'!Q11) -> #REF! | S13: {=IF($P13="","",IF(S$11="",0,IFERROR(INDEX(INDIRECT(S$6&VLOOKUP(Summary,Ref!$Y$13:$AC$18,3,FALSE)),MATCH(IF($P13="At Issue",VLOOKUP(Summary,Ref!$Y$13:$AC$18,2,FALSE),$P13),INDIRECT(S$6&VLOOKUP(Summary,Ref!$Y$13:$AC$18,4,FALSE)),0),VLOOKUP(S$10,Ref!$Y$61:$AA$63,2,FALSE)),0)))} -> 0 | T13: {=IF($P13="","",IF(T$11="",0,IFERROR(INDEX(INDIRECT(T$6&VLOOKUP(Summary,Ref!$Y$13:$AC$18,3,FALSE)),MATCH(IF($P13="At Issue",VLOOKUP(Summary,Ref!$Y$13:$AC$18,2,FALSE),$P13),INDIRECT(T$6&VLOOKUP(Summary,Ref!$Y$13:$AC$18,4,FALSE)),0),VLOOKUP(T$10,Ref!$Y$61:$AA$63,2,FALSE)),0)))} -> 0 | U13: {=IF($P13="","",IF(U$11="",0,IFERROR(INDEX(INDIRECT(U$6&VLOOKUP(Summary,Ref!$Y$13:$AC$18,3,FALSE)),MATCH(IF($P13="At Issue",VLOOKUP(Summary,Ref!$Y$13:$AC$18,2,FALSE),$P13),INDIRECT(U$6&VLOOKUP(Summary,Ref!$Y$13:$AC$18,4,FALSE)),0),VLOOKUP(U$10,Ref!$Y$61:$AA$63,2,FALSE)),0)))} -> 0 | V13: {=IF($P13="","",IF(V$11="",0,IFERROR(INDEX(INDIRECT(V$6&VLOOKUP(Summary,Ref!$Y$13:$AC$18,3,FALSE)),MATCH(IF($P13="At Issue",VLOOKUP(Summary,Ref!$Y$13:$AC$18,2,FALSE),$P13),INDIRECT(V$6&VLOOKUP(Summary,Ref!$Y$13:$AC$18,4,FALSE)),0),VLOOKUP(V$10,Ref!$Y$61:$AA$63,2,FALSE)),0)))} -> 0 | W13: {=IF($P13="","",IF(W$11="",0,IFERROR(INDEX(INDIRECT(W$6&VLOOKUP(Summary,Ref!$Y$13:$AC$18,3,FALSE)),MATCH(IF($P13="At Issue",VLOOKUP(Summary,Ref!$Y$13:$AC$18,2,FALSE),$P13),INDIRECT(W$6&VLOOKUP(Summary,Ref!$Y$13:$AC$18,4,FALSE)),0),VLOOKUP(W$10,Ref!$Y$61:$AA$63,2,FALSE)),0)))} -> 0 | X13: =IF($P13="","",'Inputs & Summary'!S11) -> #REF! | Y13: =IF($P13="","",'Inputs & Summary'!T11) -> #REF! | Z13: =IF($P13="","",IF($Z$11="",0,'Inputs & Summary'!X11)) -> 0 | AA13: =IF($P13="","",IF($AA$11="",0,IF(AND(LivBen<>"None",RIGHT(Category,2)<>"NY"),'Inputs & Summary'!AH11,""))) -> 0 | AB13: =IF($P13="","",'Inputs & Summary'!Y11) -> #REF! | AC13: =IF($P13="","",IF(RIGHT(Category,2)="NY",'Inputs & Summary'!AH11,SUM('Inputs & Summary'!AB11,'Inputs & Summary'!AE11*('Inputs & Summary'!AD11="Yes"),'Inputs & Summary'!AG11))) -> 0 | AD13: =IF($P13="","",'Inputs & Summary'!AI11) -> 0 | AE13: =IF($P13="","",'Inputs & Summary'!Z11) -> 0 | AF13: =IF($P13="","",'Inputs & Summary'!U11) -> #REF! | AG13: =IF($P13="","",'Inputs & Summary'!V11) -> #REF! | AH13: =IF($P13="","",'Inputs & Summary'!W11) -> #REF! | AI13: =IF($P13="","",IF($AI$11="",0,'Inputs & Summary'!AM11)) -> #REF! | AJ13: =IF($P13="","",IF($AJ$11="",0,IF(PTab="P7",'Inputs & Summary'!AQ11,'Inputs & Summary'!AA11))) -> #REF! | AK13: =IF($P13="","",'Inputs & Summary'!AJ11) -> #REF!
B14: Solicitation State | C14: =IF(RIGHT(Product,2)="NY",'Inputs & Summary'!$C$37,State) -> KS | F14: =IF($E14="","",INDEX([1]STRTG!$T$14:$AC$303,MATCH($E14,[1]STRTG!$P$14:$P$303,0),MATCH(F$5,[1]STRTG!$T$13:$AC$13,0))) | G14: =IF($E14="","",INDEX([1]STRTG!$T$14:$AC$303,MATCH($E14,[1]STRTG!$P$14:$P$303,0),MATCH(G$5,[1]STRTG!$T$13:$AC$13,0))) | H14: =IF($E14="","",INDEX([1]STRTG!$T$14:$AC$303,MATCH($E14,[1]STRTG!$P$14:$P$303,0),MATCH(H$5,[1]STRTG!$T$13:$AC$13,0))) | I14: =IF($E14="","",INDEX([1]STRTG!$T$14:$AC$303,MATCH($E14,[1]STRTG!$P$14:$P$303,0),MATCH(I$5,[1]STRTG!$T$13:$AC$13,0))) | J14: =IF($E14="","",INDEX([1]STRTG!$T$14:$AC$303,MATCH($E14,[1]STRTG!$P$14:$P$303,0),MATCH(J$5,[1]STRTG!$T$13:$AC$13,0))) | K14: =IF($E14="","",IF(RIGHT(VLOOKUP($E14,[1]STRTG!$P$14:$S$303,4,FALSE),6)="EPRST1",Ref!$C$103,IF(RIGHT(VLOOKUP($E14,[1]STRTG!$P$14:$S$303,4,FALSE),6)="EPRST2",Ref!$C$104,"N/A"))) | L14: =IF($E14="","",INDEX([1]STRTG!$T$14:$AC$303,MATCH($E14,[1]STRTG!$P$14:$P$303,0),MATCH(L$5,[1]STRTG!$T$13:$AC$13,0))) | P14: =IF('Inputs & Summary'!O12="","",IF('Inputs & Summary'!O12=0,"At Issue",'Inputs & Summary'!P12)) -> #REF! | Q14: =IF($P14="","",'Inputs & Summary'!O12) -> #REF! | R14: =IF($P14="","",'Inputs & Summary'!Q12) -> #REF! | S14: {=IF($P14="","",IF(S$11="",0,IFERROR(INDEX(INDIRECT(S$6&VLOOKUP(Summary,Ref!$Y$13:$AC$18,3,FALSE)),MATCH(IF($P14="At Issue",VLOOKUP(Summary,Ref!$Y$13:$AC$18,2,FALSE),$P14),INDIRECT(S$6&VLOOKUP(Summary,Ref!$Y$13:$AC$18,4,FALSE)),0),VLOOKUP(S$10,Ref!$Y$61:$AA$63,2,FALSE)),0)))} -> #REF! | T14: {=IF($P14="","",IF(T$11="",0,IFERROR(INDEX(INDIRECT(T$6&VLOOKUP(Summary,Ref!$Y$13:$AC$18,3,FALSE)),MATCH(IF($P14="At Issue",VLOOKUP(Summary,Ref!$Y$13:$AC$18,2,FALSE),$P14),INDIRECT(T$6&VLOOKUP(Summary,Ref!$Y$13:$AC$18,4,FALSE)),0),VLOOKUP(T$10,Ref!$Y$61:$AA$63,2,FALSE)),0)))} -> #REF! | U14: {=IF($P14="","",IF(U$11="",0,IFERROR(INDEX(INDIRECT(U$6&VLOOKUP(Summary,Ref!$Y$13:$AC$18,3,FALSE)),MATCH(IF($P14="At Issue",VLOOKUP(Summary,Ref!$Y$13:$AC$18,2,FALSE),$P14),INDIRECT(U$6&VLOOKUP(Summary,Ref!$Y$13:$AC$18,4,FALSE)),0),VLOOKUP(U$10,Ref!$Y$61:$AA$63,2,FALSE)),0)))} -> #REF! | V14: {=IF($P14="","",IF(V$11="",0,IFERROR(INDEX(INDIRECT(V$6&VLOOKUP(Summary,Ref!$Y$13:$AC$18,3,FALSE)),MATCH(IF($P14="At Issue",VLOOKUP(Summary,Ref!$Y$13:$AC$18,2,FALSE),$P14),INDIRECT(V$6&VLOOKUP(Summary,Ref!$Y$13:$AC$18,4,FALSE)),0),VLOOKUP(V$10,Ref!$Y$61:$AA$63,2,FALSE)),0)))} -> #REF! | W14: {=IF($P14="","",IF(W$11="",0,IFERROR(INDEX(INDIRECT(W$6&VLOOKUP(Summary,Ref!$Y$13:$AC$18,3,FALSE)),MATCH(IF($P14="At Issue",VLOOKUP(Summary,Ref!$Y$13:$AC$18,2,FALSE),$P14),INDIRECT(W$6&VLOOKUP(Summary,Ref!$Y$13:$AC$18,4,FALSE)),0),VLOOKUP(W$10,Ref!$Y$61:$AA$63,2,FALSE)),0)))} -> #REF! | X14: =IF($P14="","",'Inputs & Summary'!S12) -> #REF! | Y14: =IF($P14="","",'Inputs & Summary'!T12) -> #REF! | Z14: =IF($P14="","",IF($Z$11="",0,'Inputs & Summary'!X12)) -> #REF! | AA14: =IF($P14="","",IF($AA$11="",0,IF(AND(LivBen<>"None",RIGHT(Category,2)<>"NY"),'Inputs & Summary'!AH12,""))) -> #REF! | AB14: =IF($P14="","",'Inputs & Summary'!Y12) -> #REF! | AC14: =IF($P14="","",IF(RIGHT(Category,2)="NY",'Inputs & Summary'!AH12,SUM('Inputs & Summary'!AB12,'Inputs & Summary'!AE12*('Inputs & Summary'!AD12="Yes"),'Inputs & Summary'!AG12))) -> #REF! | AD14: =IF($P14="","",'Inputs & Summary'!AI12) -> #REF! | AE14: =IF($P14="","",'Inputs & Summary'!Z12) -> #REF! | AF14: =IF($P14="","",'Inputs & Summary'!U12) -> #REF! | AG14: =IF($P14="","",'Inputs & Summary'!V12) -> #REF! | AH14: =IF($P14="","",'Inputs & Summary'!W12) -> #REF! | AI14: =IF($P14="","",IF($AI$11="",0,'Inputs & Summary'!AM12)) -> #REF! | AJ14: =IF($P14="","",IF($AJ$11="",0,IF(PTab="P7",'Inputs & Summary'!AQ12,'Inputs & Summary'!AA12))) -> #REF! | AK14: =IF($P14="","",'Inputs & Summary'!AJ12) -> #REF!
B15: Contract Type | C15: ='Inputs & Summary'!C39 -> Qualified | F15: =IF($E15="","",INDEX([1]STRTG!$T$14:$AC$303,MATCH($E15,[1]STRTG!$P$14:$P$303,0),MATCH(F$5,[1]STRTG!$T$13:$AC$13,0))) | G15: =IF($E15="","",INDEX([1]STRTG!$T$14:$AC$303,MATCH($E15,[1]STRTG!$P$14:$P$303,0),MATCH(G$5,[1]STRTG!$T$13:$AC$13,0))) | H15: =IF($E15="","",INDEX([1]STRTG!$T$14:$AC$303,MATCH($E15,[1]STRTG!$P$14:$P$303,0),MATCH(H$5,[1]STRTG!$T$13:$AC$13,0))) | I15: =IF($E15="","",INDEX([1]STRTG!$T$14:$AC$303,MATCH($E15,[1]STRTG!$P$14:$P$303,0),MATCH(I$5,[1]STRTG!$T$13:$AC$13,0))) | J15: =IF($E15="","",INDEX([1]STRTG!$T$14:$AC$303,MATCH($E15,[1]STRTG!$P$14:$P$303,0),MATCH(J$5,[1]STRTG!$T$13:$AC$13,0))) | K15: =IF($E15="","",IF(RIGHT(VLOOKUP($E15,[1]STRTG!$P$14:$S$303,4,FALSE),6)="EPRST1",Ref!$C$103,IF(RIGHT(VLOOKUP($E15,[1]STRTG!$P$14:$S$303,4,FALSE),6)="EPRST2",Ref!$C$104,"N/A"))) | L15: =IF($E15="","",INDEX([1]STRTG!$T$14:$AC$303,MATCH($E15,[1]STRTG!$P$14:$P$303,0),MATCH(L$5,[1]STRTG!$T$13:$AC$13,0))) | P15: =IF('Inputs & Summary'!O13="","",IF('Inputs & Summary'!O13=0,"At Issue",'Inputs & Summary'!P13)) -> #REF! | Q15: =IF($P15="","",'Inputs & Summary'!O13) -> #REF! | R15: =IF($P15="","",'Inputs & Summary'!Q13) -> #REF! | S15: {=IF($P15="","",IF(S$11="",0,IFERROR(INDEX(INDIRECT(S$6&VLOOKUP(Summary,Ref!$Y$13:$AC$18,3,FALSE)),MATCH(IF($P15="At Issue",VLOOKUP(Summary,Ref!$Y$13:$AC$18,2,FALSE),$P15),INDIRECT(S$6&VLOOKUP(Summary,Ref!$Y$13:$AC$18,4,FALSE)),0),VLOOKUP(S$10,Ref!$Y$61:$AA$63,2,FALSE)),0)))} -> #REF! | T15: {=IF($P15="","",IF(T$11="",0,IFERROR(INDEX(INDIRECT(T$6&VLOOKUP(Summary,Ref!$Y$13:$AC$18,3,FALSE)),MATCH(IF($P15="At Issue",VLOOKUP(Summary,Ref!$Y$13:$AC$18,2,FALSE),$P15),INDIRECT(T$6&VLOOKUP(Summary,Ref!$Y$13:$AC$18,4,FALSE)),0),VLOOKUP(T$10,Ref!$Y$61:$AA$63,2,FALSE)),0)))} -> #REF! | U15: {=IF($P15="","",IF(U$11="",0,IFERROR(INDEX(INDIRECT(U$6&VLOOKUP(Summary,Ref!$Y$13:$AC$18,3,FALSE)),MATCH(IF($P15="At Issue",VLOOKUP(Summary,Ref!$Y$13:$AC$18,2,FALSE),$P15),INDIRECT(U$6&VLOOKUP(Summary,Ref!$Y$13:$AC$18,4,FALSE)),0),VLOOKUP(U$10,Ref!$Y$61:$AA$63,2,FALSE)),0)))} -> #REF! | V15: {=IF($P15="","",IF(V$11="",0,IFERROR(INDEX(INDIRECT(V$6&VLOOKUP(Summary,Ref!$Y$13:$AC$18,3,FALSE)),MATCH(IF($P15="At Issue",VLOOKUP(Summary,Ref!$Y$13:$AC$18,2,FALSE),$P15),INDIRECT(V$6&VLOOKUP(Summary,Ref!$Y$13:$AC$18,4,FALSE)),0),VLOOKUP(V$10,Ref!$Y$61:$AA$63,2,FALSE)),0)))} -> #REF! | W15: {=IF($P15="","",IF(W$11="",0,IFERROR(INDEX(INDIRECT(W$6&VLOOKUP(Summary,Ref!$Y$13:$AC$18,3,FALSE)),MATCH(IF($P15="At Issue",VLOOKUP(Summary,Ref!$Y$13:$AC$18,2,FALSE),$P15),INDIRECT(W$6&VLOOKUP(Summary,Ref!$Y$13:$AC$18,4,FALSE)),0),VLOOKUP(W$10,Ref!$Y$61:$AA$63,2,FALSE)),0)))} -> #REF! | X15: =IF($P15="","",'Inputs & Summary'!S13) -> #REF! | Y15: =IF($P15="","",'Inputs & Summary'!T13) -> #REF! | Z15: =IF($P15="","",IF($Z$11="",0,'Inputs & Summary'!X13)) -> #REF! | AA15: =IF($P15="","",IF($AA$11="",0,IF(AND(LivBen<>"None",RIGHT(Category,2)<>"NY"),'Inputs & Summary'!AH13,""))) -> #REF! | AB15: =IF($P15="","",'Inputs & Summary'!Y13) -> #REF! | AC15: =IF($P15="","",IF(RIGHT(Category,2)="NY",'Inputs & Summary'!AH13,SUM('Inputs & Summary'!AB13,'Inputs & Summary'!AE13*('Inputs & Summary'!AD13="Yes"),'Inputs & Summary'!AG13))) -> #REF! | AD15: =IF($P15="","",'Inputs & Summary'!AI13) -> #REF! | AE15: =IF($P15="","",'Inputs & Summary'!Z13) -> #REF! | AF15: =IF($P15="","",'Inputs & Summary'!U13) -> #REF! | AG15: =IF($P15="","",'Inputs & Summary'!V13) -> #REF! | AH15: =IF($P15="","",'Inputs & Summary'!W13) -> #REF! | AI15: =IF($P15="","",IF($AI$11="",0,'Inputs & Summary'!AM13)) -> #REF! | AJ15: =IF($P15="","",IF($AJ$11="",0,IF(PTab="P7",'Inputs & Summary'!AQ13,'Inputs & Summary'!AA13))) -> #REF! | AK15: =IF($P15="","",'Inputs & Summary'!AJ13) -> #REF!
B16: Product | C16: =Product -> Power Index Plus | F16: =IF($E16="","",INDEX([1]STRTG!$T$14:$AC$303,MATCH($E16,[1]STRTG!$P$14:$P$303,0),MATCH(F$5,[1]STRTG!$T$13:$AC$13,0))) | G16: =IF($E16="","",INDEX([1]STRTG!$T$14:$AC$303,MATCH($E16,[1]STRTG!$P$14:$P$303,0),MATCH(G$5,[1]STRTG!$T$13:$AC$13,0))) | H16: =IF($E16="","",INDEX([1]STRTG!$T$14:$AC$303,MATCH($E16,[1]STRTG!$P$14:$P$303,0),MATCH(H$5,[1]STRTG!$T$13:$AC$13,0))) | I16: =IF($E16="","",INDEX([1]STRTG!$T$14:$AC$303,MATCH($E16,[1]STRTG!$P$14:$P$303,0),MATCH(I$5,[1]STRTG!$T$13:$AC$13,0))) | J16: =IF($E16="","",INDEX([1]STRTG!$T$14:$AC$303,MATCH($E16,[1]STRTG!$P$14:$P$303,0),MATCH(J$5,[1]STRTG!$T$13:$AC$13,0))) | K16: =IF($E16="","",IF(RIGHT(VLOOKUP($E16,[1]STRTG!$P$14:$S$303,4,FALSE),6)="EPRST1",Ref!$C$103,IF(RIGHT(VLOOKUP($E16,[1]STRTG!$P$14:$S$303,4,FALSE),6)="EPRST2",Ref!$C$104,"N/A"))) | L16: =IF($E16="","",INDEX([1]STRTG!$T$14:$AC$303,MATCH($E16,[1]STRTG!$P$14:$P$303,0),MATCH(L$5,[1]STRTG!$T$13:$AC$13,0))) | P16: =IF('Inputs & Summary'!O14="","",IF('Inputs & Summary'!O14=0,"At Issue",'Inputs & Summary'!P14)) -> #REF! | Q16: =IF($P16="","",'Inputs & Summary'!O14) -> #REF! | R16: =IF($P16="","",'Inputs & Summary'!Q14) -> #REF! | S16: {=IF($P16="","",IF(S$11="",0,IFERROR(INDEX(INDIRECT(S$6&VLOOKUP(Summary,Ref!$Y$13:$AC$18,3,FALSE)),MATCH(IF($P16="At Issue",VLOOKUP(Summary,Ref!$Y$13:$AC$18,2,FALSE),$P16),INDIRECT(S$6&VLOOKUP(Summary,Ref!$Y$13:$AC$18,4,FALSE)),0),VLOOKUP(S$10,Ref!$Y$61:$AA$63,2,FALSE)),0)))} -> #REF! | T16: {=IF($P16="","",IF(T$11="",0,IFERROR(INDEX(INDIRECT(T$6&VLOOKUP(Summary,Ref!$Y$13:$AC$18,3,FALSE)),MATCH(IF($P16="At Issue",VLOOKUP(Summary,Ref!$Y$13:$AC$18,2,FALSE),$P16),INDIRECT(T$6&VLOOKUP(Summary,Ref!$Y$13:$AC$18,4,FALSE)),0),VLOOKUP(T$10,Ref!$Y$61:$AA$63,2,FALSE)),0)))} -> #REF! | U16: {=IF($P16="","",IF(U$11="",0,IFERROR(INDEX(INDIRECT(U$6&VLOOKUP(Summary,Ref!$Y$13:$AC$18,3,FALSE)),MATCH(IF($P16="At Issue",VLOOKUP(Summary,Ref!$Y$13:$AC$18,2,FALSE),$P16),INDIRECT(U$6&VLOOKUP(Summary,Ref!$Y$13:$AC$18,4,FALSE)),0),VLOOKUP(U$10,Ref!$Y$61:$AA$63,2,FALSE)),0)))} -> #REF! | V16: {=IF($P16="","",IF(V$11="",0,IFERROR(INDEX(INDIRECT(V$6&VLOOKUP(Summary,Ref!$Y$13:$AC$18,3,FALSE)),MATCH(IF($P16="At Issue",VLOOKUP(Summary,Ref!$Y$13:$AC$18,2,FALSE),$P16),INDIRECT(V$6&VLOOKUP(Summary,Ref!$Y$13:$AC$18,4,FALSE)),0),VLOOKUP(V$10,Ref!$Y$61:$AA$63,2,FALSE)),0)))} -> #REF! | W16: {=IF($P16="","",IF(W$11="",0,IFERROR(INDEX(INDIRECT(W$6&VLOOKUP(Summary,Ref!$Y$13:$AC$18,3,FALSE)),MATCH(IF($P16="At Issue",VLOOKUP(Summary,Ref!$Y$13:$AC$18,2,FALSE),$P16),INDIRECT(W$6&VLOOKUP(Summary,Ref!$Y$13:$AC$18,4,FALSE)),0),VLOOKUP(W$10,Ref!$Y$61:$AA$63,2,FALSE)),0)))} -> #REF! | X16: =IF($P16="","",'Inputs & Summary'!S14) -> #REF! | Y16: =IF($P16="","",'Inputs & Summary'!T14) -> #REF! | Z16: =IF($P16="","",IF($Z$11="",0,'Inputs & Summary'!X14)) -> #REF! | AA16: =IF($P16="","",IF($AA$11="",0,IF(AND(LivBen<>"None",RIGHT(Category,2)<>"NY"),'Inputs & Summary'!AH14,""))) -> #REF! | AB16: =IF($P16="","",'Inputs & Summary'!Y14) -> #REF! | AC16: =IF($P16="","",IF(RIGHT(Category,2)="NY",'Inputs & Summary'!AH14,SUM('Inputs & Summary'!AB14,'Inputs & Summary'!AE14*('Inputs & Summary'!AD14="Yes"),'Inputs & Summary'!AG14))) -> #REF! | AD16: =IF($P16="","",'Inputs & Summary'!AI14) -> #REF! | AE16: =IF($P16="","",'Inputs & Summary'!Z14) -> #REF! | AF16: =IF($P16="","",'Inputs & Summary'!U14) -> #REF! | AG16: =IF($P16="","",'Inputs & Summary'!V14) -> #REF! | AH16: =IF($P16="","",'Inputs & Summary'!W14) -> #REF! | AI16: =IF($P16="","",IF($AI$11="",0,'Inputs & Summary'!AM14)) -> #REF! | AJ16: =IF($P16="","",IF($AJ$11="",0,IF(PTab="P7",'Inputs & Summary'!AQ14,'Inputs & Summary'!AA14))) -> #REF! | AK16: =IF($P16="","",'Inputs & Summary'!AJ14) -> #REF!
B17: Initial Premium | C17: =InPrem -> 10000 | F17: =IF($E17="","",INDEX([1]STRTG!$T$14:$AC$303,MATCH($E17,[1]STRTG!$P$14:$P$303,0),MATCH(F$5,[1]STRTG!$T$13:$AC$13,0))) | G17: =IF($E17="","",INDEX([1]STRTG!$T$14:$AC$303,MATCH($E17,[1]STRTG!$P$14:$P$303,0),MATCH(G$5,[1]STRTG!$T$13:$AC$13,0))) | H17: =IF($E17="","",INDEX([1]STRTG!$T$14:$AC$303,MATCH($E17,[1]STRTG!$P$14:$P$303,0),MATCH(H$5,[1]STRTG!$T$13:$AC$13,0))) | I17: =IF($E17="","",INDEX([1]STRTG!$T$14:$AC$303,MATCH($E17,[1]STRTG!$P$14:$P$303,0),MATCH(I$5,[1]STRTG!$T$13:$AC$13,0))) | J17: =IF($E17="","",INDEX([1]STRTG!$T$14:$AC$303,MATCH($E17,[1]STRTG!$P$14:$P$303,0),MATCH(J$5,[1]STRTG!$T$13:$AC$13,0))) | K17: =IF($E17="","",IF(RIGHT(VLOOKUP($E17,[1]STRTG!$P$14:$S$303,4,FALSE),6)="EPRST1",Ref!$C$103,IF(RIGHT(VLOOKUP($E17,[1]STRTG!$P$14:$S$303,4,FALSE),6)="EPRST2",Ref!$C$104,"N/A"))) | L17: =IF($E17="","",INDEX([1]STRTG!$T$14:$AC$303,MATCH($E17,[1]STRTG!$P$14:$P$303,0),MATCH(L$5,[1]STRTG!$T$13:$AC$13,0))) | P17: =IF('Inputs & Summary'!O15="","",IF('Inputs & Summary'!O15=0,"At Issue",'Inputs & Summary'!P15)) -> #REF! | Q17: =IF($P17="","",'Inputs & Summary'!O15) -> #REF! | R17: =IF($P17="","",'Inputs & Summary'!Q15) -> #REF! | S17: {=IF($P17="","",IF(S$11="",0,IFERROR(INDEX(INDIRECT(S$6&VLOOKUP(Summary,Ref!$Y$13:$AC$18,3,FALSE)),MATCH(IF($P17="At Issue",VLOOKUP(Summary,Ref!$Y$13:$AC$18,2,FALSE),$P17),INDIRECT(S$6&VLOOKUP(Summary,Ref!$Y$13:$AC$18,4,FALSE)),0),VLOOKUP(S$10,Ref!$Y$61:$AA$63,2,FALSE)),0)))} -> #REF! | T17: {=IF($P17="","",IF(T$11="",0,IFERROR(INDEX(INDIRECT(T$6&VLOOKUP(Summary,Ref!$Y$13:$AC$18,3,FALSE)),MATCH(IF($P17="At Issue",VLOOKUP(Summary,Ref!$Y$13:$AC$18,2,FALSE),$P17),INDIRECT(T$6&VLOOKUP(Summary,Ref!$Y$13:$AC$18,4,FALSE)),0),VLOOKUP(T$10,Ref!$Y$61:$AA$63,2,FALSE)),0)))} -> #REF! | U17: {=IF($P17="","",IF(U$11="",0,IFERROR(INDEX(INDIRECT(U$6&VLOOKUP(Summary,Ref!$Y$13:$AC$18,3,FALSE)),MATCH(IF($P17="At Issue",VLOOKUP(Summary,Ref!$Y$13:$AC$18,2,FALSE),$P17),INDIRECT(U$6&VLOOKUP(Summary,Ref!$Y$13:$AC$18,4,FALSE)),0),VLOOKUP(U$10,Ref!$Y$61:$AA$63,2,FALSE)),0)))} -> #REF! | V17: {=IF($P17="","",IF(V$11="",0,IFERROR(INDEX(INDIRECT(V$6&VLOOKUP(Summary,Ref!$Y$13:$AC$18,3,FALSE)),MATCH(IF($P17="At Issue",VLOOKUP(Summary,Ref!$Y$13:$AC$18,2,FALSE),$P17),INDIRECT(V$6&VLOOKUP(Summary,Ref!$Y$13:$AC$18,4,FALSE)),0),VLOOKUP(V$10,Ref!$Y$61:$AA$63,2,FALSE)),0)))} -> #REF! | W17: {=IF($P17="","",IF(W$11="",0,IFERROR(INDEX(INDIRECT(W$6&VLOOKUP(Summary,Ref!$Y$13:$AC$18,3,FALSE)),MATCH(IF($P17="At Issue",VLOOKUP(Summary,Ref!$Y$13:$AC$18,2,FALSE),$P17),INDIRECT(W$6&VLOOKUP(Summary,Ref!$Y$13:$AC$18,4,FALSE)),0),VLOOKUP(W$10,Ref!$Y$61:$AA$63,2,FALSE)),0)))} -> #REF! | X17: =IF($P17="","",'Inputs & Summary'!S15) -> #REF! | Y17: =IF($P17="","",'Inputs & Summary'!T15) -> #REF! | Z17: =IF($P17="","",IF($Z$11="",0,'Inputs & Summary'!X15)) -> #REF! | AA17: =IF($P17="","",IF($AA$11="",0,IF(AND(LivBen<>"None",RIGHT(Category,2)<>"NY"),'Inputs & Summary'!AH15,""))) -> #REF! | AB17: =IF($P17="","",'Inputs & Summary'!Y15) -> #REF! | AC17: =IF($P17="","",IF(RIGHT(Category,2)="NY",'Inputs & Summary'!AH15,SUM('Inputs & Summary'!AB15,'Inputs & Summary'!AE15*('Inputs & Summary'!AD15="Yes"),'Inputs & Summary'!AG15))) -> #REF! | AD17: =IF($P17="","",'Inputs & Summary'!AI15) -> #REF! | AE17: =IF($P17="","",'Inputs & Summary'!Z15) -> #REF! | AF17: =IF($P17="","",'Inputs & Summary'!U15) -> #REF! | AG17: =IF($P17="","",'Inputs & Summary'!V15) -> #REF! | AH17: =IF($P17="","",'Inputs & Summary'!W15) -> #REF! | AI17: =IF($P17="","",IF($AI$11="",0,'Inputs & Summary'!AM15)) -> #REF! | AJ17: =IF($P17="","",IF($AJ$11="",0,IF(PTab="P7",'Inputs & Summary'!AQ15,'Inputs & Summary'!AA15))) -> #REF! | AK17: =IF($P17="","",'Inputs & Summary'!AJ15) -> #REF!
B18: Death Benefit | C18: =IF(PTab="P7","Return of Premium","Contract Value") -> Contract Value | F18: =IF($E18="","",INDEX([1]STRTG!$T$14:$AC$303,MATCH($E18,[1]STRTG!$P$14:$P$303,0),MATCH(F$5,[1]STRTG!$T$13:$AC$13,0))) | G18: =IF($E18="","",INDEX([1]STRTG!$T$14:$AC$303,MATCH($E18,[1]STRTG!$P$14:$P$303,0),MATCH(G$5,[1]STRTG!$T$13:$AC$13,0))) | H18: =IF($E18="","",INDEX([1]STRTG!$T$14:$AC$303,MATCH($E18,[1]STRTG!$P$14:$P$303,0),MATCH(H$5,[1]STRTG!$T$13:$AC$13,0))) | I18: =IF($E18="","",INDEX([1]STRTG!$T$14:$AC$303,MATCH($E18,[1]STRTG!$P$14:$P$303,0),MATCH(I$5,[1]STRTG!$T$13:$AC$13,0))) | J18: =IF($E18="","",INDEX([1]STRTG!$T$14:$AC$303,MATCH($E18,[1]STRTG!$P$14:$P$303,0),MATCH(J$5,[1]STRTG!$T$13:$AC$13,0))) | K18: =IF($E18="","",IF(RIGHT(VLOOKUP($E18,[1]STRTG!$P$14:$S$303,4,FALSE),6)="EPRST1",Ref!$C$103,IF(RIGHT(VLOOKUP($E18,[1]STRTG!$P$14:$S$303,4,FALSE),6)="EPRST2",Ref!$C$104,"N/A"))) | L18: =IF($E18="","",INDEX([1]STRTG!$T$14:$AC$303,MATCH($E18,[1]STRTG!$P$14:$P$303,0),MATCH(L$5,[1]STRTG!$T$13:$AC$13,0))) | P18: =IF('Inputs & Summary'!O16="","",IF('Inputs & Summary'!O16=0,"At Issue",'Inputs & Summary'!P16)) -> #REF! | Q18: =IF($P18="","",'Inputs & Summary'!O16) -> #REF! | R18: =IF($P18="","",'Inputs & Summary'!Q16) -> #REF! | S18: {=IF($P18="","",IF(S$11="",0,IFERROR(INDEX(INDIRECT(S$6&VLOOKUP(Summary,Ref!$Y$13:$AC$18,3,FALSE)),MATCH(IF($P18="At Issue",VLOOKUP(Summary,Ref!$Y$13:$AC$18,2,FALSE),$P18),INDIRECT(S$6&VLOOKUP(Summary,Ref!$Y$13:$AC$18,4,FALSE)),0),VLOOKUP(S$10,Ref!$Y$61:$AA$63,2,FALSE)),0)))} -> #REF! | T18: {=IF($P18="","",IF(T$11="",0,IFERROR(INDEX(INDIRECT(T$6&VLOOKUP(Summary,Ref!$Y$13:$AC$18,3,FALSE)),MATCH(IF($P18="At Issue",VLOOKUP(Summary,Ref!$Y$13:$AC$18,2,FALSE),$P18),INDIRECT(T$6&VLOOKUP(Summary,Ref!$Y$13:$AC$18,4,FALSE)),0),VLOOKUP(T$10,Ref!$Y$61:$AA$63,2,FALSE)),0)))} -> #REF! | U18: {=IF($P18="","",IF(U$11="",0,IFERROR(INDEX(INDIRECT(U$6&VLOOKUP(Summary,Ref!$Y$13:$AC$18,3,FALSE)),MATCH(IF($P18="At Issue",VLOOKUP(Summary,Ref!$Y$13:$AC$18,2,FALSE),$P18),INDIRECT(U$6&VLOOKUP(Summary,Ref!$Y$13:$AC$18,4,FALSE)),0),VLOOKUP(U$10,Ref!$Y$61:$AA$63,2,FALSE)),0)))} -> #REF! | V18: {=IF($P18="","",IF(V$11="",0,IFERROR(INDEX(INDIRECT(V$6&VLOOKUP(Summary,Ref!$Y$13:$AC$18,3,FALSE)),MATCH(IF($P18="At Issue",VLOOKUP(Summary,Ref!$Y$13:$AC$18,2,FALSE),$P18),INDIRECT(V$6&VLOOKUP(Summary,Ref!$Y$13:$AC$18,4,FALSE)),0),VLOOKUP(V$10,Ref!$Y$61:$AA$63,2,FALSE)),0)))} -> #REF! | W18: {=IF($P18="","",IF(W$11="",0,IFERROR(INDEX(INDIRECT(W$6&VLOOKUP(Summary,Ref!$Y$13:$AC$18,3,FALSE)),MATCH(IF($P18="At Issue",VLOOKUP(Summary,Ref!$Y$13:$AC$18,2,FALSE),$P18),INDIRECT(W$6&VLOOKUP(Summary,Ref!$Y$13:$AC$18,4,FALSE)),0),VLOOKUP(W$10,Ref!$Y$61:$AA$63,2,FALSE)),0)))} -> #REF! | X18: =IF($P18="","",'Inputs & Summary'!S16) -> #REF! | Y18: =IF($P18="","",'Inputs & Summary'!T16) -> #REF! | Z18: =IF($P18="","",IF($Z$11="",0,'Inputs & Summary'!X16)) -> #REF! | AA18: =IF($P18="","",IF($AA$11="",0,IF(AND(LivBen<>"None",RIGHT(Category,2)<>"NY"),'Inputs & Summary'!AH16,""))) -> #REF! | AB18: =IF($P18="","",'Inputs & Summary'!Y16) -> #REF! | AC18: =IF($P18="","",IF(RIGHT(Category,2)="NY",'Inputs & Summary'!AH16,SUM('Inputs & Summary'!AB16,'Inputs & Summary'!AE16*('Inputs & Summary'!AD16="Yes"),'Inputs & Summary'!AG16))) -> #REF! | AD18: =IF($P18="","",'Inputs & Summary'!AI16) -> #REF! | AE18: =IF($P18="","",'Inputs & Summary'!Z16) -> #REF! | AF18: =IF($P18="","",'Inputs & Summary'!U16) -> #REF! | AG18: =IF($P18="","",'Inputs & Summary'!V16) -> #REF! | AH18: =IF($P18="","",'Inputs & Summary'!W16) -> #REF! | AI18: =IF($P18="","",IF($AI$11="",0,'Inputs & Summary'!AM16)) -> #REF! | AJ18: =IF($P18="","",IF($AJ$11="",0,IF(PTab="P7",'Inputs & Summary'!AQ16,'Inputs & Summary'!AA16))) -> #REF! | AK18: =IF($P18="","",'Inputs & Summary'!AJ16) -> #REF!
B19: =IF(PTab="P7","AICO Product Fee",IF(Ref!$S$53="Y","GMAB Rate","")) -> GMAB Rate | C19: =IF(PTab="P7",AICOPrFee,IF(Ref!$S$53="Y",GMABR,"")) -> 0.05 | F19: =IF($E19="","",INDEX([1]STRTG!$T$14:$AC$303,MATCH($E19,[1]STRTG!$P$14:$P$303,0),MATCH(F$5,[1]STRTG!$T$13:$AC$13,0))) | G19: =IF($E19="","",INDEX([1]STRTG!$T$14:$AC$303,MATCH($E19,[1]STRTG!$P$14:$P$303,0),MATCH(G$5,[1]STRTG!$T$13:$AC$13,0))) | H19: =IF($E19="","",INDEX([1]STRTG!$T$14:$AC$303,MATCH($E19,[1]STRTG!$P$14:$P$303,0),MATCH(H$5,[1]STRTG!$T$13:$AC$13,0))) | I19: =IF($E19="","",INDEX([1]STRTG!$T$14:$AC$303,MATCH($E19,[1]STRTG!$P$14:$P$303,0),MATCH(I$5,[1]STRTG!$T$13:$AC$13,0))) | J19: =IF($E19="","",INDEX([1]STRTG!$T$14:$AC$303,MATCH($E19,[1]STRTG!$P$14:$P$303,0),MATCH(J$5,[1]STRTG!$T$13:$AC$13,0))) | K19: =IF($E19="","",IF(RIGHT(VLOOKUP($E19,[1]STRTG!$P$14:$S$303,4,FALSE),6)="EPRST1",Ref!$C$103,IF(RIGHT(VLOOKUP($E19,[1]STRTG!$P$14:$S$303,4,FALSE),6)="EPRST2",Ref!$C$104,"N/A"))) | L19: =IF($E19="","",INDEX([1]STRTG!$T$14:$AC$303,MATCH($E19,[1]STRTG!$P$14:$P$303,0),MATCH(L$5,[1]STRTG!$T$13:$AC$13,0))) | P19: =IF('Inputs & Summary'!O17="","",IF('Inputs & Summary'!O17=0,"At Issue",'Inputs & Summary'!P17)) -> #REF! | Q19: =IF($P19="","",'Inputs & Summary'!O17) -> #REF! | R19: =IF($P19="","",'Inputs & Summary'!Q17) -> #REF! | S19: {=IF($P19="","",IF(S$11="",0,IFERROR(INDEX(INDIRECT(S$6&VLOOKUP(Summary,Ref!$Y$13:$AC$18,3,FALSE)),MATCH(IF($P19="At Issue",VLOOKUP(Summary,Ref!$Y$13:$AC$18,2,FALSE),$P19),INDIRECT(S$6&VLOOKUP(Summary,Ref!$Y$13:$AC$18,4,FALSE)),0),VLOOKUP(S$10,Ref!$Y$61:$AA$63,2,FALSE)),0)))} -> #REF! | T19: {=IF($P19="","",IF(T$11="",0,IFERROR(INDEX(INDIRECT(T$6&VLOOKUP(Summary,Ref!$Y$13:$AC$18,3,FALSE)),MATCH(IF($P19="At Issue",VLOOKUP(Summary,Ref!$Y$13:$AC$18,2,FALSE),$P19),INDIRECT(T$6&VLOOKUP(Summary,Ref!$Y$13:$AC$18,4,FALSE)),0),VLOOKUP(T$10,Ref!$Y$61:$AA$63,2,FALSE)),0)))} -> #REF! | U19: {=IF($P19="","",IF(U$11="",0,IFERROR(INDEX(INDIRECT(U$6&VLOOKUP(Summary,Ref!$Y$13:$AC$18,3,FALSE)),MATCH(IF($P19="At Issue",VLOOKUP(Summary,Ref!$Y$13:$AC$18,2,FALSE),$P19),INDIRECT(U$6&VLOOKUP(Summary,Ref!$Y$13:$AC$18,4,FALSE)),0),VLOOKUP(U$10,Ref!$Y$61:$AA$63,2,FALSE)),0)))} -> #REF! | V19: {=IF($P19="","",IF(V$11="",0,IFERROR(INDEX(INDIRECT(V$6&VLOOKUP(Summary,Ref!$Y$13:$AC$18,3,FALSE)),MATCH(IF($P19="At Issue",VLOOKUP(Summary,Ref!$Y$13:$AC$18,2,FALSE),$P19),INDIRECT(V$6&VLOOKUP(Summary,Ref!$Y$13:$AC$18,4,FALSE)),0),VLOOKUP(V$10,Ref!$Y$61:$AA$63,2,FALSE)),0)))} -> #REF! | W19: {=IF($P19="","",IF(W$11="",0,IFERROR(INDEX(INDIRECT(W$6&VLOOKUP(Summary,Ref!$Y$13:$AC$18,3,FALSE)),MATCH(IF($P19="At Issue",VLOOKUP(Summary,Ref!$Y$13:$AC$18,2,FALSE),$P19),INDIRECT(W$6&VLOOKUP(Summary,Ref!$Y$13:$AC$18,4,FALSE)),0),VLOOKUP(W$10,Ref!$Y$61:$AA$63,2,FALSE)),0)))} -> #REF! | X19: =IF($P19="","",'Inputs & Summary'!S17) -> #REF! | Y19: =IF($P19="","",'Inputs & Summary'!T17) -> #REF! | Z19: =IF($P19="","",IF($Z$11="",0,'Inputs & Summary'!X17)) -> #REF! | AA19: =IF($P19="","",IF($AA$11="",0,IF(AND(LivBen<>"None",RIGHT(Category,2)<>"NY"),'Inputs & Summary'!AH17,""))) -> #REF! | AB19: =IF($P19="","",'Inputs & Summary'!Y17) -> #REF! | AC19: =IF($P19="","",IF(RIGHT(Category,2)="NY",'Inputs & Summary'!AH17,SUM('Inputs & Summary'!AB17,'Inputs & Summary'!AE17*('Inputs & Summary'!AD17="Yes"),'Inputs & Summary'!AG17))) -> #REF! | AD19: =IF($P19="","",'Inputs & Summary'!AI17) -> #REF! | AE19: =IF($P19="","",'Inputs & Summary'!Z17) -> #REF! | AF19: =IF($P19="","",'Inputs & Summary'!U17) -> #REF! | AG19: =IF($P19="","",'Inputs & Summary'!V17) -> #REF! | AH19: =IF($P19="","",'Inputs & Summary'!W17) -> #REF! | AI19: =IF($P19="","",IF($AI$11="",0,'Inputs & Summary'!AM17)) -> #REF! | AJ19: =IF($P19="","",IF($AJ$11="",0,IF(PTab="P7",'Inputs & Summary'!AQ17,'Inputs & Summary'!AA17))) -> #REF! | AK19: =IF($P19="","",'Inputs & Summary'!AJ17) -> #REF!
B20: =IF(PTab="P7","AICO Multiplier Rate",IF(Ref!$S$53="Y","GMAB Cadence","")) -> GMAB Cadence | C20: =IF(PTab="P7",OMR,IF(Ref!$S$53="Y",GMABC,"")) -> CDSC | F20: =IF($E20="","",INDEX([1]STRTG!$T$14:$AC$303,MATCH($E20,[1]STRTG!$P$14:$P$303,0),MATCH(F$5,[1]STRTG!$T$13:$AC$13,0))) | G20: =IF($E20="","",INDEX([1]STRTG!$T$14:$AC$303,MATCH($E20,[1]STRTG!$P$14:$P$303,0),MATCH(G$5,[1]STRTG!$T$13:$AC$13,0))) | H20: =IF($E20="","",INDEX([1]STRTG!$T$14:$AC$303,MATCH($E20,[1]STRTG!$P$14:$P$303,0),MATCH(H$5,[1]STRTG!$T$13:$AC$13,0))) | I20: =IF($E20="","",INDEX([1]STRTG!$T$14:$AC$303,MATCH($E20,[1]STRTG!$P$14:$P$303,0),MATCH(I$5,[1]STRTG!$T$13:$AC$13,0))) | J20: =IF($E20="","",INDEX([1]STRTG!$T$14:$AC$303,MATCH($E20,[1]STRTG!$P$14:$P$303,0),MATCH(J$5,[1]STRTG!$T$13:$AC$13,0))) | K20: =IF($E20="","",IF(RIGHT(VLOOKUP($E20,[1]STRTG!$P$14:$S$303,4,FALSE),6)="EPRST1",Ref!$C$103,IF(RIGHT(VLOOKUP($E20,[1]STRTG!$P$14:$S$303,4,FALSE),6)="EPRST2",Ref!$C$104,"N/A"))) | L20: =IF($E20="","",INDEX([1]STRTG!$T$14:$AC$303,MATCH($E20,[1]STRTG!$P$14:$P$303,0),MATCH(L$5,[1]STRTG!$T$13:$AC$13,0))) | P20: =IF('Inputs & Summary'!O18="","",IF('Inputs & Summary'!O18=0,"At Issue",'Inputs & Summary'!P18)) -> #REF! | Q20: =IF($P20="","",'Inputs & Summary'!O18) -> #REF! | R20: =IF($P20="","",'Inputs & Summary'!Q18) -> #REF! | S20: {=IF($P20="","",IF(S$11="",0,IFERROR(INDEX(INDIRECT(S$6&VLOOKUP(Summary,Ref!$Y$13:$AC$18,3,FALSE)),MATCH(IF($P20="At Issue",VLOOKUP(Summary,Ref!$Y$13:$AC$18,2,FALSE),$P20),INDIRECT(S$6&VLOOKUP(Summary,Ref!$Y$13:$AC$18,4,FALSE)),0),VLOOKUP(S$10,Ref!$Y$61:$AA$63,2,FALSE)),0)))} -> #REF! | T20: {=IF($P20="","",IF(T$11="",0,IFERROR(INDEX(INDIRECT(T$6&VLOOKUP(Summary,Ref!$Y$13:$AC$18,3,FALSE)),MATCH(IF($P20="At Issue",VLOOKUP(Summary,Ref!$Y$13:$AC$18,2,FALSE),$P20),INDIRECT(T$6&VLOOKUP(Summary,Ref!$Y$13:$AC$18,4,FALSE)),0),VLOOKUP(T$10,Ref!$Y$61:$AA$63,2,FALSE)),0)))} -> #REF! | U20: {=IF($P20="","",IF(U$11="",0,IFERROR(INDEX(INDIRECT(U$6&VLOOKUP(Summary,Ref!$Y$13:$AC$18,3,FALSE)),MATCH(IF($P20="At Issue",VLOOKUP(Summary,Ref!$Y$13:$AC$18,2,FALSE),$P20),INDIRECT(U$6&VLOOKUP(Summary,Ref!$Y$13:$AC$18,4,FALSE)),0),VLOOKUP(U$10,Ref!$Y$61:$AA$63,2,FALSE)),0)))} -> #REF! | V20: {=IF($P20="","",IF(V$11="",0,IFERROR(INDEX(INDIRECT(V$6&VLOOKUP(Summary,Ref!$Y$13:$AC$18,3,FALSE)),MATCH(IF($P20="At Issue",VLOOKUP(Summary,Ref!$Y$13:$AC$18,2,FALSE),$P20),INDIRECT(V$6&VLOOKUP(Summary,Ref!$Y$13:$AC$18,4,FALSE)),0),VLOOKUP(V$10,Ref!$Y$61:$AA$63,2,FALSE)),0)))} -> #REF! | W20: {=IF($P20="","",IF(W$11="",0,IFERROR(INDEX(INDIRECT(W$6&VLOOKUP(Summary,Ref!$Y$13:$AC$18,3,FALSE)),MATCH(IF($P20="At Issue",VLOOKUP(Summary,Ref!$Y$13:$AC$18,2,FALSE),$P20),INDIRECT(W$6&VLOOKUP(Summary,Ref!$Y$13:$AC$18,4,FALSE)),0),VLOOKUP(W$10,Ref!$Y$61:$AA$63,2,FALSE)),0)))} -> #REF! | X20: =IF($P20="","",'Inputs & Summary'!S18) -> #REF! | Y20: =IF($P20="","",'Inputs & Summary'!T18) -> #REF! | Z20: =IF($P20="","",IF($Z$11="",0,'Inputs & Summary'!X18)) -> #REF! | AA20: =IF($P20="","",IF($AA$11="",0,IF(AND(LivBen<>"None",RIGHT(Category,2)<>"NY"),'Inputs & Summary'!AH18,""))) -> #REF! | AB20: =IF($P20="","",'Inputs & Summary'!Y18) -> #REF! | AC20: =IF($P20="","",IF(RIGHT(Category,2)="NY",'Inputs & Summary'!AH18,SUM('Inputs & Summary'!AB18,'Inputs & Summary'!AE18*('Inputs & Summary'!AD18="Yes"),'Inputs & Summary'!AG18))) -> #REF! | AD20: =IF($P20="","",'Inputs & Summary'!AI18) -> #REF! | AE20: =IF($P20="","",'Inputs & Summary'!Z18) -> #REF! | AF20: =IF($P20="","",'Inputs & Summary'!U18) -> #REF! | AG20: =IF($P20="","",'Inputs & Summary'!V18) -> #REF! | AH20: =IF($P20="","",'Inputs & Summary'!W18) -> #REF! | AI20: =IF($P20="","",IF($AI$11="",0,'Inputs & Summary'!AM18)) -> #REF! | AJ20: =IF($P20="","",IF($AJ$11="",0,IF(PTab="P7",'Inputs & Summary'!AQ18,'Inputs & Summary'!AA18))) -> #REF! | AK20: =IF($P20="","",'Inputs & Summary'!AJ18) -> #REF!
B21: =IF(PTab="P7","AICO Maximum Rate","") | C21: =IF(PTab="P7",OMaxR,"") | F21: =IF($E21="","",INDEX([1]STRTG!$T$14:$AC$303,MATCH($E21,[1]STRTG!$P$14:$P$303,0),MATCH(F$5,[1]STRTG!$T$13:$AC$13,0))) | G21: =IF($E21="","",INDEX([1]STRTG!$T$14:$AC$303,MATCH($E21,[1]STRTG!$P$14:$P$303,0),MATCH(G$5,[1]STRTG!$T$13:$AC$13,0))) | H21: =IF($E21="","",INDEX([1]STRTG!$T$14:$AC$303,MATCH($E21,[1]STRTG!$P$14:$P$303,0),MATCH(H$5,[1]STRTG!$T$13:$AC$13,0))) | I21: =IF($E21="","",INDEX([1]STRTG!$T$14:$AC$303,MATCH($E21,[1]STRTG!$P$14:$P$303,0),MATCH(I$5,[1]STRTG!$T$13:$AC$13,0))) | J21: =IF($E21="","",INDEX([1]STRTG!$T$14:$AC$303,MATCH($E21,[1]STRTG!$P$14:$P$303,0),MATCH(J$5,[1]STRTG!$T$13:$AC$13,0))) | K21: =IF($E21="","",IF(RIGHT(VLOOKUP($E21,[1]STRTG!$P$14:$S$303,4,FALSE),6)="EPRST1",Ref!$C$103,IF(RIGHT(VLOOKUP($E21,[1]STRTG!$P$14:$S$303,4,FALSE),6)="EPRST2",Ref!$C$104,"N/A"))) | L21: =IF($E21="","",INDEX([1]STRTG!$T$14:$AC$303,MATCH($E21,[1]STRTG!$P$14:$P$303,0),MATCH(L$5,[1]STRTG!$T$13:$AC$13,0))) | P21: =IF('Inputs & Summary'!O19="","",IF('Inputs & Summary'!O19=0,"At Issue",'Inputs & Summary'!P19)) -> #REF! | Q21: =IF($P21="","",'Inputs & Summary'!O19) -> #REF! | R21: =IF($P21="","",'Inputs & Summary'!Q19) -> #REF! | S21: {=IF($P21="","",IF(S$11="",0,IFERROR(INDEX(INDIRECT(S$6&VLOOKUP(Summary,Ref!$Y$13:$AC$18,3,FALSE)),MATCH(IF($P21="At Issue",VLOOKUP(Summary,Ref!$Y$13:$AC$18,2,FALSE),$P21),INDIRECT(S$6&VLOOKUP(Summary,Ref!$Y$13:$AC$18,4,FALSE)),0),VLOOKUP(S$10,Ref!$Y$61:$AA$63,2,FALSE)),0)))} -> #REF! | T21: {=IF($P21="","",IF(T$11="",0,IFERROR(INDEX(INDIRECT(T$6&VLOOKUP(Summary,Ref!$Y$13:$AC$18,3,FALSE)),MATCH(IF($P21="At Issue",VLOOKUP(Summary,Ref!$Y$13:$AC$18,2,FALSE),$P21),INDIRECT(T$6&VLOOKUP(Summary,Ref!$Y$13:$AC$18,4,FALSE)),0),VLOOKUP(T$10,Ref!$Y$61:$AA$63,2,FALSE)),0)))} -> #REF! | U21: {=IF($P21="","",IF(U$11="",0,IFERROR(INDEX(INDIRECT(U$6&VLOOKUP(Summary,Ref!$Y$13:$AC$18,3,FALSE)),MATCH(IF($P21="At Issue",VLOOKUP(Summary,Ref!$Y$13:$AC$18,2,FALSE),$P21),INDIRECT(U$6&VLOOKUP(Summary,Ref!$Y$13:$AC$18,4,FALSE)),0),VLOOKUP(U$10,Ref!$Y$61:$AA$63,2,FALSE)),0)))} -> #REF! | V21: {=IF($P21="","",IF(V$11="",0,IFERROR(INDEX(INDIRECT(V$6&VLOOKUP(Summary,Ref!$Y$13:$AC$18,3,FALSE)),MATCH(IF($P21="At Issue",VLOOKUP(Summary,Ref!$Y$13:$AC$18,2,FALSE),$P21),INDIRECT(V$6&VLOOKUP(Summary,Ref!$Y$13:$AC$18,4,FALSE)),0),VLOOKUP(V$10,Ref!$Y$61:$AA$63,2,FALSE)),0)))} -> #REF! | W21: {=IF($P21="","",IF(W$11="",0,IFERROR(INDEX(INDIRECT(W$6&VLOOKUP(Summary,Ref!$Y$13:$AC$18,3,FALSE)),MATCH(IF($P21="At Issue",VLOOKUP(Summary,Ref!$Y$13:$AC$18,2,FALSE),$P21),INDIRECT(W$6&VLOOKUP(Summary,Ref!$Y$13:$AC$18,4,FALSE)),0),VLOOKUP(W$10,Ref!$Y$61:$AA$63,2,FALSE)),0)))} -> #REF! | X21: =IF($P21="","",'Inputs & Summary'!S19) -> #REF! | Y21: =IF($P21="","",'Inputs & Summary'!T19) -> #REF! | Z21: =IF($P21="","",IF($Z$11="",0,'Inputs & Summary'!X19)) -> #REF! | AA21: =IF($P21="","",IF($AA$11="",0,IF(AND(LivBen<>"None",RIGHT(Category,2)<>"NY"),'Inputs & Summary'!AH19,""))) -> #REF! | AB21: =IF($P21="","",'Inputs & Summary'!Y19) -> #REF! | AC21: =IF($P21="","",IF(RIGHT(Category,2)="NY",'Inputs & Summary'!AH19,SUM('Inputs & Summary'!AB19,'Inputs & Summary'!AE19*('Inputs & Summary'!AD19="Yes"),'Inputs & Summary'!AG19))) -> #REF! | AD21: =IF($P21="","",'Inputs & Summary'!AI19) -> #REF! | AE21: =IF($P21="","",'Inputs & Summary'!Z19) -> #REF! | AF21: =IF($P21="","",'Inputs & Summary'!U19) -> #REF! | AG21: =IF($P21="","",'Inputs & Summary'!V19) -> #REF! | AH21: =IF($P21="","",'Inputs & Summary'!W19) -> #REF! | AI21: =IF($P21="","",IF($AI$11="",0,'Inputs & Summary'!AM19)) -> #REF! | AJ21: =IF($P21="","",IF($AJ$11="",0,IF(PTab="P7",'Inputs & Summary'!AQ19,'Inputs & Summary'!AA19))) -> #REF! | AK21: =IF($P21="","",'Inputs & Summary'!AJ19) -> #REF!
F22: =IF($E22="","",INDEX([1]STRTG!$T$14:$AC$303,MATCH($E22,[1]STRTG!$P$14:$P$303,0),MATCH(F$5,[1]STRTG!$T$13:$AC$13,0))) | G22: =IF($E22="","",INDEX([1]STRTG!$T$14:$AC$303,MATCH($E22,[1]STRTG!$P$14:$P$303,0),MATCH(G$5,[1]STRTG!$T$13:$AC$13,0))) | H22: =IF($E22="","",INDEX([1]STRTG!$T$14:$AC$303,MATCH($E22,[1]STRTG!$P$14:$P$303,0),MATCH(H$5,[1]STRTG!$T$13:$AC$13,0))) | I22: =IF($E22="","",INDEX([1]STRTG!$T$14:$AC$303,MATCH($E22,[1]STRTG!$P$14:$P$303,0),MATCH(I$5,[1]STRTG!$T$13:$AC$13,0))) | J22: =IF($E22="","",INDEX([1]STRTG!$T$14:$AC$303,MATCH($E22,[1]STRTG!$P$14:$P$303,0),MATCH(J$5,[1]STRTG!$T$13:$AC$13,0))) | K22: =IF($E22="","",IF(RIGHT(VLOOKUP($E22,[1]STRTG!$P$14:$S$303,4,FALSE),6)="EPRST1",Ref!$C$103,IF(RIGHT(VLOOKUP($E22,[1]STRTG!$P$14:$S$303,4,FALSE),6)="EPRST2",Ref!$C$104,"N/A"))) | L22: =IF($E22="","",INDEX([1]STRTG!$T$14:$AC$303,MATCH($E22,[1]STRTG!$P$14:$P$303,0),MATCH(L$5,[1]STRTG!$T$13:$AC$13,0))) | P22: =IF('Inputs & Summary'!O20="","",IF('Inputs & Summary'!O20=0,"At Issue",'Inputs & Summary'!P20)) -> #REF! | Q22: =IF($P22="","",'Inputs & Summary'!O20) -> #REF! | R22: =IF($P22="","",'Inputs & Summary'!Q20) -> #REF! | S22: {=IF($P22="","",IF(S$11="",0,IFERROR(INDEX(INDIRECT(S$6&VLOOKUP(Summary,Ref!$Y$13:$AC$18,3,FALSE)),MATCH(IF($P22="At Issue",VLOOKUP(Summary,Ref!$Y$13:$AC$18,2,FALSE),$P22),INDIRECT(S$6&VLOOKUP(Summary,Ref!$Y$13:$AC$18,4,FALSE)),0),VLOOKUP(S$10,Ref!$Y$61:$AA$63,2,FALSE)),0)))} -> #REF! | T22: {=IF($P22="","",IF(T$11="",0,IFERROR(INDEX(INDIRECT(T$6&VLOOKUP(Summary,Ref!$Y$13:$AC$18,3,FALSE)),MATCH(IF($P22="At Issue",VLOOKUP(Summary,Ref!$Y$13:$AC$18,2,FALSE),$P22),INDIRECT(T$6&VLOOKUP(Summary,Ref!$Y$13:$AC$18,4,FALSE)),0),VLOOKUP(T$10,Ref!$Y$61:$AA$63,2,FALSE)),0)))} -> #REF! | U22: {=IF($P22="","",IF(U$11="",0,IFERROR(INDEX(INDIRECT(U$6&VLOOKUP(Summary,Ref!$Y$13:$AC$18,3,FALSE)),MATCH(IF($P22="At Issue",VLOOKUP(Summary,Ref!$Y$13:$AC$18,2,FALSE),$P22),INDIRECT(U$6&VLOOKUP(Summary,Ref!$Y$13:$AC$18,4,FALSE)),0),VLOOKUP(U$10,Ref!$Y$61:$AA$63,2,FALSE)),0)))} -> #REF! | V22: {=IF($P22="","",IF(V$11="",0,IFERROR(INDEX(INDIRECT(V$6&VLOOKUP(Summary,Ref!$Y$13:$AC$18,3,FALSE)),MATCH(IF($P22="At Issue",VLOOKUP(Summary,Ref!$Y$13:$AC$18,2,FALSE),$P22),INDIRECT(V$6&VLOOKUP(Summary,Ref!$Y$13:$AC$18,4,FALSE)),0),VLOOKUP(V$10,Ref!$Y$61:$AA$63,2,FALSE)),0)))} -> #REF! | W22: {=IF($P22="","",IF(W$11="",0,IFERROR(INDEX(INDIRECT(W$6&VLOOKUP(Summary,Ref!$Y$13:$AC$18,3,FALSE)),MATCH(IF($P22="At Issue",VLOOKUP(Summary,Ref!$Y$13:$AC$18,2,FALSE),$P22),INDIRECT(W$6&VLOOKUP(Summary,Ref!$Y$13:$AC$18,4,FALSE)),0),VLOOKUP(W$10,Ref!$Y$61:$AA$63,2,FALSE)),0)))} -> #REF! | X22: =IF($P22="","",'Inputs & Summary'!S20) -> #REF! | Y22: =IF($P22="","",'Inputs & Summary'!T20) -> #REF! | Z22: =IF($P22="","",IF($Z$11="",0,'Inputs & Summary'!X20)) -> #REF! | AA22: =IF($P22="","",IF($AA$11="",0,IF(AND(LivBen<>"None",RIGHT(Category,2)<>"NY"),'Inputs & Summary'!AH20,""))) -> #REF! | AB22: =IF($P22="","",'Inputs & Summary'!Y20) -> #REF! | AC22: =IF($P22="","",IF(RIGHT(Category,2)="NY",'Inputs & Summary'!AH20,SUM('Inputs & Summary'!AB20,'Inputs & Summary'!AE20*('Inputs & Summary'!AD20="Yes"),'Inputs & Summary'!AG20))) -> #REF! | AD22: =IF($P22="","",'Inputs & Summary'!AI20) -> #REF! | AE22: =IF($P22="","",'Inputs & Summary'!Z20) -> #REF! | AF22: =IF($P22="","",'Inputs & Summary'!U20) -> #REF! | AG22: =IF($P22="","",'Inputs & Summary'!V20) -> #REF! | AH22: =IF($P22="","",'Inputs & Summary'!W20) -> #REF! | AI22: =IF($P22="","",IF($AI$11="",0,'Inputs & Summary'!AM20)) -> #REF! | AJ22: =IF($P22="","",IF($AJ$11="",0,IF(PTab="P7",'Inputs & Summary'!AQ20,'Inputs & Summary'!AA20))) -> #REF! | AK22: =IF($P22="","",'Inputs & Summary'!AJ20) -> #REF!
B23: Living Benefit | C23: =LivBen -> None | F23: =IF($E23="","",INDEX([1]STRTG!$T$14:$AC$303,MATCH($E23,[1]STRTG!$P$14:$P$303,0),MATCH(F$5,[1]STRTG!$T$13:$AC$13,0))) | G23: =IF($E23="","",INDEX([1]STRTG!$T$14:$AC$303,MATCH($E23,[1]STRTG!$P$14:$P$303,0),MATCH(G$5,[1]STRTG!$T$13:$AC$13,0))) | H23: =IF($E23="","",INDEX([1]STRTG!$T$14:$AC$303,MATCH($E23,[1]STRTG!$P$14:$P$303,0),MATCH(H$5,[1]STRTG!$T$13:$AC$13,0))) | I23: =IF($E23="","",INDEX([1]STRTG!$T$14:$AC$303,MATCH($E23,[1]STRTG!$P$14:$P$303,0),MATCH(I$5,[1]STRTG!$T$13:$AC$13,0))) | J23: =IF($E23="","",INDEX([1]STRTG!$T$14:$AC$303,MATCH($E23,[1]STRTG!$P$14:$P$303,0),MATCH(J$5,[1]STRTG!$T$13:$AC$13,0))) | K23: =IF($E23="","",IF(RIGHT(VLOOKUP($E23,[1]STRTG!$P$14:$S$303,4,FALSE),6)="EPRST1",Ref!$C$103,IF(RIGHT(VLOOKUP($E23,[1]STRTG!$P$14:$S$303,4,FALSE),6)="EPRST2",Ref!$C$104,"N/A"))) | L23: =IF($E23="","",INDEX([1]STRTG!$T$14:$AC$303,MATCH($E23,[1]STRTG!$P$14:$P$303,0),MATCH(L$5,[1]STRTG!$T$13:$AC$13,0))) | P23: =IF('Inputs & Summary'!O21="","",IF('Inputs & Summary'!O21=0,"At Issue",'Inputs & Summary'!P21)) -> #REF! | Q23: =IF($P23="","",'Inputs & Summary'!O21) -> #REF! | R23: =IF($P23="","",'Inputs & Summary'!Q21) -> #REF! | S23: {=IF($P23="","",IF(S$11="",0,IFERROR(INDEX(INDIRECT(S$6&VLOOKUP(Summary,Ref!$Y$13:$AC$18,3,FALSE)),MATCH(IF($P23="At Issue",VLOOKUP(Summary,Ref!$Y$13:$AC$18,2,FALSE),$P23),INDIRECT(S$6&VLOOKUP(Summary,Ref!$Y$13:$AC$18,4,FALSE)),0),VLOOKUP(S$10,Ref!$Y$61:$AA$63,2,FALSE)),0)))} -> #REF! | T23: {=IF($P23="","",IF(T$11="",0,IFERROR(INDEX(INDIRECT(T$6&VLOOKUP(Summary,Ref!$Y$13:$AC$18,3,FALSE)),MATCH(IF($P23="At Issue",VLOOKUP(Summary,Ref!$Y$13:$AC$18,2,FALSE),$P23),INDIRECT(T$6&VLOOKUP(Summary,Ref!$Y$13:$AC$18,4,FALSE)),0),VLOOKUP(T$10,Ref!$Y$61:$AA$63,2,FALSE)),0)))} -> #REF! | U23: {=IF($P23="","",IF(U$11="",0,IFERROR(INDEX(INDIRECT(U$6&VLOOKUP(Summary,Ref!$Y$13:$AC$18,3,FALSE)),MATCH(IF($P23="At Issue",VLOOKUP(Summary,Ref!$Y$13:$AC$18,2,FALSE),$P23),INDIRECT(U$6&VLOOKUP(Summary,Ref!$Y$13:$AC$18,4,FALSE)),0),VLOOKUP(U$10,Ref!$Y$61:$AA$63,2,FALSE)),0)))} -> #REF! | V23: {=IF($P23="","",IF(V$11="",0,IFERROR(INDEX(INDIRECT(V$6&VLOOKUP(Summary,Ref!$Y$13:$AC$18,3,FALSE)),MATCH(IF($P23="At Issue",VLOOKUP(Summary,Ref!$Y$13:$AC$18,2,FALSE),$P23),INDIRECT(V$6&VLOOKUP(Summary,Ref!$Y$13:$AC$18,4,FALSE)),0),VLOOKUP(V$10,Ref!$Y$61:$AA$63,2,FALSE)),0)))} -> #REF! | W23: {=IF($P23="","",IF(W$11="",0,IFERROR(INDEX(INDIRECT(W$6&VLOOKUP(Summary,Ref!$Y$13:$AC$18,3,FALSE)),MATCH(IF($P23="At Issue",VLOOKUP(Summary,Ref!$Y$13:$AC$18,2,FALSE),$P23),INDIRECT(W$6&VLOOKUP(Summary,Ref!$Y$13:$AC$18,4,FALSE)),0),VLOOKUP(W$10,Ref!$Y$61:$AA$63,2,FALSE)),0)))} -> #REF! | X23: =IF($P23="","",'Inputs & Summary'!S21) -> #REF! | Y23: =IF($P23="","",'Inputs & Summary'!T21) -> #REF! | Z23: =IF($P23="","",IF($Z$11="",0,'Inputs & Summary'!X21)) -> #REF! | AA23: =IF($P23="","",IF($AA$11="",0,IF(AND(LivBen<>"None",RIGHT(Category,2)<>"NY"),'Inputs & Summary'!AH21,""))) -> #REF! | AB23: =IF($P23="","",'Inputs & Summary'!Y21) -> #REF! | AC23: =IF($P23="","",IF(RIGHT(Category,2)="NY",'Inputs & Summary'!AH21,SUM('Inputs & Summary'!AB21,'Inputs & Summary'!AE21*('Inputs & Summary'!AD21="Yes"),'Inputs & Summary'!AG21))) -> #REF! | AD23: =IF($P23="","",'Inputs & Summary'!AI21) -> #REF! | AE23: =IF($P23="","",'Inputs & Summary'!Z21) -> #REF! | AF23: =IF($P23="","",'Inputs & Summary'!U21) -> #REF! | AG23: =IF($P23="","",'Inputs & Summary'!V21) -> #REF! | AH23: =IF($P23="","",'Inputs & Summary'!W21) -> #REF! | AI23: =IF($P23="","",IF($AI$11="",0,'Inputs & Summary'!AM21)) -> #REF! | AJ23: =IF($P23="","",IF($AJ$11="",0,IF(PTab="P7",'Inputs & Summary'!AQ21,'Inputs & Summary'!AA21))) -> #REF! | AK23: =IF($P23="","",'Inputs & Summary'!AJ21) -> #REF!
B24: Withdrawal Type | C24: =IF(AND(RIGHT(Category,2)="NY",LivBen<>"None"),"GLIA",IF(LivBen<>"None","GMWB",IF(SWInd="No","None",SWMode))) -> None | F24: =IF($E24="","",INDEX([1]STRTG!$T$14:$AC$303,MATCH($E24,[1]STRTG!$P$14:$P$303,0),MATCH(F$5,[1]STRTG!$T$13:$AC$13,0))) | G24: =IF($E24="","",INDEX([1]STRTG!$T$14:$AC$303,MATCH($E24,[1]STRTG!$P$14:$P$303,0),MATCH(G$5,[1]STRTG!$T$13:$AC$13,0))) | H24: =IF($E24="","",INDEX([1]STRTG!$T$14:$AC$303,MATCH($E24,[1]STRTG!$P$14:$P$303,0),MATCH(H$5,[1]STRTG!$T$13:$AC$13,0))) | I24: =IF($E24="","",INDEX([1]STRTG!$T$14:$AC$303,MATCH($E24,[1]STRTG!$P$14:$P$303,0),MATCH(I$5,[1]STRTG!$T$13:$AC$13,0))) | J24: =IF($E24="","",INDEX([1]STRTG!$T$14:$AC$303,MATCH($E24,[1]STRTG!$P$14:$P$303,0),MATCH(J$5,[1]STRTG!$T$13:$AC$13,0))) | K24: =IF($E24="","",IF(RIGHT(VLOOKUP($E24,[1]STRTG!$P$14:$S$303,4,FALSE),6)="EPRST1",Ref!$C$103,IF(RIGHT(VLOOKUP($E24,[1]STRTG!$P$14:$S$303,4,FALSE),6)="EPRST2",Ref!$C$104,"N/A"))) | L24: =IF($E24="","",INDEX([1]STRTG!$T$14:$AC$303,MATCH($E24,[1]STRTG!$P$14:$P$303,0),MATCH(L$5,[1]STRTG!$T$13:$AC$13,0))) | P24: =IF('Inputs & Summary'!O22="","",IF('Inputs & Summary'!O22=0,"At Issue",'Inputs & Summary'!P22)) -> #REF! | Q24: =IF($P24="","",'Inputs & Summary'!O22) -> #REF! | R24: =IF($P24="","",'Inputs & Summary'!Q22) -> #REF! | S24: {=IF($P24="","",IF(S$11="",0,IFERROR(INDEX(INDIRECT(S$6&VLOOKUP(Summary,Ref!$Y$13:$AC$18,3,FALSE)),MATCH(IF($P24="At Issue",VLOOKUP(Summary,Ref!$Y$13:$AC$18,2,FALSE),$P24),INDIRECT(S$6&VLOOKUP(Summary,Ref!$Y$13:$AC$18,4,FALSE)),0),VLOOKUP(S$10,Ref!$Y$61:$AA$63,2,FALSE)),0)))} -> #REF! | T24: {=IF($P24="","",IF(T$11="",0,IFERROR(INDEX(INDIRECT(T$6&VLOOKUP(Summary,Ref!$Y$13:$AC$18,3,FALSE)),MATCH(IF($P24="At Issue",VLOOKUP(Summary,Ref!$Y$13:$AC$18,2,FALSE),$P24),INDIRECT(T$6&VLOOKUP(Summary,Ref!$Y$13:$AC$18,4,FALSE)),0),VLOOKUP(T$10,Ref!$Y$61:$AA$63,2,FALSE)),0)))} -> #REF! | U24: {=IF($P24="","",IF(U$11="",0,IFERROR(INDEX(INDIRECT(U$6&VLOOKUP(Summary,Ref!$Y$13:$AC$18,3,FALSE)),MATCH(IF($P24="At Issue",VLOOKUP(Summary,Ref!$Y$13:$AC$18,2,FALSE),$P24),INDIRECT(U$6&VLOOKUP(Summary,Ref!$Y$13:$AC$18,4,FALSE)),0),VLOOKUP(U$10,Ref!$Y$61:$AA$63,2,FALSE)),0)))} -> #REF! | V24: {=IF($P24="","",IF(V$11="",0,IFERROR(INDEX(INDIRECT(V$6&VLOOKUP(Summary,Ref!$Y$13:$AC$18,3,FALSE)),MATCH(IF($P24="At Issue",VLOOKUP(Summary,Ref!$Y$13:$AC$18,2,FALSE),$P24),INDIRECT(V$6&VLOOKUP(Summary,Ref!$Y$13:$AC$18,4,FALSE)),0),VLOOKUP(V$10,Ref!$Y$61:$AA$63,2,FALSE)),0)))} -> #REF! | W24: {=IF($P24="","",IF(W$11="",0,IFERROR(INDEX(INDIRECT(W$6&VLOOKUP(Summary,Ref!$Y$13:$AC$18,3,FALSE)),MATCH(IF($P24="At Issue",VLOOKUP(Summary,Ref!$Y$13:$AC$18,2,FALSE),$P24),INDIRECT(W$6&VLOOKUP(Summary,Ref!$Y$13:$AC$18,4,FALSE)),0),VLOOKUP(W$10,Ref!$Y$61:$AA$63,2,FALSE)),0)))} -> #REF! | X24: =IF($P24="","",'Inputs & Summary'!S22) -> #REF! | Y24: =IF($P24="","",'Inputs & Summary'!T22) -> #REF! | Z24: =IF($P24="","",IF($Z$11="",0,'Inputs & Summary'!X22)) -> #REF! | AA24: =IF($P24="","",IF($AA$11="",0,IF(AND(LivBen<>"None",RIGHT(Category,2)<>"NY"),'Inputs & Summary'!AH22,""))) -> #REF! | AB24: =IF($P24="","",'Inputs & Summary'!Y22) -> #REF! | AC24: =IF($P24="","",IF(RIGHT(Category,2)="NY",'Inputs & Summary'!AH22,SUM('Inputs & Summary'!AB22,'Inputs & Summary'!AE22*('Inputs & Summary'!AD22="Yes"),'Inputs & Summary'!AG22))) -> #REF! | AD24: =IF($P24="","",'Inputs & Summary'!AI22) -> #REF! | AE24: =IF($P24="","",'Inputs & Summary'!Z22) -> #REF! | AF24: =IF($P24="","",'Inputs & Summary'!U22) -> #REF! | AG24: =IF($P24="","",'Inputs & Summary'!V22) -> #REF! | AH24: =IF($P24="","",'Inputs & Summary'!W22) -> #REF! | AI24: =IF($P24="","",IF($AI$11="",0,'Inputs & Summary'!AM22)) -> #REF! | AJ24: =IF($P24="","",IF($AJ$11="",0,IF(PTab="P7",'Inputs & Summary'!AQ22,'Inputs & Summary'!AA22))) -> #REF! | AK24: =IF($P24="","",'Inputs & Summary'!AJ22) -> #REF!
B25: Income Start Age | C25: =IF(LivBen="None","N/A",WDAge) -> N/A | F25: =IF($E25="","",INDEX([1]STRTG!$T$14:$AC$303,MATCH($E25,[1]STRTG!$P$14:$P$303,0),MATCH(F$5,[1]STRTG!$T$13:$AC$13,0))) | G25: =IF($E25="","",INDEX([1]STRTG!$T$14:$AC$303,MATCH($E25,[1]STRTG!$P$14:$P$303,0),MATCH(G$5,[1]STRTG!$T$13:$AC$13,0))) | H25: =IF($E25="","",INDEX([1]STRTG!$T$14:$AC$303,MATCH($E25,[1]STRTG!$P$14:$P$303,0),MATCH(H$5,[1]STRTG!$T$13:$AC$13,0))) | I25: =IF($E25="","",INDEX([1]STRTG!$T$14:$AC$303,MATCH($E25,[1]STRTG!$P$14:$P$303,0),MATCH(I$5,[1]STRTG!$T$13:$AC$13,0))) | J25: =IF($E25="","",INDEX([1]STRTG!$T$14:$AC$303,MATCH($E25,[1]STRTG!$P$14:$P$303,0),MATCH(J$5,[1]STRTG!$T$13:$AC$13,0))) | K25: =IF($E25="","",IF(RIGHT(VLOOKUP($E25,[1]STRTG!$P$14:$S$303,4,FALSE),6)="EPRST1",Ref!$C$103,IF(RIGHT(VLOOKUP($E25,[1]STRTG!$P$14:$S$303,4,FALSE),6)="EPRST2",Ref!$C$104,"N/A"))) | L25: =IF($E25="","",INDEX([1]STRTG!$T$14:$AC$303,MATCH($E25,[1]STRTG!$P$14:$P$303,0),MATCH(L$5,[1]STRTG!$T$13:$AC$13,0))) | P25: =IF('Inputs & Summary'!O23="","",IF('Inputs & Summary'!O23=0,"At Issue",'Inputs & Summary'!P23)) -> #REF! | Q25: =IF($P25="","",'Inputs & Summary'!O23) -> #REF! | R25: =IF($P25="","",'Inputs & Summary'!Q23) -> #REF! | S25: {=IF($P25="","",IF(S$11="",0,IFERROR(INDEX(INDIRECT(S$6&VLOOKUP(Summary,Ref!$Y$13:$AC$18,3,FALSE)),MATCH(IF($P25="At Issue",VLOOKUP(Summary,Ref!$Y$13:$AC$18,2,FALSE),$P25),INDIRECT(S$6&VLOOKUP(Summary,Ref!$Y$13:$AC$18,4,FALSE)),0),VLOOKUP(S$10,Ref!$Y$61:$AA$63,2,FALSE)),0)))} -> #REF! | T25: {=IF($P25="","",IF(T$11="",0,IFERROR(INDEX(INDIRECT(T$6&VLOOKUP(Summary,Ref!$Y$13:$AC$18,3,FALSE)),MATCH(IF($P25="At Issue",VLOOKUP(Summary,Ref!$Y$13:$AC$18,2,FALSE),$P25),INDIRECT(T$6&VLOOKUP(Summary,Ref!$Y$13:$AC$18,4,FALSE)),0),VLOOKUP(T$10,Ref!$Y$61:$AA$63,2,FALSE)),0)))} -> #REF! | U25: {=IF($P25="","",IF(U$11="",0,IFERROR(INDEX(INDIRECT(U$6&VLOOKUP(Summary,Ref!$Y$13:$AC$18,3,FALSE)),MATCH(IF($P25="At Issue",VLOOKUP(Summary,Ref!$Y$13:$AC$18,2,FALSE),$P25),INDIRECT(U$6&VLOOKUP(Summary,Ref!$Y$13:$AC$18,4,FALSE)),0),VLOOKUP(U$10,Ref!$Y$61:$AA$63,2,FALSE)),0)))} -> #REF! | V25: {=IF($P25="","",IF(V$11="",0,IFERROR(INDEX(INDIRECT(V$6&VLOOKUP(Summary,Ref!$Y$13:$AC$18,3,FALSE)),MATCH(IF($P25="At Issue",VLOOKUP(Summary,Ref!$Y$13:$AC$18,2,FALSE),$P25),INDIRECT(V$6&VLOOKUP(Summary,Ref!$Y$13:$AC$18,4,FALSE)),0),VLOOKUP(V$10,Ref!$Y$61:$AA$63,2,FALSE)),0)))} -> #REF! | W25: {=IF($P25="","",IF(W$11="",0,IFERROR(INDEX(INDIRECT(W$6&VLOOKUP(Summary,Ref!$Y$13:$AC$18,3,FALSE)),MATCH(IF($P25="At Issue",VLOOKUP(Summary,Ref!$Y$13:$AC$18,2,FALSE),$P25),INDIRECT(W$6&VLOOKUP(Summary,Ref!$Y$13:$AC$18,4,FALSE)),0),VLOOKUP(W$10,Ref!$Y$61:$AA$63,2,FALSE)),0)))} -> #REF! | X25: =IF($P25="","",'Inputs & Summary'!S23) -> #REF! | Y25: =IF($P25="","",'Inputs & Summary'!T23) -> #REF! | Z25: =IF($P25="","",IF($Z$11="",0,'Inputs & Summary'!X23)) -> #REF! | AA25: =IF($P25="","",IF($AA$11="",0,IF(AND(LivBen<>"None",RIGHT(Category,2)<>"NY"),'Inputs & Summary'!AH23,""))) -> #REF! | AB25: =IF($P25="","",'Inputs & Summary'!Y23) -> #REF! | AC25: =IF($P25="","",IF(RIGHT(Category,2)="NY",'Inputs & Summary'!AH23,SUM('Inputs & Summary'!AB23,'Inputs & Summary'!AE23*('Inputs & Summary'!AD23="Yes"),'Inputs & Summary'!AG23))) -> #REF! | AD25: =IF($P25="","",'Inputs & Summary'!AI23) -> #REF! | AE25: =IF($P25="","",'Inputs & Summary'!Z23) -> #REF! | AF25: =IF($P25="","",'Inputs & Summary'!U23) -> #REF! | AG25: =IF($P25="","",'Inputs & Summary'!V23) -> #REF! | AH25: =IF($P25="","",'Inputs & Summary'!W23) -> #REF! | AI25: =IF($P25="","",IF($AI$11="",0,'Inputs & Summary'!AM23)) -> #REF! | AJ25: =IF($P25="","",IF($AJ$11="",0,IF(PTab="P7",'Inputs & Summary'!AQ23,'Inputs & Summary'!AA23))) -> #REF! | AK25: =IF($P25="","",'Inputs & Summary'!AJ23) -> #REF!
B26: =IF(AND(RIGHT(Category,2)="NY",LivBen<>"None"),"Initial Income Rate","Withdrawal Rate") -> Withdrawal Rate | C26: =IF(AND(RIGHT(Category,2)="NY",LivBen<>"None"),VLOOKUP(IF(Election="Joint Life",MIN(IssAge1,IssAge2),IssAge1),Ref!$BC$7:$BF$39,4,FALSE),IF(LivBen<>"None",VLOOKUP(WDAge,Ref!$BC$7:$BF$39,2),"N/A")) -> N/A | F26: =IF($E26="","",INDEX([1]STRTG!$T$14:$AC$303,MATCH($E26,[1]STRTG!$P$14:$P$303,0),MATCH(F$5,[1]STRTG!$T$13:$AC$13,0))) | G26: =IF($E26="","",INDEX([1]STRTG!$T$14:$AC$303,MATCH($E26,[1]STRTG!$P$14:$P$303,0),MATCH(G$5,[1]STRTG!$T$13:$AC$13,0))) | H26: =IF($E26="","",INDEX([1]STRTG!$T$14:$AC$303,MATCH($E26,[1]STRTG!$P$14:$P$303,0),MATCH(H$5,[1]STRTG!$T$13:$AC$13,0))) | I26: =IF($E26="","",INDEX([1]STRTG!$T$14:$AC$303,MATCH($E26,[1]STRTG!$P$14:$P$303,0),MATCH(I$5,[1]STRTG!$T$13:$AC$13,0))) | J26: =IF($E26="","",INDEX([1]STRTG!$T$14:$AC$303,MATCH($E26,[1]STRTG!$P$14:$P$303,0),MATCH(J$5,[1]STRTG!$T$13:$AC$13,0))) | K26: =IF($E26="","",IF(RIGHT(VLOOKUP($E26,[1]STRTG!$P$14:$S$303,4,FALSE),6)="EPRST1",Ref!$C$103,IF(RIGHT(VLOOKUP($E26,[1]STRTG!$P$14:$S$303,4,FALSE),6)="EPRST2",Ref!$C$104,"N/A"))) | L26: =IF($E26="","",INDEX([1]STRTG!$T$14:$AC$303,MATCH($E26,[1]STRTG!$P$14:$P$303,0),MATCH(L$5,[1]STRTG!$T$13:$AC$13,0))) | P26: =IF('Inputs & Summary'!O24="","",IF('Inputs & Summary'!O24=0,"At Issue",'Inputs & Summary'!P24)) -> #REF! | Q26: =IF($P26="","",'Inputs & Summary'!O24) -> #REF! | R26: =IF($P26="","",'Inputs & Summary'!Q24) -> #REF! | S26: {=IF($P26="","",IF(S$11="",0,IFERROR(INDEX(INDIRECT(S$6&VLOOKUP(Summary,Ref!$Y$13:$AC$18,3,FALSE)),MATCH(IF($P26="At Issue",VLOOKUP(Summary,Ref!$Y$13:$AC$18,2,FALSE),$P26),INDIRECT(S$6&VLOOKUP(Summary,Ref!$Y$13:$AC$18,4,FALSE)),0),VLOOKUP(S$10,Ref!$Y$61:$AA$63,2,FALSE)),0)))} -> #REF! | T26: {=IF($P26="","",IF(T$11="",0,IFERROR(INDEX(INDIRECT(T$6&VLOOKUP(Summary,Ref!$Y$13:$AC$18,3,FALSE)),MATCH(IF($P26="At Issue",VLOOKUP(Summary,Ref!$Y$13:$AC$18,2,FALSE),$P26),INDIRECT(T$6&VLOOKUP(Summary,Ref!$Y$13:$AC$18,4,FALSE)),0),VLOOKUP(T$10,Ref!$Y$61:$AA$63,2,FALSE)),0)))} -> #REF! | U26: {=IF($P26="","",IF(U$11="",0,IFERROR(INDEX(INDIRECT(U$6&VLOOKUP(Summary,Ref!$Y$13:$AC$18,3,FALSE)),MATCH(IF($P26="At Issue",VLOOKUP(Summary,Ref!$Y$13:$AC$18,2,FALSE),$P26),INDIRECT(U$6&VLOOKUP(Summary,Ref!$Y$13:$AC$18,4,FALSE)),0),VLOOKUP(U$10,Ref!$Y$61:$AA$63,2,FALSE)),0)))} -> #REF! | V26: {=IF($P26="","",IF(V$11="",0,IFERROR(INDEX(INDIRECT(V$6&VLOOKUP(Summary,Ref!$Y$13:$AC$18,3,FALSE)),MATCH(IF($P26="At Issue",VLOOKUP(Summary,Ref!$Y$13:$AC$18,2,FALSE),$P26),INDIRECT(V$6&VLOOKUP(Summary,Ref!$Y$13:$AC$18,4,FALSE)),0),VLOOKUP(V$10,Ref!$Y$61:$AA$63,2,FALSE)),0)))} -> #REF! | W26: {=IF($P26="","",IF(W$11="",0,IFERROR(INDEX(INDIRECT(W$6&VLOOKUP(Summary,Ref!$Y$13:$AC$18,3,FALSE)),MATCH(IF($P26="At Issue",VLOOKUP(Summary,Ref!$Y$13:$AC$18,2,FALSE),$P26),INDIRECT(W$6&VLOOKUP(Summary,Ref!$Y$13:$AC$18,4,FALSE)),0),VLOOKUP(W$10,Ref!$Y$61:$AA$63,2,FALSE)),0)))} -> #REF! | X26: =IF($P26="","",'Inputs & Summary'!S24) -> #REF! | Y26: =IF($P26="","",'Inputs & Summary'!T24) -> #REF! | Z26: =IF($P26="","",IF($Z$11="",0,'Inputs & Summary'!X24)) -> #REF! | AA26: =IF($P26="","",IF($AA$11="",0,IF(AND(LivBen<>"None",RIGHT(Category,2)<>"NY"),'Inputs & Summary'!AH24,""))) -> #REF! | AB26: =IF($P26="","",'Inputs & Summary'!Y24) -> #REF! | AC26: =IF($P26="","",IF(RIGHT(Category,2)="NY",'Inputs & Summary'!AH24,SUM('Inputs & Summary'!AB24,'Inputs & Summary'!AE24*('Inputs & Summary'!AD24="Yes"),'Inputs & Summary'!AG24))) -> #REF! | AD26: =IF($P26="","",'Inputs & Summary'!AI24) -> #REF! | AE26: =IF($P26="","",'Inputs & Summary'!Z24) -> #REF! | AF26: =IF($P26="","",'Inputs & Summary'!U24) -> #REF! | AG26: =IF($P26="","",'Inputs & Summary'!V24) -> #REF! | AH26: =IF($P26="","",'Inputs & Summary'!W24) -> #REF! | AI26: =IF($P26="","",IF($AI$11="",0,'Inputs & Summary'!AM24)) -> #REF! | AJ26: =IF($P26="","",IF($AJ$11="",0,IF(PTab="P7",'Inputs & Summary'!AQ24,'Inputs & Summary'!AA24))) -> #REF! | AK26: =IF($P26="","",'Inputs & Summary'!AJ24) -> #REF!
B27: =IF(AND(RIGHT(Category,2)="NY",LivBen<>"None"),"Income Percentage Increase","") | C27: =IF(AND(RIGHT(Category,2)="NY",LivBen<>"None"),IPI,"") | F27: =IF($E27="","",INDEX([1]STRTG!$T$14:$AC$303,MATCH($E27,[1]STRTG!$P$14:$P$303,0),MATCH(F$5,[1]STRTG!$T$13:$AC$13,0))) | G27: =IF($E27="","",INDEX([1]STRTG!$T$14:$AC$303,MATCH($E27,[1]STRTG!$P$14:$P$303,0),MATCH(G$5,[1]STRTG!$T$13:$AC$13,0))) | H27: =IF($E27="","",INDEX([1]STRTG!$T$14:$AC$303,MATCH($E27,[1]STRTG!$P$14:$P$303,0),MATCH(H$5,[1]STRTG!$T$13:$AC$13,0))) | I27: =IF($E27="","",INDEX([1]STRTG!$T$14:$AC$303,MATCH($E27,[1]STRTG!$P$14:$P$303,0),MATCH(I$5,[1]STRTG!$T$13:$AC$13,0))) | J27: =IF($E27="","",INDEX([1]STRTG!$T$14:$AC$303,MATCH($E27,[1]STRTG!$P$14:$P$303,0),MATCH(J$5,[1]STRTG!$T$13:$AC$13,0))) | K27: =IF($E27="","",IF(RIGHT(VLOOKUP($E27,[1]STRTG!$P$14:$S$303,4,FALSE),6)="EPRST1",Ref!$C$103,IF(RIGHT(VLOOKUP($E27,[1]STRTG!$P$14:$S$303,4,FALSE),6)="EPRST2",Ref!$C$104,"N/A"))) | L27: =IF($E27="","",INDEX([1]STRTG!$T$14:$AC$303,MATCH($E27,[1]STRTG!$P$14:$P$303,0),MATCH(L$5,[1]STRTG!$T$13:$AC$13,0))) | P27: =IF('Inputs & Summary'!O25="","",IF('Inputs & Summary'!O25=0,"At Issue",'Inputs & Summary'!P25)) -> #REF! | Q27: =IF($P27="","",'Inputs & Summary'!O25) -> #REF! | R27: =IF($P27="","",'Inputs & Summary'!Q25) -> #REF! | S27: {=IF($P27="","",IF(S$11="",0,IFERROR(INDEX(INDIRECT(S$6&VLOOKUP(Summary,Ref!$Y$13:$AC$18,3,FALSE)),MATCH(IF($P27="At Issue",VLOOKUP(Summary,Ref!$Y$13:$AC$18,2,FALSE),$P27),INDIRECT(S$6&VLOOKUP(Summary,Ref!$Y$13:$AC$18,4,FALSE)),0),VLOOKUP(S$10,Ref!$Y$61:$AA$63,2,FALSE)),0)))} -> #REF! | T27: {=IF($P27="","",IF(T$11="",0,IFERROR(INDEX(INDIRECT(T$6&VLOOKUP(Summary,Ref!$Y$13:$AC$18,3,FALSE)),MATCH(IF($P27="At Issue",VLOOKUP(Summary,Ref!$Y$13:$AC$18,2,FALSE),$P27),INDIRECT(T$6&VLOOKUP(Summary,Ref!$Y$13:$AC$18,4,FALSE)),0),VLOOKUP(T$10,Ref!$Y$61:$AA$63,2,FALSE)),0)))} -> #REF! | U27: {=IF($P27="","",IF(U$11="",0,IFERROR(INDEX(INDIRECT(U$6&VLOOKUP(Summary,Ref!$Y$13:$AC$18,3,FALSE)),MATCH(IF($P27="At Issue",VLOOKUP(Summary,Ref!$Y$13:$AC$18,2,FALSE),$P27),INDIRECT(U$6&VLOOKUP(Summary,Ref!$Y$13:$AC$18,4,FALSE)),0),VLOOKUP(U$10,Ref!$Y$61:$AA$63,2,FALSE)),0)))} -> #REF! | V27: {=IF($P27="","",IF(V$11="",0,IFERROR(INDEX(INDIRECT(V$6&VLOOKUP(Summary,Ref!$Y$13:$AC$18,3,FALSE)),MATCH(IF($P27="At Issue",VLOOKUP(Summary,Ref!$Y$13:$AC$18,2,FALSE),$P27),INDIRECT(V$6&VLOOKUP(Summary,Ref!$Y$13:$AC$18,4,FALSE)),0),VLOOKUP(V$10,Ref!$Y$61:$AA$63,2,FALSE)),0)))} -> #REF! | W27: {=IF($P27="","",IF(W$11="",0,IFERROR(INDEX(INDIRECT(W$6&VLOOKUP(Summary,Ref!$Y$13:$AC$18,3,FALSE)),MATCH(IF($P27="At Issue",VLOOKUP(Summary,Ref!$Y$13:$AC$18,2,FALSE),$P27),INDIRECT(W$6&VLOOKUP(Summary,Ref!$Y$13:$AC$18,4,FALSE)),0),VLOOKUP(W$10,Ref!$Y$61:$AA$63,2,FALSE)),0)))} -> #REF! | X27: =IF($P27="","",'Inputs & Summary'!S25) -> #REF! | Y27: =IF($P27="","",'Inputs & Summary'!T25) -> #REF! | Z27: =IF($P27="","",IF($Z$11="",0,'Inputs & Summary'!X25)) -> #REF! | AA27: =IF($P27="","",IF($AA$11="",0,IF(AND(LivBen<>"None",RIGHT(Category,2)<>"NY"),'Inputs & Summary'!AH25,""))) -> #REF! | AB27: =IF($P27="","",'Inputs & Summary'!Y25) -> #REF! | AC27: =IF($P27="","",IF(RIGHT(Category,2)="NY",'Inputs & Summary'!AH25,SUM('Inputs & Summary'!AB25,'Inputs & Summary'!AE25*('Inputs & Summary'!AD25="Yes"),'Inputs & Summary'!AG25))) -> #REF! | AD27: =IF($P27="","",'Inputs & Summary'!AI25) -> #REF! | AE27: =IF($P27="","",'Inputs & Summary'!Z25) -> #REF! | AF27: =IF($P27="","",'Inputs & Summary'!U25) -> #REF! | AG27: =IF($P27="","",'Inputs & Summary'!V25) -> #REF! | AH27: =IF($P27="","",'Inputs & Summary'!W25) -> #REF! | AI27: =IF($P27="","",IF($AI$11="",0,'Inputs & Summary'!AM25)) -> #REF! | AJ27: =IF($P27="","",IF($AJ$11="",0,IF(PTab="P7",'Inputs & Summary'!AQ25,'Inputs & Summary'!AA25))) -> #REF! | AK27: =IF($P27="","",'Inputs & Summary'!AJ25) -> #REF!
B28: =IF(AND(RIGHT(Category,2)<>"NY",LivBen<>"None"),"GMWB Fee","") | C28: =IF(AND(RIGHT(Category,2)<>"NY",LivBen<>"None"),GMWBFee,"") | F28: =IF($E28="","",INDEX([1]STRTG!$T$14:$AC$303,MATCH($E28,[1]STRTG!$P$14:$P$303,0),MATCH(F$5,[1]STRTG!$T$13:$AC$13,0))) | G28: =IF($E28="","",INDEX([1]STRTG!$T$14:$AC$303,MATCH($E28,[1]STRTG!$P$14:$P$303,0),MATCH(G$5,[1]STRTG!$T$13:$AC$13,0))) | H28: =IF($E28="","",INDEX([1]STRTG!$T$14:$AC$303,MATCH($E28,[1]STRTG!$P$14:$P$303,0),MATCH(H$5,[1]STRTG!$T$13:$AC$13,0))) | I28: =IF($E28="","",INDEX([1]STRTG!$T$14:$AC$303,MATCH($E28,[1]STRTG!$P$14:$P$303,0),MATCH(I$5,[1]STRTG!$T$13:$AC$13,0))) | J28: =IF($E28="","",INDEX([1]STRTG!$T$14:$AC$303,MATCH($E28,[1]STRTG!$P$14:$P$303,0),MATCH(J$5,[1]STRTG!$T$13:$AC$13,0))) | K28: =IF($E28="","",IF(RIGHT(VLOOKUP($E28,[1]STRTG!$P$14:$S$303,4,FALSE),6)="EPRST1",Ref!$C$103,IF(RIGHT(VLOOKUP($E28,[1]STRTG!$P$14:$S$303,4,FALSE),6)="EPRST2",Ref!$C$104,"N/A"))) | L28: =IF($E28="","",INDEX([1]STRTG!$T$14:$AC$303,MATCH($E28,[1]STRTG!$P$14:$P$303,0),MATCH(L$5,[1]STRTG!$T$13:$AC$13,0))) | P28: =IF('Inputs & Summary'!O26="","",IF('Inputs & Summary'!O26=0,"At Issue",'Inputs & Summary'!P26)) -> #REF! | Q28: =IF($P28="","",'Inputs & Summary'!O26) -> #REF! | R28: =IF($P28="","",'Inputs & Summary'!Q26) -> #REF! | S28: {=IF($P28="","",IF(S$11="",0,IFERROR(INDEX(INDIRECT(S$6&VLOOKUP(Summary,Ref!$Y$13:$AC$18,3,FALSE)),MATCH(IF($P28="At Issue",VLOOKUP(Summary,Ref!$Y$13:$AC$18,2,FALSE),$P28),INDIRECT(S$6&VLOOKUP(Summary,Ref!$Y$13:$AC$18,4,FALSE)),0),VLOOKUP(S$10,Ref!$Y$61:$AA$63,2,FALSE)),0)))} -> #REF! | T28: {=IF($P28="","",IF(T$11="",0,IFERROR(INDEX(INDIRECT(T$6&VLOOKUP(Summary,Ref!$Y$13:$AC$18,3,FALSE)),MATCH(IF($P28="At Issue",VLOOKUP(Summary,Ref!$Y$13:$AC$18,2,FALSE),$P28),INDIRECT(T$6&VLOOKUP(Summary,Ref!$Y$13:$AC$18,4,FALSE)),0),VLOOKUP(T$10,Ref!$Y$61:$AA$63,2,FALSE)),0)))} -> #REF! | U28: {=IF($P28="","",IF(U$11="",0,IFERROR(INDEX(INDIRECT(U$6&VLOOKUP(Summary,Ref!$Y$13:$AC$18,3,FALSE)),MATCH(IF($P28="At Issue",VLOOKUP(Summary,Ref!$Y$13:$AC$18,2,FALSE),$P28),INDIRECT(U$6&VLOOKUP(Summary,Ref!$Y$13:$AC$18,4,FALSE)),0),VLOOKUP(U$10,Ref!$Y$61:$AA$63,2,FALSE)),0)))} -> #REF! | V28: {=IF($P28="","",IF(V$11="",0,IFERROR(INDEX(INDIRECT(V$6&VLOOKUP(Summary,Ref!$Y$13:$AC$18,3,FALSE)),MATCH(IF($P28="At Issue",VLOOKUP(Summary,Ref!$Y$13:$AC$18,2,FALSE),$P28),INDIRECT(V$6&VLOOKUP(Summary,Ref!$Y$13:$AC$18,4,FALSE)),0),VLOOKUP(V$10,Ref!$Y$61:$AA$63,2,FALSE)),0)))} -> #REF! | W28: {=IF($P28="","",IF(W$11="",0,IFERROR(INDEX(INDIRECT(W$6&VLOOKUP(Summary,Ref!$Y$13:$AC$18,3,FALSE)),MATCH(IF($P28="At Issue",VLOOKUP(Summary,Ref!$Y$13:$AC$18,2,FALSE),$P28),INDIRECT(W$6&VLOOKUP(Summary,Ref!$Y$13:$AC$18,4,FALSE)),0),VLOOKUP(W$10,Ref!$Y$61:$AA$63,2,FALSE)),0)))} -> #REF! | X28: =IF($P28="","",'Inputs & Summary'!S26) -> #REF! | Y28: =IF($P28="","",'Inputs & Summary'!T26) -> #REF! | Z28: =IF($P28="","",IF($Z$11="",0,'Inputs & Summary'!X26)) -> #REF! | AA28: =IF($P28="","",IF($AA$11="",0,IF(AND(LivBen<>"None",RIGHT(Category,2)<>"NY"),'Inputs & Summary'!AH26,""))) -> #REF! | AB28: =IF($P28="","",'Inputs & Summary'!Y26) -> #REF! | AC28: =IF($P28="","",IF(RIGHT(Category,2)="NY",'Inputs & Summary'!AH26,SUM('Inputs & Summary'!AB26,'Inputs & Summary'!AE26*('Inputs & Summary'!AD26="Yes"),'Inputs & Summary'!AG26))) -> #REF! | AD28: =IF($P28="","",'Inputs & Summary'!AI26) -> #REF! | AE28: =IF($P28="","",'Inputs & Summary'!Z26) -> #REF! | AF28: =IF($P28="","",'Inputs & Summary'!U26) -> #REF! | AG28: =IF($P28="","",'Inputs & Summary'!V26) -> #REF! | AH28: =IF($P28="","",'Inputs & Summary'!W26) -> #REF! | AI28: =IF($P28="","",IF($AI$11="",0,'Inputs & Summary'!AM26)) -> #REF! | AJ28: =IF($P28="","",IF($AJ$11="",0,IF(PTab="P7",'Inputs & Summary'!AQ26,'Inputs & Summary'!AA26))) -> #REF! | AK28: =IF($P28="","",'Inputs & Summary'!AJ26) -> #REF!
P29: =IF('Inputs & Summary'!O27="","",IF('Inputs & Summary'!O27=0,"At Issue",'Inputs & Summary'!P27)) -> #REF! | Q29: =IF($P29="","",'Inputs & Summary'!O27) -> #REF! | R29: =IF($P29="","",'Inputs & Summary'!Q27) -> #REF! | S29: {=IF($P29="","",IF(S$11="",0,IFERROR(INDEX(INDIRECT(S$6&VLOOKUP(Summary,Ref!$Y$13:$AC$18,3,FALSE)),MATCH(IF($P29="At Issue",VLOOKUP(Summary,Ref!$Y$13:$AC$18,2,FALSE),$P29),INDIRECT(S$6&VLOOKUP(Summary,Ref!$Y$13:$AC$18,4,FALSE)),0),VLOOKUP(S$10,Ref!$Y$61:$AA$63,2,FALSE)),0)))} -> #REF! | T29: {=IF($P29="","",IF(T$11="",0,IFERROR(INDEX(INDIRECT(T$6&VLOOKUP(Summary,Ref!$Y$13:$AC$18,3,FALSE)),MATCH(IF($P29="At Issue",VLOOKUP(Summary,Ref!$Y$13:$AC$18,2,FALSE),$P29),INDIRECT(T$6&VLOOKUP(Summary,Ref!$Y$13:$AC$18,4,FALSE)),0),VLOOKUP(T$10,Ref!$Y$61:$AA$63,2,FALSE)),0)))} -> #REF! | U29: {=IF($P29="","",IF(U$11="",0,IFERROR(INDEX(INDIRECT(U$6&VLOOKUP(Summary,Ref!$Y$13:$AC$18,3,FALSE)),MATCH(IF($P29="At Issue",VLOOKUP(Summary,Ref!$Y$13:$AC$18,2,FALSE),$P29),INDIRECT(U$6&VLOOKUP(Summary,Ref!$Y$13:$AC$18,4,FALSE)),0),VLOOKUP(U$10,Ref!$Y$61:$AA$63,2,FALSE)),0)))} -> #REF! | V29: {=IF($P29="","",IF(V$11="",0,IFERROR(INDEX(INDIRECT(V$6&VLOOKUP(Summary,Ref!$Y$13:$AC$18,3,FALSE)),MATCH(IF($P29="At Issue",VLOOKUP(Summary,Ref!$Y$13:$AC$18,2,FALSE),$P29),INDIRECT(V$6&VLOOKUP(Summary,Ref!$Y$13:$AC$18,4,FALSE)),0),VLOOKUP(V$10,Ref!$Y$61:$AA$63,2,FALSE)),0)))} -> #REF! | W29: {=IF($P29="","",IF(W$11="",0,IFERROR(INDEX(INDIRECT(W$6&VLOOKUP(Summary,Ref!$Y$13:$AC$18,3,FALSE)),MATCH(IF($P29="At Issue",VLOOKUP(Summary,Ref!$Y$13:$AC$18,2,FALSE),$P29),INDIRECT(W$6&VLOOKUP(Summary,Ref!$Y$13:$AC$18,4,FALSE)),0),VLOOKUP(W$10,Ref!$Y$61:$AA$63,2,FALSE)),0)))} -> #REF! | X29: =IF($P29="","",'Inputs & Summary'!S27) -> #REF! | Y29: =IF($P29="","",'Inputs & Summary'!T27) -> #REF! | Z29: =IF($P29="","",IF($Z$11="",0,'Inputs & Summary'!X27)) -> #REF! | AA29: =IF($P29="","",IF($AA$11="",0,IF(AND(LivBen<>"None",RIGHT(Category,2)<>"NY"),'Inputs & Summary'!AH27,""))) -> #REF! | AB29: =IF($P29="","",'Inputs & Summary'!Y27) -> #REF! | AC29: =IF($P29="","",IF(RIGHT(Category,2)="NY",'Inputs & Summary'!AH27,SUM('Inputs & Summary'!AB27,'Inputs & Summary'!AE27*('Inputs & Summary'!AD27="Yes"),'Inputs & Summary'!AG27))) -> #REF! | AD29: =IF($P29="","",'Inputs & Summary'!AI27) -> #REF! | AE29: =IF($P29="","",'Inputs & Summary'!Z27) -> #REF! | AF29: =IF($P29="","",'Inputs & Summary'!U27) -> #REF! | AG29: =IF($P29="","",'Inputs & Summary'!V27) -> #REF! | AH29: =IF($P29="","",'Inputs & Summary'!W27) -> #REF! | AI29: =IF($P29="","",IF($AI$11="",0,'Inputs & Summary'!AM27)) -> #REF! | AJ29: =IF($P29="","",IF($AJ$11="",0,IF(PTab="P7",'Inputs & Summary'!AQ27,'Inputs & Summary'!AA27))) -> #REF! | AK29: =IF($P29="","",'Inputs & Summary'!AJ27) -> #REF!
E30: =IF(SUM('Inputs & Summary'!$E$109:$E$137)=1,"Selected Check-a-Box Distribution","") -> Selected Check-a-Box Distribution | P30: =IF('Inputs & Summary'!O28="","",IF('Inputs & Summary'!O28=0,"At Issue",'Inputs & Summary'!P28)) -> #REF! | Q30: =IF($P30="","",'Inputs & Summary'!O28) -> #REF! | R30: =IF($P30="","",'Inputs & Summary'!Q28) -> #REF! | S30: {=IF($P30="","",IF(S$11="",0,IFERROR(INDEX(INDIRECT(S$6&VLOOKUP(Summary,Ref!$Y$13:$AC$18,3,FALSE)),MATCH(IF($P30="At Issue",VLOOKUP(Summary,Ref!$Y$13:$AC$18,2,FALSE),$P30),INDIRECT(S$6&VLOOKUP(Summary,Ref!$Y$13:$AC$18,4,FALSE)),0),VLOOKUP(S$10,Ref!$Y$61:$AA$63,2,FALSE)),0)))} -> #REF! | T30: {=IF($P30="","",IF(T$11="",0,IFERROR(INDEX(INDIRECT(T$6&VLOOKUP(Summary,Ref!$Y$13:$AC$18,3,FALSE)),MATCH(IF($P30="At Issue",VLOOKUP(Summary,Ref!$Y$13:$AC$18,2,FALSE),$P30),INDIRECT(T$6&VLOOKUP(Summary,Ref!$Y$13:$AC$18,4,FALSE)),0),VLOOKUP(T$10,Ref!$Y$61:$AA$63,2,FALSE)),0)))} -> #REF! | U30: {=IF($P30="","",IF(U$11="",0,IFERROR(INDEX(INDIRECT(U$6&VLOOKUP(Summary,Ref!$Y$13:$AC$18,3,FALSE)),MATCH(IF($P30="At Issue",VLOOKUP(Summary,Ref!$Y$13:$AC$18,2,FALSE),$P30),INDIRECT(U$6&VLOOKUP(Summary,Ref!$Y$13:$AC$18,4,FALSE)),0),VLOOKUP(U$10,Ref!$Y$61:$AA$63,2,FALSE)),0)))} -> #REF! | V30: {=IF($P30="","",IF(V$11="",0,IFERROR(INDEX(INDIRECT(V$6&VLOOKUP(Summary,Ref!$Y$13:$AC$18,3,FALSE)),MATCH(IF($P30="At Issue",VLOOKUP(Summary,Ref!$Y$13:$AC$18,2,FALSE),$P30),INDIRECT(V$6&VLOOKUP(Summary,Ref!$Y$13:$AC$18,4,FALSE)),0),VLOOKUP(V$10,Ref!$Y$61:$AA$63,2,FALSE)),0)))} -> #REF! | W30: {=IF($P30="","",IF(W$11="",0,IFERROR(INDEX(INDIRECT(W$6&VLOOKUP(Summary,Ref!$Y$13:$AC$18,3,FALSE)),MATCH(IF($P30="At Issue",VLOOKUP(Summary,Ref!$Y$13:$AC$18,2,FALSE),$P30),INDIRECT(W$6&VLOOKUP(Summary,Ref!$Y$13:$AC$18,4,FALSE)),0),VLOOKUP(W$10,Ref!$Y$61:$AA$63,2,FALSE)),0)))} -> #REF! | X30: =IF($P30="","",'Inputs & Summary'!S28) -> #REF! | Y30: =IF($P30="","",'Inputs & Summary'!T28) -> #REF! | Z30: =IF($P30="","",IF($Z$11="",0,'Inputs & Summary'!X28)) -> #REF! | AA30: =IF($P30="","",IF($AA$11="",0,IF(AND(LivBen<>"None",RIGHT(Category,2)<>"NY"),'Inputs & Summary'!AH28,""))) -> #REF! | AB30: =IF($P30="","",'Inputs & Summary'!Y28) -> #REF! | AC30: =IF($P30="","",IF(RIGHT(Category,2)="NY",'Inputs & Summary'!AH28,SUM('Inputs & Summary'!AB28,'Inputs & Summary'!AE28*('Inputs & Summary'!AD28="Yes"),'Inputs & Summary'!AG28))) -> #REF! | AD30: =IF($P30="","",'Inputs & Summary'!AI28) -> #REF! | AE30: =IF($P30="","",'Inputs & Summary'!Z28) -> #REF! | AF30: =IF($P30="","",'Inputs & Summary'!U28) -> #REF! | AG30: =IF($P30="","",'Inputs & Summary'!V28) -> #REF! | AH30: =IF($P30="","",'Inputs & Summary'!W28) -> #REF! | AI30: =IF($P30="","",IF($AI$11="",0,'Inputs & Summary'!AM28)) -> #REF! | AJ30: =IF($P30="","",IF($AJ$11="",0,IF(PTab="P7",'Inputs & Summary'!AQ28,'Inputs & Summary'!AA28))) -> #REF! | AK30: =IF($P30="","",'Inputs & Summary'!AJ28) -> #REF!
P31: =IF('Inputs & Summary'!O29="","",IF('Inputs & Summary'!O29=0,"At Issue",'Inputs & Summary'!P29)) -> #REF! | Q31: =IF($P31="","",'Inputs & Summary'!O29) -> #REF! | R31: =IF($P31="","",'Inputs & Summary'!Q29) -> #REF! | S31: {=IF($P31="","",IF(S$11="",0,IFERROR(INDEX(INDIRECT(S$6&VLOOKUP(Summary,Ref!$Y$13:$AC$18,3,FALSE)),MATCH(IF($P31="At Issue",VLOOKUP(Summary,Ref!$Y$13:$AC$18,2,FALSE),$P31),INDIRECT(S$6&VLOOKUP(Summary,Ref!$Y$13:$AC$18,4,FALSE)),0),VLOOKUP(S$10,Ref!$Y$61:$AA$63,2,FALSE)),0)))} -> #REF! | T31: {=IF($P31="","",IF(T$11="",0,IFERROR(INDEX(INDIRECT(T$6&VLOOKUP(Summary,Ref!$Y$13:$AC$18,3,FALSE)),MATCH(IF($P31="At Issue",VLOOKUP(Summary,Ref!$Y$13:$AC$18,2,FALSE),$P31),INDIRECT(T$6&VLOOKUP(Summary,Ref!$Y$13:$AC$18,4,FALSE)),0),VLOOKUP(T$10,Ref!$Y$61:$AA$63,2,FALSE)),0)))} -> #REF! | U31: {=IF($P31="","",IF(U$11="",0,IFERROR(INDEX(INDIRECT(U$6&VLOOKUP(Summary,Ref!$Y$13:$AC$18,3,FALSE)),MATCH(IF($P31="At Issue",VLOOKUP(Summary,Ref!$Y$13:$AC$18,2,FALSE),$P31),INDIRECT(U$6&VLOOKUP(Summary,Ref!$Y$13:$AC$18,4,FALSE)),0),VLOOKUP(U$10,Ref!$Y$61:$AA$63,2,FALSE)),0)))} -> #REF! | V31: {=IF($P31="","",IF(V$11="",0,IFERROR(INDEX(INDIRECT(V$6&VLOOKUP(Summary,Ref!$Y$13:$AC$18,3,FALSE)),MATCH(IF($P31="At Issue",VLOOKUP(Summary,Ref!$Y$13:$AC$18,2,FALSE),$P31),INDIRECT(V$6&VLOOKUP(Summary,Ref!$Y$13:$AC$18,4,FALSE)),0),VLOOKUP(V$10,Ref!$Y$61:$AA$63,2,FALSE)),0)))} -> #REF! | W31: {=IF($P31="","",IF(W$11="",0,IFERROR(INDEX(INDIRECT(W$6&VLOOKUP(Summary,Ref!$Y$13:$AC$18,3,FALSE)),MATCH(IF($P31="At Issue",VLOOKUP(Summary,Ref!$Y$13:$AC$18,2,FALSE),$P31),INDIRECT(W$6&VLOOKUP(Summary,Ref!$Y$13:$AC$18,4,FALSE)),0),VLOOKUP(W$10,Ref!$Y$61:$AA$63,2,FALSE)),0)))} -> #REF! | X31: =IF($P31="","",'Inputs & Summary'!S29) -> #REF! | Y31: =IF($P31="","",'Inputs & Summary'!T29) -> #REF! | Z31: =IF($P31="","",IF($Z$11="",0,'Inputs & Summary'!X29)) -> #REF! | AA31: =IF($P31="","",IF($AA$11="",0,IF(AND(LivBen<>"None",RIGHT(Category,2)<>"NY"),'Inputs & Summary'!AH29,""))) -> #REF! | AB31: =IF($P31="","",'Inputs & Summary'!Y29) -> #REF! | AC31: =IF($P31="","",IF(RIGHT(Category,2)="NY",'Inputs & Summary'!AH29,SUM('Inputs & Summary'!AB29,'Inputs & Summary'!AE29*('Inputs & Summary'!AD29="Yes"),'Inputs & Summary'!AG29))) -> #REF! | AD31: =IF($P31="","",'Inputs & Summary'!AI29) -> #REF! | AE31: =IF($P31="","",'Inputs & Summary'!Z29) -> #REF! | AF31: =IF($P31="","",'Inputs & Summary'!U29) -> #REF! | AG31: =IF($P31="","",'Inputs & Summary'!V29) -> #REF! | AH31: =IF($P31="","",'Inputs & Summary'!W29) -> #REF! | AI31: =IF($P31="","",IF($AI$11="",0,'Inputs & Summary'!AM29)) -> #REF! | AJ31: =IF($P31="","",IF($AJ$11="",0,IF(PTab="P7",'Inputs & Summary'!AQ29,'Inputs & Summary'!AA29))) -> #REF! | AK31: =IF($P31="","",'Inputs & Summary'!AJ29) -> #REF!
P32: =IF('Inputs & Summary'!O30="","",IF('Inputs & Summary'!O30=0,"At Issue",'Inputs & Summary'!P30)) -> #REF! | Q32: =IF($P32="","",'Inputs & Summary'!O30) -> #REF! | R32: =IF($P32="","",'Inputs & Summary'!Q30) -> #REF! | S32: {=IF($P32="","",IF(S$11="",0,IFERROR(INDEX(INDIRECT(S$6&VLOOKUP(Summary,Ref!$Y$13:$AC$18,3,FALSE)),MATCH(IF($P32="At Issue",VLOOKUP(Summary,Ref!$Y$13:$AC$18,2,FALSE),$P32),INDIRECT(S$6&VLOOKUP(Summary,Ref!$Y$13:$AC$18,4,FALSE)),0),VLOOKUP(S$10,Ref!$Y$61:$AA$63,2,FALSE)),0)))} -> #REF! | T32: {=IF($P32="","",IF(T$11="",0,IFERROR(INDEX(INDIRECT(T$6&VLOOKUP(Summary,Ref!$Y$13:$AC$18,3,FALSE)),MATCH(IF($P32="At Issue",VLOOKUP(Summary,Ref!$Y$13:$AC$18,2,FALSE),$P32),INDIRECT(T$6&VLOOKUP(Summary,Ref!$Y$13:$AC$18,4,FALSE)),0),VLOOKUP(T$10,Ref!$Y$61:$AA$63,2,FALSE)),0)))} -> #REF! | U32: {=IF($P32="","",IF(U$11="",0,IFERROR(INDEX(INDIRECT(U$6&VLOOKUP(Summary,Ref!$Y$13:$AC$18,3,FALSE)),MATCH(IF($P32="At Issue",VLOOKUP(Summary,Ref!$Y$13:$AC$18,2,FALSE),$P32),INDIRECT(U$6&VLOOKUP(Summary,Ref!$Y$13:$AC$18,4,FALSE)),0),VLOOKUP(U$10,Ref!$Y$61:$AA$63,2,FALSE)),0)))} -> #REF! | V32: {=IF($P32="","",IF(V$11="",0,IFERROR(INDEX(INDIRECT(V$6&VLOOKUP(Summary,Ref!$Y$13:$AC$18,3,FALSE)),MATCH(IF($P32="At Issue",VLOOKUP(Summary,Ref!$Y$13:$AC$18,2,FALSE),$P32),INDIRECT(V$6&VLOOKUP(Summary,Ref!$Y$13:$AC$18,4,FALSE)),0),VLOOKUP(V$10,Ref!$Y$61:$AA$63,2,FALSE)),0)))} -> #REF! | W32: {=IF($P32="","",IF(W$11="",0,IFERROR(INDEX(INDIRECT(W$6&VLOOKUP(Summary,Ref!$Y$13:$AC$18,3,FALSE)),MATCH(IF($P32="At Issue",VLOOKUP(Summary,Ref!$Y$13:$AC$18,2,FALSE),$P32),INDIRECT(W$6&VLOOKUP(Summary,Ref!$Y$13:$AC$18,4,FALSE)),0),VLOOKUP(W$10,Ref!$Y$61:$AA$63,2,FALSE)),0)))} -> #REF! | X32: =IF($P32="","",'Inputs & Summary'!S30) -> #REF! | Y32: =IF($P32="","",'Inputs & Summary'!T30) -> #REF! | Z32: =IF($P32="","",IF($Z$11="",0,'Inputs & Summary'!X30)) -> #REF! | AA32: =IF($P32="","",IF($AA$11="",0,IF(AND(LivBen<>"None",RIGHT(Category,2)<>"NY"),'Inputs & Summary'!AH30,""))) -> #REF! | AB32: =IF($P32="","",'Inputs & Summary'!Y30) -> #REF! | AC32: =IF($P32="","",IF(RIGHT(Category,2)="NY",'Inputs & Summary'!AH30,SUM('Inputs & Summary'!AB30,'Inputs & Summary'!AE30*('Inputs & Summary'!AD30="Yes"),'Inputs & Summary'!AG30))) -> #REF! | AD32: =IF($P32="","",'Inputs & Summary'!AI30) -> #REF! | AE32: =IF($P32="","",'Inputs & Summary'!Z30) -> #REF! | AF32: =IF($P32="","",'Inputs & Summary'!U30) -> #REF! | AG32: =IF($P32="","",'Inputs & Summary'!V30) -> #REF! | AH32: =IF($P32="","",'Inputs & Summary'!W30) -> #REF! | AI32: =IF($P32="","",IF($AI$11="",0,'Inputs & Summary'!AM30)) -> #REF! | AJ32: =IF($P32="","",IF($AJ$11="",0,IF(PTab="P7",'Inputs & Summary'!AQ30,'Inputs & Summary'!AA30))) -> #REF! | AK32: =IF($P32="","",'Inputs & Summary'!AJ30) -> #REF!
E33: {=IF(SUM('Inputs & Summary'!$E$109:$E$137)=1,_xlfn.ANCHORARRAY(E10),"")} -> 1-Year Fixed Rate, Fixed Account | F33: =IF(AND(SUM('Inputs & Summary'!$E$109:$E$137)=1,E33<>""),INDEX($L$10:$L$19,MATCH(E33,$E$10:$E$19,0),1),NA()) -> 0.1 | P33: =IF('Inputs & Summary'!O31="","",IF('Inputs & Summary'!O31=0,"At Issue",'Inputs & Summary'!P31)) -> #REF! | Q33: =IF($P33="","",'Inputs & Summary'!O31) -> #REF! | R33: =IF($P33="","",'Inputs & Summary'!Q31) -> #REF! | S33: {=IF($P33="","",IF(S$11="",0,IFERROR(INDEX(INDIRECT(S$6&VLOOKUP(Summary,Ref!$Y$13:$AC$18,3,FALSE)),MATCH(IF($P33="At Issue",VLOOKUP(Summary,Ref!$Y$13:$AC$18,2,FALSE),$P33),INDIRECT(S$6&VLOOKUP(Summary,Ref!$Y$13:$AC$18,4,FALSE)),0),VLOOKUP(S$10,Ref!$Y$61:$AA$63,2,FALSE)),0)))} -> #REF! | T33: {=IF($P33="","",IF(T$11="",0,IFERROR(INDEX(INDIRECT(T$6&VLOOKUP(Summary,Ref!$Y$13:$AC$18,3,FALSE)),MATCH(IF($P33="At Issue",VLOOKUP(Summary,Ref!$Y$13:$AC$18,2,FALSE),$P33),INDIRECT(T$6&VLOOKUP(Summary,Ref!$Y$13:$AC$18,4,FALSE)),0),VLOOKUP(T$10,Ref!$Y$61:$AA$63,2,FALSE)),0)))} -> #REF! | U33: {=IF($P33="","",IF(U$11="",0,IFERROR(INDEX(INDIRECT(U$6&VLOOKUP(Summary,Ref!$Y$13:$AC$18,3,FALSE)),MATCH(IF($P33="At Issue",VLOOKUP(Summary,Ref!$Y$13:$AC$18,2,FALSE),$P33),INDIRECT(U$6&VLOOKUP(Summary,Ref!$Y$13:$AC$18,4,FALSE)),0),VLOOKUP(U$10,Ref!$Y$61:$AA$63,2,FALSE)),0)))} -> #REF! | V33: {=IF($P33="","",IF(V$11="",0,IFERROR(INDEX(INDIRECT(V$6&VLOOKUP(Summary,Ref!$Y$13:$AC$18,3,FALSE)),MATCH(IF($P33="At Issue",VLOOKUP(Summary,Ref!$Y$13:$AC$18,2,FALSE),$P33),INDIRECT(V$6&VLOOKUP(Summary,Ref!$Y$13:$AC$18,4,FALSE)),0),VLOOKUP(V$10,Ref!$Y$61:$AA$63,2,FALSE)),0)))} -> #REF! | W33: {=IF($P33="","",IF(W$11="",0,IFERROR(INDEX(INDIRECT(W$6&VLOOKUP(Summary,Ref!$Y$13:$AC$18,3,FALSE)),MATCH(IF($P33="At Issue",VLOOKUP(Summary,Ref!$Y$13:$AC$18,2,FALSE),$P33),INDIRECT(W$6&VLOOKUP(Summary,Ref!$Y$13:$AC$18,4,FALSE)),0),VLOOKUP(W$10,Ref!$Y$61:$AA$63,2,FALSE)),0)))} -> #REF! | X33: =IF($P33="","",'Inputs & Summary'!S31) -> #REF! | Y33: =IF($P33="","",'Inputs & Summary'!T31) -> #REF! | Z33: =IF($P33="","",IF($Z$11="",0,'Inputs & Summary'!X31)) -> #REF! | AA33: =IF($P33="","",IF($AA$11="",0,IF(AND(LivBen<>"None",RIGHT(Category,2)<>"NY"),'Inputs & Summary'!AH31,""))) -> #REF! | AB33: =IF($P33="","",'Inputs & Summary'!Y31) -> #REF! | AC33: =IF($P33="","",IF(RIGHT(Category,2)="NY",'Inputs & Summary'!AH31,SUM('Inputs & Summary'!AB31,'Inputs & Summary'!AE31*('Inputs & Summary'!AD31="Yes"),'Inputs & Summary'!AG31))) -> #REF! | AD33: =IF($P33="","",'Inputs & Summary'!AI31) -> #REF! | AE33: =IF($P33="","",'Inputs & Summary'!Z31) -> #REF! | AF33: =IF($P33="","",'Inputs & Summary'!U31) -> #REF! | AG33: =IF($P33="","",'Inputs & Summary'!V31) -> #REF! | AH33: =IF($P33="","",'Inputs & Summary'!W31) -> #REF! | AI33: =IF($P33="","",IF($AI$11="",0,'Inputs & Summary'!AM31)) -> #REF! | AJ33: =IF($P33="","",IF($AJ$11="",0,IF(PTab="P7",'Inputs & Summary'!AQ31,'Inputs & Summary'!AA31))) -> #REF! | AK33: =IF($P33="","",'Inputs & Summary'!AJ31) -> #REF!
E34: 1-Year PTP with Secure Cap, S&P 500 | F34: =IF(AND(SUM('Inputs & Summary'!$E$109:$E$137)=1,E34<>""),INDEX($L$10:$L$19,MATCH(E34,$E$10:$E$19,0),1),NA()) -> 0.4 | P34: =IF('Inputs & Summary'!O32="","",IF('Inputs & Summary'!O32=0,"At Issue",'Inputs & Summary'!P32)) -> #REF! | Q34: =IF($P34="","",'Inputs & Summary'!O32) -> #REF! | R34: =IF($P34="","",'Inputs & Summary'!Q32) -> #REF! | S34: {=IF($P34="","",IF(S$11="",0,IFERROR(INDEX(INDIRECT(S$6&VLOOKUP(Summary,Ref!$Y$13:$AC$18,3,FALSE)),MATCH(IF($P34="At Issue",VLOOKUP(Summary,Ref!$Y$13:$AC$18,2,FALSE),$P34),INDIRECT(S$6&VLOOKUP(Summary,Ref!$Y$13:$AC$18,4,FALSE)),0),VLOOKUP(S$10,Ref!$Y$61:$AA$63,2,FALSE)),0)))} -> #REF! | T34: {=IF($P34="","",IF(T$11="",0,IFERROR(INDEX(INDIRECT(T$6&VLOOKUP(Summary,Ref!$Y$13:$AC$18,3,FALSE)),MATCH(IF($P34="At Issue",VLOOKUP(Summary,Ref!$Y$13:$AC$18,2,FALSE),$P34),INDIRECT(T$6&VLOOKUP(Summary,Ref!$Y$13:$AC$18,4,FALSE)),0),VLOOKUP(T$10,Ref!$Y$61:$AA$63,2,FALSE)),0)))} -> #REF! | U34: {=IF($P34="","",IF(U$11="",0,IFERROR(INDEX(INDIRECT(U$6&VLOOKUP(Summary,Ref!$Y$13:$AC$18,3,FALSE)),MATCH(IF($P34="At Issue",VLOOKUP(Summary,Ref!$Y$13:$AC$18,2,FALSE),$P34),INDIRECT(U$6&VLOOKUP(Summary,Ref!$Y$13:$AC$18,4,FALSE)),0),VLOOKUP(U$10,Ref!$Y$61:$AA$63,2,FALSE)),0)))} -> #REF! | V34: {=IF($P34="","",IF(V$11="",0,IFERROR(INDEX(INDIRECT(V$6&VLOOKUP(Summary,Ref!$Y$13:$AC$18,3,FALSE)),MATCH(IF($P34="At Issue",VLOOKUP(Summary,Ref!$Y$13:$AC$18,2,FALSE),$P34),INDIRECT(V$6&VLOOKUP(Summary,Ref!$Y$13:$AC$18,4,FALSE)),0),VLOOKUP(V$10,Ref!$Y$61:$AA$63,2,FALSE)),0)))} -> #REF! | W34: {=IF($P34="","",IF(W$11="",0,IFERROR(INDEX(INDIRECT(W$6&VLOOKUP(Summary,Ref!$Y$13:$AC$18,3,FALSE)),MATCH(IF($P34="At Issue",VLOOKUP(Summary,Ref!$Y$13:$AC$18,2,FALSE),$P34),INDIRECT(W$6&VLOOKUP(Summary,Ref!$Y$13:$AC$18,4,FALSE)),0),VLOOKUP(W$10,Ref!$Y$61:$AA$63,2,FALSE)),0)))} -> #REF! | X34: =IF($P34="","",'Inputs & Summary'!S32) -> #REF! | Y34: =IF($P34="","",'Inputs & Summary'!T32) -> #REF! | Z34: =IF($P34="","",IF($Z$11="",0,'Inputs & Summary'!X32)) -> #REF! | AA34: =IF($P34="","",IF($AA$11="",0,IF(AND(LivBen<>"None",RIGHT(Category,2)<>"NY"),'Inputs & Summary'!AH32,""))) -> #REF! | AB34: =IF($P34="","",'Inputs & Summary'!Y32) -> #REF! | AC34: =IF($P34="","",IF(RIGHT(Category,2)="NY",'Inputs & Summary'!AH32,SUM('Inputs & Summary'!AB32,'Inputs & Summary'!AE32*('Inputs & Summary'!AD32="Yes"),'Inputs & Summary'!AG32))) -> #REF! | AD34: =IF($P34="","",'Inputs & Summary'!AI32) -> #REF! | AE34: =IF($P34="","",'Inputs & Summary'!Z32) -> #REF! | AF34: =IF($P34="","",'Inputs & Summary'!U32) -> #REF! | AG34: =IF($P34="","",'Inputs & Summary'!V32) -> #REF! | AH34: =IF($P34="","",'Inputs & Summary'!W32) -> #REF! | AI34: =IF($P34="","",IF($AI$11="",0,'Inputs & Summary'!AM32)) -> #REF! | AJ34: =IF($P34="","",IF($AJ$11="",0,IF(PTab="P7",'Inputs & Summary'!AQ32,'Inputs & Summary'!AA32))) -> #REF! | AK34: =IF($P34="","",'Inputs & Summary'!AJ32) -> #REF!
E35: 1-Year PTP with Cap, PIMCO Global Optima | F35: =IF(AND(SUM('Inputs & Summary'!$E$109:$E$137)=1,E35<>""),INDEX($L$10:$L$19,MATCH(E35,$E$10:$E$19,0),1),NA()) -> 0.1 | P35: =IF('Inputs & Summary'!O33="","",IF('Inputs & Summary'!O33=0,"At Issue",'Inputs & Summary'!P33)) -> #REF! | Q35: =IF($P35="","",'Inputs & Summary'!O33) -> #REF! | R35: =IF($P35="","",'Inputs & Summary'!Q33) -> #REF! | S35: {=IF($P35="","",IF(S$11="",0,IFERROR(INDEX(INDIRECT(S$6&VLOOKUP(Summary,Ref!$Y$13:$AC$18,3,FALSE)),MATCH(IF($P35="At Issue",VLOOKUP(Summary,Ref!$Y$13:$AC$18,2,FALSE),$P35),INDIRECT(S$6&VLOOKUP(Summary,Ref!$Y$13:$AC$18,4,FALSE)),0),VLOOKUP(S$10,Ref!$Y$61:$AA$63,2,FALSE)),0)))} -> #REF! | T35: {=IF($P35="","",IF(T$11="",0,IFERROR(INDEX(INDIRECT(T$6&VLOOKUP(Summary,Ref!$Y$13:$AC$18,3,FALSE)),MATCH(IF($P35="At Issue",VLOOKUP(Summary,Ref!$Y$13:$AC$18,2,FALSE),$P35),INDIRECT(T$6&VLOOKUP(Summary,Ref!$Y$13:$AC$18,4,FALSE)),0),VLOOKUP(T$10,Ref!$Y$61:$AA$63,2,FALSE)),0)))} -> #REF! | U35: {=IF($P35="","",IF(U$11="",0,IFERROR(INDEX(INDIRECT(U$6&VLOOKUP(Summary,Ref!$Y$13:$AC$18,3,FALSE)),MATCH(IF($P35="At Issue",VLOOKUP(Summary,Ref!$Y$13:$AC$18,2,FALSE),$P35),INDIRECT(U$6&VLOOKUP(Summary,Ref!$Y$13:$AC$18,4,FALSE)),0),VLOOKUP(U$10,Ref!$Y$61:$AA$63,2,FALSE)),0)))} -> #REF! | V35: {=IF($P35="","",IF(V$11="",0,IFERROR(INDEX(INDIRECT(V$6&VLOOKUP(Summary,Ref!$Y$13:$AC$18,3,FALSE)),MATCH(IF($P35="At Issue",VLOOKUP(Summary,Ref!$Y$13:$AC$18,2,FALSE),$P35),INDIRECT(V$6&VLOOKUP(Summary,Ref!$Y$13:$AC$18,4,FALSE)),0),VLOOKUP(V$10,Ref!$Y$61:$AA$63,2,FALSE)),0)))} -> #REF! | W35: {=IF($P35="","",IF(W$11="",0,IFERROR(INDEX(INDIRECT(W$6&VLOOKUP(Summary,Ref!$Y$13:$AC$18,3,FALSE)),MATCH(IF($P35="At Issue",VLOOKUP(Summary,Ref!$Y$13:$AC$18,2,FALSE),$P35),INDIRECT(W$6&VLOOKUP(Summary,Ref!$Y$13:$AC$18,4,FALSE)),0),VLOOKUP(W$10,Ref!$Y$61:$AA$63,2,FALSE)),0)))} -> #REF! | X35: =IF($P35="","",'Inputs & Summary'!S33) -> #REF! | Y35: =IF($P35="","",'Inputs & Summary'!T33) -> #REF! | Z35: =IF($P35="","",IF($Z$11="",0,'Inputs & Summary'!X33)) -> #REF! | AA35: =IF($P35="","",IF($AA$11="",0,IF(AND(LivBen<>"None",RIGHT(Category,2)<>"NY"),'Inputs & Summary'!AH33,""))) -> #REF! | AB35: =IF($P35="","",'Inputs & Summary'!Y33) -> #REF! | AC35: =IF($P35="","",IF(RIGHT(Category,2)="NY",'Inputs & Summary'!AH33,SUM('Inputs & Summary'!AB33,'Inputs & Summary'!AE33*('Inputs & Summary'!AD33="Yes"),'Inputs & Summary'!AG33))) -> #REF! | AD35: =IF($P35="","",'Inputs & Summary'!AI33) -> #REF! | AE35: =IF($P35="","",'Inputs & Summary'!Z33) -> #REF! | AF35: =IF($P35="","",'Inputs & Summary'!U33) -> #REF! | AG35: =IF($P35="","",'Inputs & Summary'!V33) -> #REF! | AH35: =IF($P35="","",'Inputs & Summary'!W33) -> #REF! | AI35: =IF($P35="","",IF($AI$11="",0,'Inputs & Summary'!AM33)) -> #REF! | AJ35: =IF($P35="","",IF($AJ$11="",0,IF(PTab="P7",'Inputs & Summary'!AQ33,'Inputs & Summary'!AA33))) -> #REF! | AK35: =IF($P35="","",'Inputs & Summary'!AJ33) -> #REF!
E36: 1-Year PTP with ParRate, MLSB | F36: =IF(AND(SUM('Inputs & Summary'!$E$109:$E$137)=1,E36<>""),INDEX($L$10:$L$19,MATCH(E36,$E$10:$E$19,0),1),NA()) -> 0.4 | P36: =IF('Inputs & Summary'!O34="","",IF('Inputs & Summary'!O34=0,"At Issue",'Inputs & Summary'!P34)) | Q36: =IF($P36="","",'Inputs & Summary'!O34) | R36: =IF($P36="","",'Inputs & Summary'!Q34) | S36: {=IF($P36="","",IF(S$11="",0,IFERROR(INDEX(INDIRECT(S$6&VLOOKUP(Summary,Ref!$Y$13:$AC$18,3,FALSE)),MATCH(IF($P36="At Issue",VLOOKUP(Summary,Ref!$Y$13:$AC$18,2,FALSE),$P36),INDIRECT(S$6&VLOOKUP(Summary,Ref!$Y$13:$AC$18,4,FALSE)),0),VLOOKUP(S$10,Ref!$Y$61:$AA$63,2,FALSE)),0)))} | T36: {=IF($P36="","",IF(T$11="",0,IFERROR(INDEX(INDIRECT(T$6&VLOOKUP(Summary,Ref!$Y$13:$AC$18,3,FALSE)),MATCH(IF($P36="At Issue",VLOOKUP(Summary,Ref!$Y$13:$AC$18,2,FALSE),$P36),INDIRECT(T$6&VLOOKUP(Summary,Ref!$Y$13:$AC$18,4,FALSE)),0),VLOOKUP(T$10,Ref!$Y$61:$AA$63,2,FALSE)),0)))} | U36: {=IF($P36="","",IF(U$11="",0,IFERROR(INDEX(INDIRECT(U$6&VLOOKUP(Summary,Ref!$Y$13:$AC$18,3,FALSE)),MATCH(IF($P36="At Issue",VLOOKUP(Summary,Ref!$Y$13:$AC$18,2,FALSE),$P36),INDIRECT(U$6&VLOOKUP(Summary,Ref!$Y$13:$AC$18,4,FALSE)),0),VLOOKUP(U$10,Ref!$Y$61:$AA$63,2,FALSE)),0)))} | V36: {=IF($P36="","",IF(V$11="",0,IFERROR(INDEX(INDIRECT(V$6&VLOOKUP(Summary,Ref!$Y$13:$AC$18,3,FALSE)),MATCH(IF($P36="At Issue",VLOOKUP(Summary,Ref!$Y$13:$AC$18,2,FALSE),$P36),INDIRECT(V$6&VLOOKUP(Summary,Ref!$Y$13:$AC$18,4,FALSE)),0),VLOOKUP(V$10,Ref!$Y$61:$AA$63,2,FALSE)),0)))} | W36: {=IF($P36="","",IF(W$11="",0,IFERROR(INDEX(INDIRECT(W$6&VLOOKUP(Summary,Ref!$Y$13:$AC$18,3,FALSE)),MATCH(IF($P36="At Issue",VLOOKUP(Summary,Ref!$Y$13:$AC$18,2,FALSE),$P36),INDIRECT(W$6&VLOOKUP(Summary,Ref!$Y$13:$AC$18,4,FALSE)),0),VLOOKUP(W$10,Ref!$Y$61:$AA$63,2,FALSE)),0)))} | X36: =IF($P36="","",'Inputs & Summary'!S34) | Y36: =IF($P36="","",'Inputs & Summary'!T34) | Z36: =IF($P36="","",IF($Z$11="",0,'Inputs & Summary'!X34)) | AA36: =IF($P36="","",IF($AA$11="",0,IF(AND(LivBen<>"None",RIGHT(Category,2)<>"NY"),'Inputs & Summary'!AH34,""))) | AB36: =IF($P36="","",'Inputs & Summary'!Y34) | AC36: =IF($P36="","",IF(RIGHT(Category,2)="NY",'Inputs & Summary'!AH34,SUM('Inputs & Summary'!AB34,'Inputs & Summary'!AE34*('Inputs & Summary'!AD34="Yes"),'Inputs & Summary'!AG34))) | AD36: =IF($P36="","",'Inputs & Summary'!AI34) | AE36: =IF($P36="","",'Inputs & Summary'!Z34) | AF36: =IF($P36="","",'Inputs & Summary'!U34) | AG36: =IF($P36="","",'Inputs & Summary'!V34) | AH36: =IF($P36="","",'Inputs & Summary'!W34) | AI36: =IF($P36="","",IF($AI$11="",0,'Inputs & Summary'!AM34)) | AJ36: =IF($P36="","",IF($AJ$11="",0,IF(PTab="P7",'Inputs & Summary'!AQ34,'Inputs & Summary'!AA34))) | AK36: =IF($P36="","",'Inputs & Summary'!AJ34)
F37: =IF(AND(SUM('Inputs & Summary'!$E$109:$E$137)=1,E37<>""),INDEX($L$10:$L$19,MATCH(E37,$E$10:$E$19,0),1),NA()) -> #N/A | P37: =IF('Inputs & Summary'!O35="","",IF('Inputs & Summary'!O35=0,"At Issue",'Inputs & Summary'!P35)) | Q37: =IF($P37="","",'Inputs & Summary'!O35) | R37: =IF($P37="","",'Inputs & Summary'!Q35) | S37: {=IF($P37="","",IF(S$11="",0,IFERROR(INDEX(INDIRECT(S$6&VLOOKUP(Summary,Ref!$Y$13:$AC$18,3,FALSE)),MATCH(IF($P37="At Issue",VLOOKUP(Summary,Ref!$Y$13:$AC$18,2,FALSE),$P37),INDIRECT(S$6&VLOOKUP(Summary,Ref!$Y$13:$AC$18,4,FALSE)),0),VLOOKUP(S$10,Ref!$Y$61:$AA$63,2,FALSE)),0)))} | T37: {=IF($P37="","",IF(T$11="",0,IFERROR(INDEX(INDIRECT(T$6&VLOOKUP(Summary,Ref!$Y$13:$AC$18,3,FALSE)),MATCH(IF($P37="At Issue",VLOOKUP(Summary,Ref!$Y$13:$AC$18,2,FALSE),$P37),INDIRECT(T$6&VLOOKUP(Summary,Ref!$Y$13:$AC$18,4,FALSE)),0),VLOOKUP(T$10,Ref!$Y$61:$AA$63,2,FALSE)),0)))} | U37: {=IF($P37="","",IF(U$11="",0,IFERROR(INDEX(INDIRECT(U$6&VLOOKUP(Summary,Ref!$Y$13:$AC$18,3,FALSE)),MATCH(IF($P37="At Issue",VLOOKUP(Summary,Ref!$Y$13:$AC$18,2,FALSE),$P37),INDIRECT(U$6&VLOOKUP(Summary,Ref!$Y$13:$AC$18,4,FALSE)),0),VLOOKUP(U$10,Ref!$Y$61:$AA$63,2,FALSE)),0)))} | V37: {=IF($P37="","",IF(V$11="",0,IFERROR(INDEX(INDIRECT(V$6&VLOOKUP(Summary,Ref!$Y$13:$AC$18,3,FALSE)),MATCH(IF($P37="At Issue",VLOOKUP(Summary,Ref!$Y$13:$AC$18,2,FALSE),$P37),INDIRECT(V$6&VLOOKUP(Summary,Ref!$Y$13:$AC$18,4,FALSE)),0),VLOOKUP(V$10,Ref!$Y$61:$AA$63,2,FALSE)),0)))} | W37: {=IF($P37="","",IF(W$11="",0,IFERROR(INDEX(INDIRECT(W$6&VLOOKUP(Summary,Ref!$Y$13:$AC$18,3,FALSE)),MATCH(IF($P37="At Issue",VLOOKUP(Summary,Ref!$Y$13:$AC$18,2,FALSE),$P37),INDIRECT(W$6&VLOOKUP(Summary,Ref!$Y$13:$AC$18,4,FALSE)),0),VLOOKUP(W$10,Ref!$Y$61:$AA$63,2,FALSE)),0)))} | X37: =IF($P37="","",'Inputs & Summary'!S35) | Y37: =IF($P37="","",'Inputs & Summary'!T35) | Z37: =IF($P37="","",IF($Z$11="",0,'Inputs & Summary'!X35)) | AA37: =IF($P37="","",IF($AA$11="",0,IF(AND(LivBen<>"None",RIGHT(Category,2)<>"NY"),'Inputs & Summary'!AH35,""))) | AB37: =IF($P37="","",'Inputs & Summary'!Y35) | AC37: =IF($P37="","",IF(RIGHT(Category,2)="NY",'Inputs & Summary'!AH35,SUM('Inputs & Summary'!AB35,'Inputs & Summary'!AE35*('Inputs & Summary'!AD35="Yes"),'Inputs & Summary'!AG35))) | AD37: =IF($P37="","",'Inputs & Summary'!AI35) | AE37: =IF($P37="","",'Inputs & Summary'!Z35) | AF37: =IF($P37="","",'Inputs & Summary'!U35) | AG37: =IF($P37="","",'Inputs & Summary'!V35) | AH37: =IF($P37="","",'Inputs & Summary'!W35) | AI37: =IF($P37="","",IF($AI$11="",0,'Inputs & Summary'!AM35)) | AJ37: =IF($P37="","",IF($AJ$11="",0,IF(PTab="P7",'Inputs & Summary'!AQ35,'Inputs & Summary'!AA35))) | AK37: =IF($P37="","",'Inputs & Summary'!AJ35)
F38: =IF(AND(SUM('Inputs & Summary'!$E$109:$E$137)=1,E38<>""),INDEX($L$10:$L$19,MATCH(E38,$E$10:$E$19,0),1),NA()) -> #N/A | P38: =IF('Inputs & Summary'!O36="","",IF('Inputs & Summary'!O36=0,"At Issue",'Inputs & Summary'!P36)) | Q38: =IF($P38="","",'Inputs & Summary'!O36) | R38: =IF($P38="","",'Inputs & Summary'!Q36) | S38: {=IF($P38="","",IF(S$11="",0,IFERROR(INDEX(INDIRECT(S$6&VLOOKUP(Summary,Ref!$Y$13:$AC$18,3,FALSE)),MATCH(IF($P38="At Issue",VLOOKUP(Summary,Ref!$Y$13:$AC$18,2,FALSE),$P38),INDIRECT(S$6&VLOOKUP(Summary,Ref!$Y$13:$AC$18,4,FALSE)),0),VLOOKUP(S$10,Ref!$Y$61:$AA$63,2,FALSE)),0)))} | T38: {=IF($P38="","",IF(T$11="",0,IFERROR(INDEX(INDIRECT(T$6&VLOOKUP(Summary,Ref!$Y$13:$AC$18,3,FALSE)),MATCH(IF($P38="At Issue",VLOOKUP(Summary,Ref!$Y$13:$AC$18,2,FALSE),$P38),INDIRECT(T$6&VLOOKUP(Summary,Ref!$Y$13:$AC$18,4,FALSE)),0),VLOOKUP(T$10,Ref!$Y$61:$AA$63,2,FALSE)),0)))} | U38: {=IF($P38="","",IF(U$11="",0,IFERROR(INDEX(INDIRECT(U$6&VLOOKUP(Summary,Ref!$Y$13:$AC$18,3,FALSE)),MATCH(IF($P38="At Issue",VLOOKUP(Summary,Ref!$Y$13:$AC$18,2,FALSE),$P38),INDIRECT(U$6&VLOOKUP(Summary,Ref!$Y$13:$AC$18,4,FALSE)),0),VLOOKUP(U$10,Ref!$Y$61:$AA$63,2,FALSE)),0)))} | V38: {=IF($P38="","",IF(V$11="",0,IFERROR(INDEX(INDIRECT(V$6&VLOOKUP(Summary,Ref!$Y$13:$AC$18,3,FALSE)),MATCH(IF($P38="At Issue",VLOOKUP(Summary,Ref!$Y$13:$AC$18,2,FALSE),$P38),INDIRECT(V$6&VLOOKUP(Summary,Ref!$Y$13:$AC$18,4,FALSE)),0),VLOOKUP(V$10,Ref!$Y$61:$AA$63,2,FALSE)),0)))} | W38: {=IF($P38="","",IF(W$11="",0,IFERROR(INDEX(INDIRECT(W$6&VLOOKUP(Summary,Ref!$Y$13:$AC$18,3,FALSE)),MATCH(IF($P38="At Issue",VLOOKUP(Summary,Ref!$Y$13:$AC$18,2,FALSE),$P38),INDIRECT(W$6&VLOOKUP(Summary,Ref!$Y$13:$AC$18,4,FALSE)),0),VLOOKUP(W$10,Ref!$Y$61:$AA$63,2,FALSE)),0)))} | X38: =IF($P38="","",'Inputs & Summary'!S36) | Y38: =IF($P38="","",'Inputs & Summary'!T36) | Z38: =IF($P38="","",IF($Z$11="",0,'Inputs & Summary'!X36)) | AA38: =IF($P38="","",IF($AA$11="",0,IF(AND(LivBen<>"None",RIGHT(Category,2)<>"NY"),'Inputs & Summary'!AH36,""))) | AB38: =IF($P38="","",'Inputs & Summary'!Y36) | AC38: =IF($P38="","",IF(RIGHT(Category,2)="NY",'Inputs & Summary'!AH36,SUM('Inputs & Summary'!AB36,'Inputs & Summary'!AE36*('Inputs & Summary'!AD36="Yes"),'Inputs & Summary'!AG36))) | AD38: =IF($P38="","",'Inputs & Summary'!AI36) | AE38: =IF($P38="","",'Inputs & Summary'!Z36) | AF38: =IF($P38="","",'Inputs & Summary'!U36) | AG38: =IF($P38="","",'Inputs & Summary'!V36) | AH38: =IF($P38="","",'Inputs & Summary'!W36) | AI38: =IF($P38="","",IF($AI$11="",0,'Inputs & Summary'!AM36)) | AJ38: =IF($P38="","",IF($AJ$11="",0,IF(PTab="P7",'Inputs & Summary'!AQ36,'Inputs & Summary'!AA36))) | AK38: =IF($P38="","",'Inputs & Summary'!AJ36)
F39: =IF(AND(SUM('Inputs & Summary'!$E$109:$E$137)=1,E39<>""),INDEX($L$10:$L$19,MATCH(E39,$E$10:$E$19,0),1),NA()) -> #N/A | P39: =IF('Inputs & Summary'!O37="","",IF('Inputs & Summary'!O37=0,"At Issue",'Inputs & Summary'!P37)) | Q39: =IF($P39="","",'Inputs & Summary'!O37) | R39: =IF($P39="","",'Inputs & Summary'!Q37) | S39: {=IF($P39="","",IF(S$11="",0,IFERROR(INDEX(INDIRECT(S$6&VLOOKUP(Summary,Ref!$Y$13:$AC$18,3,FALSE)),MATCH(IF($P39="At Issue",VLOOKUP(Summary,Ref!$Y$13:$AC$18,2,FALSE),$P39),INDIRECT(S$6&VLOOKUP(Summary,Ref!$Y$13:$AC$18,4,FALSE)),0),VLOOKUP(S$10,Ref!$Y$61:$AA$63,2,FALSE)),0)))} | T39: {=IF($P39="","",IF(T$11="",0,IFERROR(INDEX(INDIRECT(T$6&VLOOKUP(Summary,Ref!$Y$13:$AC$18,3,FALSE)),MATCH(IF($P39="At Issue",VLOOKUP(Summary,Ref!$Y$13:$AC$18,2,FALSE),$P39),INDIRECT(T$6&VLOOKUP(Summary,Ref!$Y$13:$AC$18,4,FALSE)),0),VLOOKUP(T$10,Ref!$Y$61:$AA$63,2,FALSE)),0)))} | U39: {=IF($P39="","",IF(U$11="",0,IFERROR(INDEX(INDIRECT(U$6&VLOOKUP(Summary,Ref!$Y$13:$AC$18,3,FALSE)),MATCH(IF($P39="At Issue",VLOOKUP(Summary,Ref!$Y$13:$AC$18,2,FALSE),$P39),INDIRECT(U$6&VLOOKUP(Summary,Ref!$Y$13:$AC$18,4,FALSE)),0),VLOOKUP(U$10,Ref!$Y$61:$AA$63,2,FALSE)),0)))} | V39: {=IF($P39="","",IF(V$11="",0,IFERROR(INDEX(INDIRECT(V$6&VLOOKUP(Summary,Ref!$Y$13:$AC$18,3,FALSE)),MATCH(IF($P39="At Issue",VLOOKUP(Summary,Ref!$Y$13:$AC$18,2,FALSE),$P39),INDIRECT(V$6&VLOOKUP(Summary,Ref!$Y$13:$AC$18,4,FALSE)),0),VLOOKUP(V$10,Ref!$Y$61:$AA$63,2,FALSE)),0)))} | W39: {=IF($P39="","",IF(W$11="",0,IFERROR(INDEX(INDIRECT(W$6&VLOOKUP(Summary,Ref!$Y$13:$AC$18,3,FALSE)),MATCH(IF($P39="At Issue",VLOOKUP(Summary,Ref!$Y$13:$AC$18,2,FALSE),$P39),INDIRECT(W$6&VLOOKUP(Summary,Ref!$Y$13:$AC$18,4,FALSE)),0),VLOOKUP(W$10,Ref!$Y$61:$AA$63,2,FALSE)),0)))} | X39: =IF($P39="","",'Inputs & Summary'!S37) | Y39: =IF($P39="","",'Inputs & Summary'!T37) | Z39: =IF($P39="","",IF($Z$11="",0,'Inputs & Summary'!X37)) | AA39: =IF($P39="","",IF($AA$11="",0,IF(AND(LivBen<>"None",RIGHT(Category,2)<>"NY"),'Inputs & Summary'!AH37,""))) | AB39: =IF($P39="","",'Inputs & Summary'!Y37) | AC39: =IF($P39="","",IF(RIGHT(Category,2)="NY",'Inputs & Summary'!AH37,SUM('Inputs & Summary'!AB37,'Inputs & Summary'!AE37*('Inputs & Summary'!AD37="Yes"),'Inputs & Summary'!AG37))) | AD39: =IF($P39="","",'Inputs & Summary'!AI37) | AE39: =IF($P39="","",'Inputs & Summary'!Z37) | AF39: =IF($P39="","",'Inputs & Summary'!U37) | AG39: =IF($P39="","",'Inputs & Summary'!V37) | AH39: =IF($P39="","",'Inputs & Summary'!W37) | AI39: =IF($P39="","",IF($AI$11="",0,'Inputs & Summary'!AM37)) | AJ39: =IF($P39="","",IF($AJ$11="",0,IF(PTab="P7",'Inputs & Summary'!AQ37,'Inputs & Summary'!AA37))) | AK39: =IF($P39="","",'Inputs & Summary'!AJ37)
F40: =IF(AND(SUM('Inputs & Summary'!$E$109:$E$137)=1,E40<>""),INDEX($L$10:$L$19,MATCH(E40,$E$10:$E$19,0),1),NA()) -> #N/A | P40: =IF('Inputs & Summary'!O38="","",IF('Inputs & Summary'!O38=0,"At Issue",'Inputs & Summary'!P38)) | Q40: =IF($P40="","",'Inputs & Summary'!O38) | R40: =IF($P40="","",'Inputs & Summary'!Q38) | S40: {=IF($P40="","",IF(S$11="",0,IFERROR(INDEX(INDIRECT(S$6&VLOOKUP(Summary,Ref!$Y$13:$AC$18,3,FALSE)),MATCH(IF($P40="At Issue",VLOOKUP(Summary,Ref!$Y$13:$AC$18,2,FALSE),$P40),INDIRECT(S$6&VLOOKUP(Summary,Ref!$Y$13:$AC$18,4,FALSE)),0),VLOOKUP(S$10,Ref!$Y$61:$AA$63,2,FALSE)),0)))} | T40: {=IF($P40="","",IF(T$11="",0,IFERROR(INDEX(INDIRECT(T$6&VLOOKUP(Summary,Ref!$Y$13:$AC$18,3,FALSE)),MATCH(IF($P40="At Issue",VLOOKUP(Summary,Ref!$Y$13:$AC$18,2,FALSE),$P40),INDIRECT(T$6&VLOOKUP(Summary,Ref!$Y$13:$AC$18,4,FALSE)),0),VLOOKUP(T$10,Ref!$Y$61:$AA$63,2,FALSE)),0)))} | U40: {=IF($P40="","",IF(U$11="",0,IFERROR(INDEX(INDIRECT(U$6&VLOOKUP(Summary,Ref!$Y$13:$AC$18,3,FALSE)),MATCH(IF($P40="At Issue",VLOOKUP(Summary,Ref!$Y$13:$AC$18,2,FALSE),$P40),INDIRECT(U$6&VLOOKUP(Summary,Ref!$Y$13:$AC$18,4,FALSE)),0),VLOOKUP(U$10,Ref!$Y$61:$AA$63,2,FALSE)),0)))} | V40: {=IF($P40="","",IF(V$11="",0,IFERROR(INDEX(INDIRECT(V$6&VLOOKUP(Summary,Ref!$Y$13:$AC$18,3,FALSE)),MATCH(IF($P40="At Issue",VLOOKUP(Summary,Ref!$Y$13:$AC$18,2,FALSE),$P40),INDIRECT(V$6&VLOOKUP(Summary,Ref!$Y$13:$AC$18,4,FALSE)),0),VLOOKUP(V$10,Ref!$Y$61:$AA$63,2,FALSE)),0)))} | W40: {=IF($P40="","",IF(W$11="",0,IFERROR(INDEX(INDIRECT(W$6&VLOOKUP(Summary,Ref!$Y$13:$AC$18,3,FALSE)),MATCH(IF($P40="At Issue",VLOOKUP(Summary,Ref!$Y$13:$AC$18,2,FALSE),$P40),INDIRECT(W$6&VLOOKUP(Summary,Ref!$Y$13:$AC$18,4,FALSE)),0),VLOOKUP(W$10,Ref!$Y$61:$AA$63,2,FALSE)),0)))} | X40: =IF($P40="","",'Inputs & Summary'!S38) | Y40: =IF($P40="","",'Inputs & Summary'!T38) | Z40: =IF($P40="","",IF($Z$11="",0,'Inputs & Summary'!X38)) | AA40: =IF($P40="","",IF($AA$11="",0,IF(AND(LivBen<>"None",RIGHT(Category,2)<>"NY"),'Inputs & Summary'!AH38,""))) | AB40: =IF($P40="","",'Inputs & Summary'!Y38) | AC40: =IF($P40="","",IF(RIGHT(Category,2)="NY",'Inputs & Summary'!AH38,SUM('Inputs & Summary'!AB38,'Inputs & Summary'!AE38*('Inputs & Summary'!AD38="Yes"),'Inputs & Summary'!AG38))) | AD40: =IF($P40="","",'Inputs & Summary'!AI38) | AE40: =IF($P40="","",'Inputs & Summary'!Z38) | AF40: =IF($P40="","",'Inputs & Summary'!U38) | AG40: =IF($P40="","",'Inputs & Summary'!V38) | AH40: =IF($P40="","",'Inputs & Summary'!W38) | AI40: =IF($P40="","",IF($AI$11="",0,'Inputs & Summary'!AM38)) | AJ40: =IF($P40="","",IF($AJ$11="",0,IF(PTab="P7",'Inputs & Summary'!AQ38,'Inputs & Summary'!AA38))) | AK40: =IF($P40="","",'Inputs & Summary'!AJ38)
F41: =IF(AND(SUM('Inputs & Summary'!$E$109:$E$137)=1,E41<>""),INDEX($L$10:$L$19,MATCH(E41,$E$10:$E$19,0),1),NA()) -> #N/A | P41: =IF('Inputs & Summary'!O39="","",IF('Inputs & Summary'!O39=0,"At Issue",'Inputs & Summary'!P39)) | Q41: =IF($P41="","",'Inputs & Summary'!O39) | R41: =IF($P41="","",'Inputs & Summary'!Q39) | S41: {=IF($P41="","",IF(S$11="",0,IFERROR(INDEX(INDIRECT(S$6&VLOOKUP(Summary,Ref!$Y$13:$AC$18,3,FALSE)),MATCH(IF($P41="At Issue",VLOOKUP(Summary,Ref!$Y$13:$AC$18,2,FALSE),$P41),INDIRECT(S$6&VLOOKUP(Summary,Ref!$Y$13:$AC$18,4,FALSE)),0),VLOOKUP(S$10,Ref!$Y$61:$AA$63,2,FALSE)),0)))} | T41: {=IF($P41="","",IF(T$11="",0,IFERROR(INDEX(INDIRECT(T$6&VLOOKUP(Summary,Ref!$Y$13:$AC$18,3,FALSE)),MATCH(IF($P41="At Issue",VLOOKUP(Summary,Ref!$Y$13:$AC$18,2,FALSE),$P41),INDIRECT(T$6&VLOOKUP(Summary,Ref!$Y$13:$AC$18,4,FALSE)),0),VLOOKUP(T$10,Ref!$Y$61:$AA$63,2,FALSE)),0)))} | U41: {=IF($P41="","",IF(U$11="",0,IFERROR(INDEX(INDIRECT(U$6&VLOOKUP(Summary,Ref!$Y$13:$AC$18,3,FALSE)),MATCH(IF($P41="At Issue",VLOOKUP(Summary,Ref!$Y$13:$AC$18,2,FALSE),$P41),INDIRECT(U$6&VLOOKUP(Summary,Ref!$Y$13:$AC$18,4,FALSE)),0),VLOOKUP(U$10,Ref!$Y$61:$AA$63,2,FALSE)),0)))} | V41: {=IF($P41="","",IF(V$11="",0,IFERROR(INDEX(INDIRECT(V$6&VLOOKUP(Summary,Ref!$Y$13:$AC$18,3,FALSE)),MATCH(IF($P41="At Issue",VLOOKUP(Summary,Ref!$Y$13:$AC$18,2,FALSE),$P41),INDIRECT(V$6&VLOOKUP(Summary,Ref!$Y$13:$AC$18,4,FALSE)),0),VLOOKUP(V$10,Ref!$Y$61:$AA$63,2,FALSE)),0)))} | W41: {=IF($P41="","",IF(W$11="",0,IFERROR(INDEX(INDIRECT(W$6&VLOOKUP(Summary,Ref!$Y$13:$AC$18,3,FALSE)),MATCH(IF($P41="At Issue",VLOOKUP(Summary,Ref!$Y$13:$AC$18,2,FALSE),$P41),INDIRECT(W$6&VLOOKUP(Summary,Ref!$Y$13:$AC$18,4,FALSE)),0),VLOOKUP(W$10,Ref!$Y$61:$AA$63,2,FALSE)),0)))} | X41: =IF($P41="","",'Inputs & Summary'!S39) | Y41: =IF($P41="","",'Inputs & Summary'!T39) | Z41: =IF($P41="","",IF($Z$11="",0,'Inputs & Summary'!X39)) | AA41: =IF($P41="","",IF($AA$11="",0,IF(AND(LivBen<>"None",RIGHT(Category,2)<>"NY"),'Inputs & Summary'!AH39,""))) | AB41: =IF($P41="","",'Inputs & Summary'!Y39) | AC41: =IF($P41="","",IF(RIGHT(Category,2)="NY",'Inputs & Summary'!AH39,SUM('Inputs & Summary'!AB39,'Inputs & Summary'!AE39*('Inputs & Summary'!AD39="Yes"),'Inputs & Summary'!AG39))) | AD41: =IF($P41="","",'Inputs & Summary'!AI39) | AE41: =IF($P41="","",'Inputs & Summary'!Z39) | AF41: =IF($P41="","",'Inputs & Summary'!U39) | AG41: =IF($P41="","",'Inputs & Summary'!V39) | AH41: =IF($P41="","",'Inputs & Summary'!W39) | AI41: =IF($P41="","",IF($AI$11="",0,'Inputs & Summary'!AM39)) | AJ41: =IF($P41="","",IF($AJ$11="",0,IF(PTab="P7",'Inputs & Summary'!AQ39,'Inputs & Summary'!AA39))) | AK41: =IF($P41="","",'Inputs & Summary'!AJ39)
F42: =IF(AND(SUM('Inputs & Summary'!$E$109:$E$137)=1,E42<>""),INDEX($L$10:$L$19,MATCH(E42,$E$10:$E$19,0),1),NA()) -> #N/A | P42: =IF('Inputs & Summary'!O40="","",IF('Inputs & Summary'!O40=0,"At Issue",'Inputs & Summary'!P40)) | Q42: =IF($P42="","",'Inputs & Summary'!O40) | R42: =IF($P42="","",'Inputs & Summary'!Q40) | S42: {=IF($P42="","",IF(S$11="",0,IFERROR(INDEX(INDIRECT(S$6&VLOOKUP(Summary,Ref!$Y$13:$AC$18,3,FALSE)),MATCH(IF($P42="At Issue",VLOOKUP(Summary,Ref!$Y$13:$AC$18,2,FALSE),$P42),INDIRECT(S$6&VLOOKUP(Summary,Ref!$Y$13:$AC$18,4,FALSE)),0),VLOOKUP(S$10,Ref!$Y$61:$AA$63,2,FALSE)),0)))} | T42: {=IF($P42="","",IF(T$11="",0,IFERROR(INDEX(INDIRECT(T$6&VLOOKUP(Summary,Ref!$Y$13:$AC$18,3,FALSE)),MATCH(IF($P42="At Issue",VLOOKUP(Summary,Ref!$Y$13:$AC$18,2,FALSE),$P42),INDIRECT(T$6&VLOOKUP(Summary,Ref!$Y$13:$AC$18,4,FALSE)),0),VLOOKUP(T$10,Ref!$Y$61:$AA$63,2,FALSE)),0)))} | U42: {=IF($P42="","",IF(U$11="",0,IFERROR(INDEX(INDIRECT(U$6&VLOOKUP(Summary,Ref!$Y$13:$AC$18,3,FALSE)),MATCH(IF($P42="At Issue",VLOOKUP(Summary,Ref!$Y$13:$AC$18,2,FALSE),$P42),INDIRECT(U$6&VLOOKUP(Summary,Ref!$Y$13:$AC$18,4,FALSE)),0),VLOOKUP(U$10,Ref!$Y$61:$AA$63,2,FALSE)),0)))} | V42: {=IF($P42="","",IF(V$11="",0,IFERROR(INDEX(INDIRECT(V$6&VLOOKUP(Summary,Ref!$Y$13:$AC$18,3,FALSE)),MATCH(IF($P42="At Issue",VLOOKUP(Summary,Ref!$Y$13:$AC$18,2,FALSE),$P42),INDIRECT(V$6&VLOOKUP(Summary,Ref!$Y$13:$AC$18,4,FALSE)),0),VLOOKUP(V$10,Ref!$Y$61:$AA$63,2,FALSE)),0)))} | W42: {=IF($P42="","",IF(W$11="",0,IFERROR(INDEX(INDIRECT(W$6&VLOOKUP(Summary,Ref!$Y$13:$AC$18,3,FALSE)),MATCH(IF($P42="At Issue",VLOOKUP(Summary,Ref!$Y$13:$AC$18,2,FALSE),$P42),INDIRECT(W$6&VLOOKUP(Summary,Ref!$Y$13:$AC$18,4,FALSE)),0),VLOOKUP(W$10,Ref!$Y$61:$AA$63,2,FALSE)),0)))} | X42: =IF($P42="","",'Inputs & Summary'!S40) | Y42: =IF($P42="","",'Inputs & Summary'!T40) | Z42: =IF($P42="","",IF($Z$11="",0,'Inputs & Summary'!X40)) | AA42: =IF($P42="","",IF($AA$11="",0,IF(AND(LivBen<>"None",RIGHT(Category,2)<>"NY"),'Inputs & Summary'!AH40,""))) | AB42: =IF($P42="","",'Inputs & Summary'!Y40) | AC42: =IF($P42="","",IF(RIGHT(Category,2)="NY",'Inputs & Summary'!AH40,SUM('Inputs & Summary'!AB40,'Inputs & Summary'!AE40*('Inputs & Summary'!AD40="Yes"),'Inputs & Summary'!AG40))) | AD42: =IF($P42="","",'Inputs & Summary'!AI40) | AE42: =IF($P42="","",'Inputs & Summary'!Z40) | AF42: =IF($P42="","",'Inputs & Summary'!U40) | AG42: =IF($P42="","",'Inputs & Summary'!V40) | AH42: =IF($P42="","",'Inputs & Summary'!W40) | AI42: =IF($P42="","",IF($AI$11="",0,'Inputs & Summary'!AM40)) | AJ42: =IF($P42="","",IF($AJ$11="",0,IF(PTab="P7",'Inputs & Summary'!AQ40,'Inputs & Summary'!AA40))) | AK42: =IF($P42="","",'Inputs & Summary'!AJ40)
P43: =IF('Inputs & Summary'!O41="","",IF('Inputs & Summary'!O41=0,"At Issue",'Inputs & Summary'!P41)) | Q43: =IF($P43="","",'Inputs & Summary'!O41) | R43: =IF($P43="","",'Inputs & Summary'!Q41) | S43: {=IF($P43="","",IF(S$11="",0,IFERROR(INDEX(INDIRECT(S$6&VLOOKUP(Summary,Ref!$Y$13:$AC$18,3,FALSE)),MATCH(IF($P43="At Issue",VLOOKUP(Summary,Ref!$Y$13:$AC$18,2,FALSE),$P43),INDIRECT(S$6&VLOOKUP(Summary,Ref!$Y$13:$AC$18,4,FALSE)),0),VLOOKUP(S$10,Ref!$Y$61:$AA$63,2,FALSE)),0)))} | T43: {=IF($P43="","",IF(T$11="",0,IFERROR(INDEX(INDIRECT(T$6&VLOOKUP(Summary,Ref!$Y$13:$AC$18,3,FALSE)),MATCH(IF($P43="At Issue",VLOOKUP(Summary,Ref!$Y$13:$AC$18,2,FALSE),$P43),INDIRECT(T$6&VLOOKUP(Summary,Ref!$Y$13:$AC$18,4,FALSE)),0),VLOOKUP(T$10,Ref!$Y$61:$AA$63,2,FALSE)),0)))} | U43: {=IF($P43="","",IF(U$11="",0,IFERROR(INDEX(INDIRECT(U$6&VLOOKUP(Summary,Ref!$Y$13:$AC$18,3,FALSE)),MATCH(IF($P43="At Issue",VLOOKUP(Summary,Ref!$Y$13:$AC$18,2,FALSE),$P43),INDIRECT(U$6&VLOOKUP(Summary,Ref!$Y$13:$AC$18,4,FALSE)),0),VLOOKUP(U$10,Ref!$Y$61:$AA$63,2,FALSE)),0)))} | V43: {=IF($P43="","",IF(V$11="",0,IFERROR(INDEX(INDIRECT(V$6&VLOOKUP(Summary,Ref!$Y$13:$AC$18,3,FALSE)),MATCH(IF($P43="At Issue",VLOOKUP(Summary,Ref!$Y$13:$AC$18,2,FALSE),$P43),INDIRECT(V$6&VLOOKUP(Summary,Ref!$Y$13:$AC$18,4,FALSE)),0),VLOOKUP(V$10,Ref!$Y$61:$AA$63,2,FALSE)),0)))} | W43: {=IF($P43="","",IF(W$11="",0,IFERROR(INDEX(INDIRECT(W$6&VLOOKUP(Summary,Ref!$Y$13:$AC$18,3,FALSE)),MATCH(IF($P43="At Issue",VLOOKUP(Summary,Ref!$Y$13:$AC$18,2,FALSE),$P43),INDIRECT(W$6&VLOOKUP(Summary,Ref!$Y$13:$AC$18,4,FALSE)),0),VLOOKUP(W$10,Ref!$Y$61:$AA$63,2,FALSE)),0)))} | X43: =IF($P43="","",'Inputs & Summary'!S41) | Y43: =IF($P43="","",'Inputs & Summary'!T41) | Z43: =IF($P43="","",IF($Z$11="",0,'Inputs & Summary'!X41)) | AA43: =IF($P43="","",IF($AA$11="",0,IF(AND(LivBen<>"None",RIGHT(Category,2)<>"NY"),'Inputs & Summary'!AH41,""))) | AB43: =IF($P43="","",'Inputs & Summary'!Y41) | AC43: =IF($P43="","",IF(RIGHT(Category,2)="NY",'Inputs & Summary'!AH41,SUM('Inputs & Summary'!AB41,'Inputs & Summary'!AE41*('Inputs & Summary'!AD41="Yes"),'Inputs & Summary'!AG41))) | AD43: =IF($P43="","",'Inputs & Summary'!AI41) | AE43: =IF($P43="","",'Inputs & Summary'!Z41) | AF43: =IF($P43="","",'Inputs & Summary'!U41) | AG43: =IF($P43="","",'Inputs & Summary'!V41) | AH43: =IF($P43="","",'Inputs & Summary'!W41) | AI43: =IF($P43="","",IF($AI$11="",0,'Inputs & Summary'!AM41)) | AJ43: =IF($P43="","",IF($AJ$11="",0,IF(PTab="P7",'Inputs & Summary'!AQ41,'Inputs & Summary'!AA41))) | AK43: =IF($P43="","",'Inputs & Summary'!AJ41)
P44: =IF('Inputs & Summary'!O42="","",IF('Inputs & Summary'!O42=0,"At Issue",'Inputs & Summary'!P42)) | Q44: =IF($P44="","",'Inputs & Summary'!O42) | R44: =IF($P44="","",'Inputs & Summary'!Q42) | S44: {=IF($P44="","",IF(S$11="",0,IFERROR(INDEX(INDIRECT(S$6&VLOOKUP(Summary,Ref!$Y$13:$AC$18,3,FALSE)),MATCH(IF($P44="At Issue",VLOOKUP(Summary,Ref!$Y$13:$AC$18,2,FALSE),$P44),INDIRECT(S$6&VLOOKUP(Summary,Ref!$Y$13:$AC$18,4,FALSE)),0),VLOOKUP(S$10,Ref!$Y$61:$AA$63,2,FALSE)),0)))} | T44: {=IF($P44="","",IF(T$11="",0,IFERROR(INDEX(INDIRECT(T$6&VLOOKUP(Summary,Ref!$Y$13:$AC$18,3,FALSE)),MATCH(IF($P44="At Issue",VLOOKUP(Summary,Ref!$Y$13:$AC$18,2,FALSE),$P44),INDIRECT(T$6&VLOOKUP(Summary,Ref!$Y$13:$AC$18,4,FALSE)),0),VLOOKUP(T$10,Ref!$Y$61:$AA$63,2,FALSE)),0)))} | U44: {=IF($P44="","",IF(U$11="",0,IFERROR(INDEX(INDIRECT(U$6&VLOOKUP(Summary,Ref!$Y$13:$AC$18,3,FALSE)),MATCH(IF($P44="At Issue",VLOOKUP(Summary,Ref!$Y$13:$AC$18,2,FALSE),$P44),INDIRECT(U$6&VLOOKUP(Summary,Ref!$Y$13:$AC$18,4,FALSE)),0),VLOOKUP(U$10,Ref!$Y$61:$AA$63,2,FALSE)),0)))} | V44: {=IF($P44="","",IF(V$11="",0,IFERROR(INDEX(INDIRECT(V$6&VLOOKUP(Summary,Ref!$Y$13:$AC$18,3,FALSE)),MATCH(IF($P44="At Issue",VLOOKUP(Summary,Ref!$Y$13:$AC$18,2,FALSE),$P44),INDIRECT(V$6&VLOOKUP(Summary,Ref!$Y$13:$AC$18,4,FALSE)),0),VLOOKUP(V$10,Ref!$Y$61:$AA$63,2,FALSE)),0)))} | W44: {=IF($P44="","",IF(W$11="",0,IFERROR(INDEX(INDIRECT(W$6&VLOOKUP(Summary,Ref!$Y$13:$AC$18,3,FALSE)),MATCH(IF($P44="At Issue",VLOOKUP(Summary,Ref!$Y$13:$AC$18,2,FALSE),$P44),INDIRECT(W$6&VLOOKUP(Summary,Ref!$Y$13:$AC$18,4,FALSE)),0),VLOOKUP(W$10,Ref!$Y$61:$AA$63,2,FALSE)),0)))} | X44: =IF($P44="","",'Inputs & Summary'!S42) | Y44: =IF($P44="","",'Inputs & Summary'!T42) | Z44: =IF($P44="","",IF($Z$11="",0,'Inputs & Summary'!X42)) | AA44: =IF($P44="","",IF($AA$11="",0,IF(AND(LivBen<>"None",RIGHT(Category,2)<>"NY"),'Inputs & Summary'!AH42,""))) | AB44: =IF($P44="","",'Inputs & Summary'!Y42) | AC44: =IF($P44="","",IF(RIGHT(Category,2)="NY",'Inputs & Summary'!AH42,SUM('Inputs & Summary'!AB42,'Inputs & Summary'!AE42*('Inputs & Summary'!AD42="Yes"),'Inputs & Summary'!AG42))) | AD44: =IF($P44="","",'Inputs & Summary'!AI42) | AE44: =IF($P44="","",'Inputs & Summary'!Z42) | AF44: =IF($P44="","",'Inputs & Summary'!U42) | AG44: =IF($P44="","",'Inputs & Summary'!V42) | AH44: =IF($P44="","",'Inputs & Summary'!W42) | AI44: =IF($P44="","",IF($AI$11="",0,'Inputs & Summary'!AM42)) | AJ44: =IF($P44="","",IF($AJ$11="",0,IF(PTab="P7",'Inputs & Summary'!AQ42,'Inputs & Summary'!AA42))) | AK44: =IF($P44="","",'Inputs & Summary'!AJ42)
P45: =IF('Inputs & Summary'!O43="","",IF('Inputs & Summary'!O43=0,"At Issue",'Inputs & Summary'!P43)) | Q45: =IF($P45="","",'Inputs & Summary'!O43) | R45: =IF($P45="","",'Inputs & Summary'!Q43) | S45: {=IF($P45="","",IF(S$11="",0,IFERROR(INDEX(INDIRECT(S$6&VLOOKUP(Summary,Ref!$Y$13:$AC$18,3,FALSE)),MATCH(IF($P45="At Issue",VLOOKUP(Summary,Ref!$Y$13:$AC$18,2,FALSE),$P45),INDIRECT(S$6&VLOOKUP(Summary,Ref!$Y$13:$AC$18,4,FALSE)),0),VLOOKUP(S$10,Ref!$Y$61:$AA$63,2,FALSE)),0)))} | T45: {=IF($P45="","",IF(T$11="",0,IFERROR(INDEX(INDIRECT(T$6&VLOOKUP(Summary,Ref!$Y$13:$AC$18,3,FALSE)),MATCH(IF($P45="At Issue",VLOOKUP(Summary,Ref!$Y$13:$AC$18,2,FALSE),$P45),INDIRECT(T$6&VLOOKUP(Summary,Ref!$Y$13:$AC$18,4,FALSE)),0),VLOOKUP(T$10,Ref!$Y$61:$AA$63,2,FALSE)),0)))} | U45: {=IF($P45="","",IF(U$11="",0,IFERROR(INDEX(INDIRECT(U$6&VLOOKUP(Summary,Ref!$Y$13:$AC$18,3,FALSE)),MATCH(IF($P45="At Issue",VLOOKUP(Summary,Ref!$Y$13:$AC$18,2,FALSE),$P45),INDIRECT(U$6&VLOOKUP(Summary,Ref!$Y$13:$AC$18,4,FALSE)),0),VLOOKUP(U$10,Ref!$Y$61:$AA$63,2,FALSE)),0)))} | V45: {=IF($P45="","",IF(V$11="",0,IFERROR(INDEX(INDIRECT(V$6&VLOOKUP(Summary,Ref!$Y$13:$AC$18,3,FALSE)),MATCH(IF($P45="At Issue",VLOOKUP(Summary,Ref!$Y$13:$AC$18,2,FALSE),$P45),INDIRECT(V$6&VLOOKUP(Summary,Ref!$Y$13:$AC$18,4,FALSE)),0),VLOOKUP(V$10,Ref!$Y$61:$AA$63,2,FALSE)),0)))} | W45: {=IF($P45="","",IF(W$11="",0,IFERROR(INDEX(INDIRECT(W$6&VLOOKUP(Summary,Ref!$Y$13:$AC$18,3,FALSE)),MATCH(IF($P45="At Issue",VLOOKUP(Summary,Ref!$Y$13:$AC$18,2,FALSE),$P45),INDIRECT(W$6&VLOOKUP(Summary,Ref!$Y$13:$AC$18,4,FALSE)),0),VLOOKUP(W$10,Ref!$Y$61:$AA$63,2,FALSE)),0)))} | X45: =IF($P45="","",'Inputs & Summary'!S43) | Y45: =IF($P45="","",'Inputs & Summary'!T43) | Z45: =IF($P45="","",IF($Z$11="",0,'Inputs & Summary'!X43)) | AA45: =IF($P45="","",IF($AA$11="",0,IF(AND(LivBen<>"None",RIGHT(Category,2)<>"NY"),'Inputs & Summary'!AH43,""))) | AB45: =IF($P45="","",'Inputs & Summary'!Y43) | AC45: =IF($P45="","",IF(RIGHT(Category,2)="NY",'Inputs & Summary'!AH43,SUM('Inputs & Summary'!AB43,'Inputs & Summary'!AE43*('Inputs & Summary'!AD43="Yes"),'Inputs & Summary'!AG43))) | AD45: =IF($P45="","",'Inputs & Summary'!AI43) | AE45: =IF($P45="","",'Inputs & Summary'!Z43) | AF45: =IF($P45="","",'Inputs & Summary'!U43) | AG45: =IF($P45="","",'Inputs & Summary'!V43) | AH45: =IF($P45="","",'Inputs & Summary'!W43) | AI45: =IF($P45="","",IF($AI$11="",0,'Inputs & Summary'!AM43)) | AJ45: =IF($P45="","",IF($AJ$11="",0,IF(PTab="P7",'Inputs & Summary'!AQ43,'Inputs & Summary'!AA43))) | AK45: =IF($P45="","",'Inputs & Summary'!AJ43)
P46: =IF('Inputs & Summary'!O44="","",IF('Inputs & Summary'!O44=0,"At Issue",'Inputs & Summary'!P44)) | Q46: =IF($P46="","",'Inputs & Summary'!O44) | R46: =IF($P46="","",'Inputs & Summary'!Q44) | S46: {=IF($P46="","",IF(S$11="",0,IFERROR(INDEX(INDIRECT(S$6&VLOOKUP(Summary,Ref!$Y$13:$AC$18,3,FALSE)),MATCH(IF($P46="At Issue",VLOOKUP(Summary,Ref!$Y$13:$AC$18,2,FALSE),$P46),INDIRECT(S$6&VLOOKUP(Summary,Ref!$Y$13:$AC$18,4,FALSE)),0),VLOOKUP(S$10,Ref!$Y$61:$AA$63,2,FALSE)),0)))} | T46: {=IF($P46="","",IF(T$11="",0,IFERROR(INDEX(INDIRECT(T$6&VLOOKUP(Summary,Ref!$Y$13:$AC$18,3,FALSE)),MATCH(IF($P46="At Issue",VLOOKUP(Summary,Ref!$Y$13:$AC$18,2,FALSE),$P46),INDIRECT(T$6&VLOOKUP(Summary,Ref!$Y$13:$AC$18,4,FALSE)),0),VLOOKUP(T$10,Ref!$Y$61:$AA$63,2,FALSE)),0)))} | U46: {=IF($P46="","",IF(U$11="",0,IFERROR(INDEX(INDIRECT(U$6&VLOOKUP(Summary,Ref!$Y$13:$AC$18,3,FALSE)),MATCH(IF($P46="At Issue",VLOOKUP(Summary,Ref!$Y$13:$AC$18,2,FALSE),$P46),INDIRECT(U$6&VLOOKUP(Summary,Ref!$Y$13:$AC$18,4,FALSE)),0),VLOOKUP(U$10,Ref!$Y$61:$AA$63,2,FALSE)),0)))} | V46: {=IF($P46="","",IF(V$11="",0,IFERROR(INDEX(INDIRECT(V$6&VLOOKUP(Summary,Ref!$Y$13:$AC$18,3,FALSE)),MATCH(IF($P46="At Issue",VLOOKUP(Summary,Ref!$Y$13:$AC$18,2,FALSE),$P46),INDIRECT(V$6&VLOOKUP(Summary,Ref!$Y$13:$AC$18,4,FALSE)),0),VLOOKUP(V$10,Ref!$Y$61:$AA$63,2,FALSE)),0)))} | W46: {=IF($P46="","",IF(W$11="",0,IFERROR(INDEX(INDIRECT(W$6&VLOOKUP(Summary,Ref!$Y$13:$AC$18,3,FALSE)),MATCH(IF($P46="At Issue",VLOOKUP(Summary,Ref!$Y$13:$AC$18,2,FALSE),$P46),INDIRECT(W$6&VLOOKUP(Summary,Ref!$Y$13:$AC$18,4,FALSE)),0),VLOOKUP(W$10,Ref!$Y$61:$AA$63,2,FALSE)),0)))} | X46: =IF($P46="","",'Inputs & Summary'!S44) | Y46: =IF($P46="","",'Inputs & Summary'!T44) | Z46: =IF($P46="","",IF($Z$11="",0,'Inputs & Summary'!X44)) | AA46: =IF($P46="","",IF($AA$11="",0,IF(AND(LivBen<>"None",RIGHT(Category,2)<>"NY"),'Inputs & Summary'!AH44,""))) | AB46: =IF($P46="","",'Inputs & Summary'!Y44) | AC46: =IF($P46="","",IF(RIGHT(Category,2)="NY",'Inputs & Summary'!AH44,SUM('Inputs & Summary'!AB44,'Inputs & Summary'!AE44*('Inputs & Summary'!AD44="Yes"),'Inputs & Summary'!AG44))) | AD46: =IF($P46="","",'Inputs & Summary'!AI44) | AE46: =IF($P46="","",'Inputs & Summary'!Z44) | AF46: =IF($P46="","",'Inputs & Summary'!U44) | AG46: =IF($P46="","",'Inputs & Summary'!V44) | AH46: =IF($P46="","",'Inputs & Summary'!W44) | AI46: =IF($P46="","",IF($AI$11="",0,'Inputs & Summary'!AM44)) | AJ46: =IF($P46="","",IF($AJ$11="",0,IF(PTab="P7",'Inputs & Summary'!AQ44,'Inputs & Summary'!AA44))) | AK46: =IF($P46="","",'Inputs & Summary'!AJ44)
P47: =IF('Inputs & Summary'!O45="","",IF('Inputs & Summary'!O45=0,"At Issue",'Inputs & Summary'!P45)) | Q47: =IF($P47="","",'Inputs & Summary'!O45) | R47: =IF($P47="","",'Inputs & Summary'!Q45) | S47: {=IF($P47="","",IF(S$11="",0,IFERROR(INDEX(INDIRECT(S$6&VLOOKUP(Summary,Ref!$Y$13:$AC$18,3,FALSE)),MATCH(IF($P47="At Issue",VLOOKUP(Summary,Ref!$Y$13:$AC$18,2,FALSE),$P47),INDIRECT(S$6&VLOOKUP(Summary,Ref!$Y$13:$AC$18,4,FALSE)),0),VLOOKUP(S$10,Ref!$Y$61:$AA$63,2,FALSE)),0)))} | T47: {=IF($P47="","",IF(T$11="",0,IFERROR(INDEX(INDIRECT(T$6&VLOOKUP(Summary,Ref!$Y$13:$AC$18,3,FALSE)),MATCH(IF($P47="At Issue",VLOOKUP(Summary,Ref!$Y$13:$AC$18,2,FALSE),$P47),INDIRECT(T$6&VLOOKUP(Summary,Ref!$Y$13:$AC$18,4,FALSE)),0),VLOOKUP(T$10,Ref!$Y$61:$AA$63,2,FALSE)),0)))} | U47: {=IF($P47="","",IF(U$11="",0,IFERROR(INDEX(INDIRECT(U$6&VLOOKUP(Summary,Ref!$Y$13:$AC$18,3,FALSE)),MATCH(IF($P47="At Issue",VLOOKUP(Summary,Ref!$Y$13:$AC$18,2,FALSE),$P47),INDIRECT(U$6&VLOOKUP(Summary,Ref!$Y$13:$AC$18,4,FALSE)),0),VLOOKUP(U$10,Ref!$Y$61:$AA$63,2,FALSE)),0)))} | V47: {=IF($P47="","",IF(V$11="",0,IFERROR(INDEX(INDIRECT(V$6&VLOOKUP(Summary,Ref!$Y$13:$AC$18,3,FALSE)),MATCH(IF($P47="At Issue",VLOOKUP(Summary,Ref!$Y$13:$AC$18,2,FALSE),$P47),INDIRECT(V$6&VLOOKUP(Summary,Ref!$Y$13:$AC$18,4,FALSE)),0),VLOOKUP(V$10,Ref!$Y$61:$AA$63,2,FALSE)),0)))} | W47: {=IF($P47="","",IF(W$11="",0,IFERROR(INDEX(INDIRECT(W$6&VLOOKUP(Summary,Ref!$Y$13:$AC$18,3,FALSE)),MATCH(IF($P47="At Issue",VLOOKUP(Summary,Ref!$Y$13:$AC$18,2,FALSE),$P47),INDIRECT(W$6&VLOOKUP(Summary,Ref!$Y$13:$AC$18,4,FALSE)),0),VLOOKUP(W$10,Ref!$Y$61:$AA$63,2,FALSE)),0)))} | X47: =IF($P47="","",'Inputs & Summary'!S45) | Y47: =IF($P47="","",'Inputs & Summary'!T45) | Z47: =IF($P47="","",IF($Z$11="",0,'Inputs & Summary'!X45)) | AA47: =IF($P47="","",IF($AA$11="",0,IF(AND(LivBen<>"None",RIGHT(Category,2)<>"NY"),'Inputs & Summary'!AH45,""))) | AB47: =IF($P47="","",'Inputs & Summary'!Y45) | AC47: =IF($P47="","",IF(RIGHT(Category,2)="NY",'Inputs & Summary'!AH45,SUM('Inputs & Summary'!AB45,'Inputs & Summary'!AE45*('Inputs & Summary'!AD45="Yes"),'Inputs & Summary'!AG45))) | AD47: =IF($P47="","",'Inputs & Summary'!AI45) | AE47: =IF($P47="","",'Inputs & Summary'!Z45) | AF47: =IF($P47="","",'Inputs & Summary'!U45) | AG47: =IF($P47="","",'Inputs & Summary'!V45) | AH47: =IF($P47="","",'Inputs & Summary'!W45) | AI47: =IF($P47="","",IF($AI$11="",0,'Inputs & Summary'!AM45)) | AJ47: =IF($P47="","",IF($AJ$11="",0,IF(PTab="P7",'Inputs & Summary'!AQ45,'Inputs & Summary'!AA45))) | AK47: =IF($P47="","",'Inputs & Summary'!AJ45)
P48: =IF('Inputs & Summary'!O46="","",IF('Inputs & Summary'!O46=0,"At Issue",'Inputs & Summary'!P46)) | Q48: =IF($P48="","",'Inputs & Summary'!O46) | R48: =IF($P48="","",'Inputs & Summary'!Q46) | S48: {=IF($P48="","",IF(S$11="",0,IFERROR(INDEX(INDIRECT(S$6&VLOOKUP(Summary,Ref!$Y$13:$AC$18,3,FALSE)),MATCH(IF($P48="At Issue",VLOOKUP(Summary,Ref!$Y$13:$AC$18,2,FALSE),$P48),INDIRECT(S$6&VLOOKUP(Summary,Ref!$Y$13:$AC$18,4,FALSE)),0),VLOOKUP(S$10,Ref!$Y$61:$AA$63,2,FALSE)),0)))} | T48: {=IF($P48="","",IF(T$11="",0,IFERROR(INDEX(INDIRECT(T$6&VLOOKUP(Summary,Ref!$Y$13:$AC$18,3,FALSE)),MATCH(IF($P48="At Issue",VLOOKUP(Summary,Ref!$Y$13:$AC$18,2,FALSE),$P48),INDIRECT(T$6&VLOOKUP(Summary,Ref!$Y$13:$AC$18,4,FALSE)),0),VLOOKUP(T$10,Ref!$Y$61:$AA$63,2,FALSE)),0)))} | U48: {=IF($P48="","",IF(U$11="",0,IFERROR(INDEX(INDIRECT(U$6&VLOOKUP(Summary,Ref!$Y$13:$AC$18,3,FALSE)),MATCH(IF($P48="At Issue",VLOOKUP(Summary,Ref!$Y$13:$AC$18,2,FALSE),$P48),INDIRECT(U$6&VLOOKUP(Summary,Ref!$Y$13:$AC$18,4,FALSE)),0),VLOOKUP(U$10,Ref!$Y$61:$AA$63,2,FALSE)),0)))} | V48: {=IF($P48="","",IF(V$11="",0,IFERROR(INDEX(INDIRECT(V$6&VLOOKUP(Summary,Ref!$Y$13:$AC$18,3,FALSE)),MATCH(IF($P48="At Issue",VLOOKUP(Summary,Ref!$Y$13:$AC$18,2,FALSE),$P48),INDIRECT(V$6&VLOOKUP(Summary,Ref!$Y$13:$AC$18,4,FALSE)),0),VLOOKUP(V$10,Ref!$Y$61:$AA$63,2,FALSE)),0)))} | W48: {=IF($P48="","",IF(W$11="",0,IFERROR(INDEX(INDIRECT(W$6&VLOOKUP(Summary,Ref!$Y$13:$AC$18,3,FALSE)),MATCH(IF($P48="At Issue",VLOOKUP(Summary,Ref!$Y$13:$AC$18,2,FALSE),$P48),INDIRECT(W$6&VLOOKUP(Summary,Ref!$Y$13:$AC$18,4,FALSE)),0),VLOOKUP(W$10,Ref!$Y$61:$AA$63,2,FALSE)),0)))} | X48: =IF($P48="","",'Inputs & Summary'!S46) | Y48: =IF($P48="","",'Inputs & Summary'!T46) | Z48: =IF($P48="","",IF($Z$11="",0,'Inputs & Summary'!X46)) | AA48: =IF($P48="","",IF($AA$11="",0,IF(AND(LivBen<>"None",RIGHT(Category,2)<>"NY"),'Inputs & Summary'!AH46,""))) | AB48: =IF($P48="","",'Inputs & Summary'!Y46) | AC48: =IF($P48="","",IF(RIGHT(Category,2)="NY",'Inputs & Summary'!AH46,SUM('Inputs & Summary'!AB46,'Inputs & Summary'!AE46*('Inputs & Summary'!AD46="Yes"),'Inputs & Summary'!AG46))) | AD48: =IF($P48="","",'Inputs & Summary'!AI46) | AE48: =IF($P48="","",'Inputs & Summary'!Z46) | AF48: =IF($P48="","",'Inputs & Summary'!U46) | AG48: =IF($P48="","",'Inputs & Summary'!V46) | AH48: =IF($P48="","",'Inputs & Summary'!W46) | AI48: =IF($P48="","",IF($AI$11="",0,'Inputs & Summary'!AM46)) | AJ48: =IF($P48="","",IF($AJ$11="",0,IF(PTab="P7",'Inputs & Summary'!AQ46,'Inputs & Summary'!AA46))) | AK48: =IF($P48="","",'Inputs & Summary'!AJ46)
P49: =IF('Inputs & Summary'!O47="","",IF('Inputs & Summary'!O47=0,"At Issue",'Inputs & Summary'!P47)) | Q49: =IF($P49="","",'Inputs & Summary'!O47) | R49: =IF($P49="","",'Inputs & Summary'!Q47) | S49: {=IF($P49="","",IF(S$11="",0,IFERROR(INDEX(INDIRECT(S$6&VLOOKUP(Summary,Ref!$Y$13:$AC$18,3,FALSE)),MATCH(IF($P49="At Issue",VLOOKUP(Summary,Ref!$Y$13:$AC$18,2,FALSE),$P49),INDIRECT(S$6&VLOOKUP(Summary,Ref!$Y$13:$AC$18,4,FALSE)),0),VLOOKUP(S$10,Ref!$Y$61:$AA$63,2,FALSE)),0)))} | T49: {=IF($P49="","",IF(T$11="",0,IFERROR(INDEX(INDIRECT(T$6&VLOOKUP(Summary,Ref!$Y$13:$AC$18,3,FALSE)),MATCH(IF($P49="At Issue",VLOOKUP(Summary,Ref!$Y$13:$AC$18,2,FALSE),$P49),INDIRECT(T$6&VLOOKUP(Summary,Ref!$Y$13:$AC$18,4,FALSE)),0),VLOOKUP(T$10,Ref!$Y$61:$AA$63,2,FALSE)),0)))} | U49: {=IF($P49="","",IF(U$11="",0,IFERROR(INDEX(INDIRECT(U$6&VLOOKUP(Summary,Ref!$Y$13:$AC$18,3,FALSE)),MATCH(IF($P49="At Issue",VLOOKUP(Summary,Ref!$Y$13:$AC$18,2,FALSE),$P49),INDIRECT(U$6&VLOOKUP(Summary,Ref!$Y$13:$AC$18,4,FALSE)),0),VLOOKUP(U$10,Ref!$Y$61:$AA$63,2,FALSE)),0)))} | V49: {=IF($P49="","",IF(V$11="",0,IFERROR(INDEX(INDIRECT(V$6&VLOOKUP(Summary,Ref!$Y$13:$AC$18,3,FALSE)),MATCH(IF($P49="At Issue",VLOOKUP(Summary,Ref!$Y$13:$AC$18,2,FALSE),$P49),INDIRECT(V$6&VLOOKUP(Summary,Ref!$Y$13:$AC$18,4,FALSE)),0),VLOOKUP(V$10,Ref!$Y$61:$AA$63,2,FALSE)),0)))} | W49: {=IF($P49="","",IF(W$11="",0,IFERROR(INDEX(INDIRECT(W$6&VLOOKUP(Summary,Ref!$Y$13:$AC$18,3,FALSE)),MATCH(IF($P49="At Issue",VLOOKUP(Summary,Ref!$Y$13:$AC$18,2,FALSE),$P49),INDIRECT(W$6&VLOOKUP(Summary,Ref!$Y$13:$AC$18,4,FALSE)),0),VLOOKUP(W$10,Ref!$Y$61:$AA$63,2,FALSE)),0)))} | X49: =IF($P49="","",'Inputs & Summary'!S47) | Y49: =IF($P49="","",'Inputs & Summary'!T47) | Z49: =IF($P49="","",IF($Z$11="",0,'Inputs & Summary'!X47)) | AA49: =IF($P49="","",IF($AA$11="",0,IF(AND(LivBen<>"None",RIGHT(Category,2)<>"NY"),'Inputs & Summary'!AH47,""))) | AB49: =IF($P49="","",'Inputs & Summary'!Y47) | AC49: =IF($P49="","",IF(RIGHT(Category,2)="NY",'Inputs & Summary'!AH47,SUM('Inputs & Summary'!AB47,'Inputs & Summary'!AE47*('Inputs & Summary'!AD47="Yes"),'Inputs & Summary'!AG47))) | AD49: =IF($P49="","",'Inputs & Summary'!AI47) | AE49: =IF($P49="","",'Inputs & Summary'!Z47) | AF49: =IF($P49="","",'Inputs & Summary'!U47) | AG49: =IF($P49="","",'Inputs & Summary'!V47) | AH49: =IF($P49="","",'Inputs & Summary'!W47) | AI49: =IF($P49="","",IF($AI$11="",0,'Inputs & Summary'!AM47)) | AJ49: =IF($P49="","",IF($AJ$11="",0,IF(PTab="P7",'Inputs & Summary'!AQ47,'Inputs & Summary'!AA47))) | AK49: =IF($P49="","",'Inputs & Summary'!AJ47)
P50: =IF('Inputs & Summary'!O48="","",IF('Inputs & Summary'!O48=0,"At Issue",'Inputs & Summary'!P48)) | Q50: =IF($P50="","",'Inputs & Summary'!O48) | R50: =IF($P50="","",'Inputs & Summary'!Q48) | S50: {=IF($P50="","",IF(S$11="",0,IFERROR(INDEX(INDIRECT(S$6&VLOOKUP(Summary,Ref!$Y$13:$AC$18,3,FALSE)),MATCH(IF($P50="At Issue",VLOOKUP(Summary,Ref!$Y$13:$AC$18,2,FALSE),$P50),INDIRECT(S$6&VLOOKUP(Summary,Ref!$Y$13:$AC$18,4,FALSE)),0),VLOOKUP(S$10,Ref!$Y$61:$AA$63,2,FALSE)),0)))} | T50: {=IF($P50="","",IF(T$11="",0,IFERROR(INDEX(INDIRECT(T$6&VLOOKUP(Summary,Ref!$Y$13:$AC$18,3,FALSE)),MATCH(IF($P50="At Issue",VLOOKUP(Summary,Ref!$Y$13:$AC$18,2,FALSE),$P50),INDIRECT(T$6&VLOOKUP(Summary,Ref!$Y$13:$AC$18,4,FALSE)),0),VLOOKUP(T$10,Ref!$Y$61:$AA$63,2,FALSE)),0)))} | U50: {=IF($P50="","",IF(U$11="",0,IFERROR(INDEX(INDIRECT(U$6&VLOOKUP(Summary,Ref!$Y$13:$AC$18,3,FALSE)),MATCH(IF($P50="At Issue",VLOOKUP(Summary,Ref!$Y$13:$AC$18,2,FALSE),$P50),INDIRECT(U$6&VLOOKUP(Summary,Ref!$Y$13:$AC$18,4,FALSE)),0),VLOOKUP(U$10,Ref!$Y$61:$AA$63,2,FALSE)),0)))} | V50: {=IF($P50="","",IF(V$11="",0,IFERROR(INDEX(INDIRECT(V$6&VLOOKUP(Summary,Ref!$Y$13:$AC$18,3,FALSE)),MATCH(IF($P50="At Issue",VLOOKUP(Summary,Ref!$Y$13:$AC$18,2,FALSE),$P50),INDIRECT(V$6&VLOOKUP(Summary,Ref!$Y$13:$AC$18,4,FALSE)),0),VLOOKUP(V$10,Ref!$Y$61:$AA$63,2,FALSE)),0)))} | W50: {=IF($P50="","",IF(W$11="",0,IFERROR(INDEX(INDIRECT(W$6&VLOOKUP(Summary,Ref!$Y$13:$AC$18,3,FALSE)),MATCH(IF($P50="At Issue",VLOOKUP(Summary,Ref!$Y$13:$AC$18,2,FALSE),$P50),INDIRECT(W$6&VLOOKUP(Summary,Ref!$Y$13:$AC$18,4,FALSE)),0),VLOOKUP(W$10,Ref!$Y$61:$AA$63,2,FALSE)),0)))} | X50: =IF($P50="","",'Inputs & Summary'!S48) | Y50: =IF($P50="","",'Inputs & Summary'!T48) | Z50: =IF($P50="","",IF($Z$11="",0,'Inputs & Summary'!X48)) | AA50: =IF($P50="","",IF($AA$11="",0,IF(AND(LivBen<>"None",RIGHT(Category,2)<>"NY"),'Inputs & Summary'!AH48,""))) | AB50: =IF($P50="","",'Inputs & Summary'!Y48) | AC50: =IF($P50="","",IF(RIGHT(Category,2)="NY",'Inputs & Summary'!AH48,SUM('Inputs & Summary'!AB48,'Inputs & Summary'!AE48*('Inputs & Summary'!AD48="Yes"),'Inputs & Summary'!AG48))) | AD50: =IF($P50="","",'Inputs & Summary'!AI48) | AE50: =IF($P50="","",'Inputs & Summary'!Z48) | AF50: =IF($P50="","",'Inputs & Summary'!U48) | AG50: =IF($P50="","",'Inputs & Summary'!V48) | AH50: =IF($P50="","",'Inputs & Summary'!W48) | AI50: =IF($P50="","",IF($AI$11="",0,'Inputs & Summary'!AM48)) | AJ50: =IF($P50="","",IF($AJ$11="",0,IF(PTab="P7",'Inputs & Summary'!AQ48,'Inputs & Summary'!AA48))) | AK50: =IF($P50="","",'Inputs & Summary'!AJ48)
P51: =IF('Inputs & Summary'!O49="","",IF('Inputs & Summary'!O49=0,"At Issue",'Inputs & Summary'!P49)) | Q51: =IF($P51="","",'Inputs & Summary'!O49) | R51: =IF($P51="","",'Inputs & Summary'!Q49) | S51: {=IF($P51="","",IF(S$11="",0,IFERROR(INDEX(INDIRECT(S$6&VLOOKUP(Summary,Ref!$Y$13:$AC$18,3,FALSE)),MATCH(IF($P51="At Issue",VLOOKUP(Summary,Ref!$Y$13:$AC$18,2,FALSE),$P51),INDIRECT(S$6&VLOOKUP(Summary,Ref!$Y$13:$AC$18,4,FALSE)),0),VLOOKUP(S$10,Ref!$Y$61:$AA$63,2,FALSE)),0)))} | T51: {=IF($P51="","",IF(T$11="",0,IFERROR(INDEX(INDIRECT(T$6&VLOOKUP(Summary,Ref!$Y$13:$AC$18,3,FALSE)),MATCH(IF($P51="At Issue",VLOOKUP(Summary,Ref!$Y$13:$AC$18,2,FALSE),$P51),INDIRECT(T$6&VLOOKUP(Summary,Ref!$Y$13:$AC$18,4,FALSE)),0),VLOOKUP(T$10,Ref!$Y$61:$AA$63,2,FALSE)),0)))} | U51: {=IF($P51="","",IF(U$11="",0,IFERROR(INDEX(INDIRECT(U$6&VLOOKUP(Summary,Ref!$Y$13:$AC$18,3,FALSE)),MATCH(IF($P51="At Issue",VLOOKUP(Summary,Ref!$Y$13:$AC$18,2,FALSE),$P51),INDIRECT(U$6&VLOOKUP(Summary,Ref!$Y$13:$AC$18,4,FALSE)),0),VLOOKUP(U$10,Ref!$Y$61:$AA$63,2,FALSE)),0)))} | V51: {=IF($P51="","",IF(V$11="",0,IFERROR(INDEX(INDIRECT(V$6&VLOOKUP(Summary,Ref!$Y$13:$AC$18,3,FALSE)),MATCH(IF($P51="At Issue",VLOOKUP(Summary,Ref!$Y$13:$AC$18,2,FALSE),$P51),INDIRECT(V$6&VLOOKUP(Summary,Ref!$Y$13:$AC$18,4,FALSE)),0),VLOOKUP(V$10,Ref!$Y$61:$AA$63,2,FALSE)),0)))} | W51: {=IF($P51="","",IF(W$11="",0,IFERROR(INDEX(INDIRECT(W$6&VLOOKUP(Summary,Ref!$Y$13:$AC$18,3,FALSE)),MATCH(IF($P51="At Issue",VLOOKUP(Summary,Ref!$Y$13:$AC$18,2,FALSE),$P51),INDIRECT(W$6&VLOOKUP(Summary,Ref!$Y$13:$AC$18,4,FALSE)),0),VLOOKUP(W$10,Ref!$Y$61:$AA$63,2,FALSE)),0)))} | X51: =IF($P51="","",'Inputs & Summary'!S49) | Y51: =IF($P51="","",'Inputs & Summary'!T49) | Z51: =IF($P51="","",IF($Z$11="",0,'Inputs & Summary'!X49)) | AA51: =IF($P51="","",IF($AA$11="",0,IF(AND(LivBen<>"None",RIGHT(Category,2)<>"NY"),'Inputs & Summary'!AH49,""))) | AB51: =IF($P51="","",'Inputs & Summary'!Y49) | AC51: =IF($P51="","",IF(RIGHT(Category,2)="NY",'Inputs & Summary'!AH49,SUM('Inputs & Summary'!AB49,'Inputs & Summary'!AE49*('Inputs & Summary'!AD49="Yes"),'Inputs & Summary'!AG49))) | AD51: =IF($P51="","",'Inputs & Summary'!AI49) | AE51: =IF($P51="","",'Inputs & Summary'!Z49) | AF51: =IF($P51="","",'Inputs & Summary'!U49) | AG51: =IF($P51="","",'Inputs & Summary'!V49) | AH51: =IF($P51="","",'Inputs & Summary'!W49) | AI51: =IF($P51="","",IF($AI$11="",0,'Inputs & Summary'!AM49)) | AJ51: =IF($P51="","",IF($AJ$11="",0,IF(PTab="P7",'Inputs & Summary'!AQ49,'Inputs & Summary'!AA49))) | AK51: =IF($P51="","",'Inputs & Summary'!AJ49)
P52: =IF('Inputs & Summary'!O50="","",IF('Inputs & Summary'!O50=0,"At Issue",'Inputs & Summary'!P50)) | Q52: =IF($P52="","",'Inputs & Summary'!O50) | R52: =IF($P52="","",'Inputs & Summary'!Q50) | S52: {=IF($P52="","",IF(S$11="",0,IFERROR(INDEX(INDIRECT(S$6&VLOOKUP(Summary,Ref!$Y$13:$AC$18,3,FALSE)),MATCH(IF($P52="At Issue",VLOOKUP(Summary,Ref!$Y$13:$AC$18,2,FALSE),$P52),INDIRECT(S$6&VLOOKUP(Summary,Ref!$Y$13:$AC$18,4,FALSE)),0),VLOOKUP(S$10,Ref!$Y$61:$AA$63,2,FALSE)),0)))} | T52: {=IF($P52="","",IF(T$11="",0,IFERROR(INDEX(INDIRECT(T$6&VLOOKUP(Summary,Ref!$Y$13:$AC$18,3,FALSE)),MATCH(IF($P52="At Issue",VLOOKUP(Summary,Ref!$Y$13:$AC$18,2,FALSE),$P52),INDIRECT(T$6&VLOOKUP(Summary,Ref!$Y$13:$AC$18,4,FALSE)),0),VLOOKUP(T$10,Ref!$Y$61:$AA$63,2,FALSE)),0)))} | U52: {=IF($P52="","",IF(U$11="",0,IFERROR(INDEX(INDIRECT(U$6&VLOOKUP(Summary,Ref!$Y$13:$AC$18,3,FALSE)),MATCH(IF($P52="At Issue",VLOOKUP(Summary,Ref!$Y$13:$AC$18,2,FALSE),$P52),INDIRECT(U$6&VLOOKUP(Summary,Ref!$Y$13:$AC$18,4,FALSE)),0),VLOOKUP(U$10,Ref!$Y$61:$AA$63,2,FALSE)),0)))} | V52: {=IF($P52="","",IF(V$11="",0,IFERROR(INDEX(INDIRECT(V$6&VLOOKUP(Summary,Ref!$Y$13:$AC$18,3,FALSE)),MATCH(IF($P52="At Issue",VLOOKUP(Summary,Ref!$Y$13:$AC$18,2,FALSE),$P52),INDIRECT(V$6&VLOOKUP(Summary,Ref!$Y$13:$AC$18,4,FALSE)),0),VLOOKUP(V$10,Ref!$Y$61:$AA$63,2,FALSE)),0)))} | W52: {=IF($P52="","",IF(W$11="",0,IFERROR(INDEX(INDIRECT(W$6&VLOOKUP(Summary,Ref!$Y$13:$AC$18,3,FALSE)),MATCH(IF($P52="At Issue",VLOOKUP(Summary,Ref!$Y$13:$AC$18,2,FALSE),$P52),INDIRECT(W$6&VLOOKUP(Summary,Ref!$Y$13:$AC$18,4,FALSE)),0),VLOOKUP(W$10,Ref!$Y$61:$AA$63,2,FALSE)),0)))} | X52: =IF($P52="","",'Inputs & Summary'!S50) | Y52: =IF($P52="","",'Inputs & Summary'!T50) | Z52: =IF($P52="","",IF($Z$11="",0,'Inputs & Summary'!X50)) | AA52: =IF($P52="","",IF($AA$11="",0,IF(AND(LivBen<>"None",RIGHT(Category,2)<>"NY"),'Inputs & Summary'!AH50,""))) | AB52: =IF($P52="","",'Inputs & Summary'!Y50) | AC52: =IF($P52="","",IF(RIGHT(Category,2)="NY",'Inputs & Summary'!AH50,SUM('Inputs & Summary'!AB50,'Inputs & Summary'!AE50*('Inputs & Summary'!AD50="Yes"),'Inputs & Summary'!AG50))) | AD52: =IF($P52="","",'Inputs & Summary'!AI50) | AE52: =IF($P52="","",'Inputs & Summary'!Z50) | AF52: =IF($P52="","",'Inputs & Summary'!U50) | AG52: =IF($P52="","",'Inputs & Summary'!V50) | AH52: =IF($P52="","",'Inputs & Summary'!W50) | AI52: =IF($P52="","",IF($AI$11="",0,'Inputs & Summary'!AM50)) | AJ52: =IF($P52="","",IF($AJ$11="",0,IF(PTab="P7",'Inputs & Summary'!AQ50,'Inputs & Summary'!AA50))) | AK52: =IF($P52="","",'Inputs & Summary'!AJ50)
P53: =IF('Inputs & Summary'!O51="","",IF('Inputs & Summary'!O51=0,"At Issue",'Inputs & Summary'!P51)) | Q53: =IF($P53="","",'Inputs & Summary'!O51) | R53: =IF($P53="","",'Inputs & Summary'!Q51) | S53: {=IF($P53="","",IF(S$11="",0,IFERROR(INDEX(INDIRECT(S$6&VLOOKUP(Summary,Ref!$Y$13:$AC$18,3,FALSE)),MATCH(IF($P53="At Issue",VLOOKUP(Summary,Ref!$Y$13:$AC$18,2,FALSE),$P53),INDIRECT(S$6&VLOOKUP(Summary,Ref!$Y$13:$AC$18,4,FALSE)),0),VLOOKUP(S$10,Ref!$Y$61:$AA$63,2,FALSE)),0)))} | T53: {=IF($P53="","",IF(T$11="",0,IFERROR(INDEX(INDIRECT(T$6&VLOOKUP(Summary,Ref!$Y$13:$AC$18,3,FALSE)),MATCH(IF($P53="At Issue",VLOOKUP(Summary,Ref!$Y$13:$AC$18,2,FALSE),$P53),INDIRECT(T$6&VLOOKUP(Summary,Ref!$Y$13:$AC$18,4,FALSE)),0),VLOOKUP(T$10,Ref!$Y$61:$AA$63,2,FALSE)),0)))} | U53: {=IF($P53="","",IF(U$11="",0,IFERROR(INDEX(INDIRECT(U$6&VLOOKUP(Summary,Ref!$Y$13:$AC$18,3,FALSE)),MATCH(IF($P53="At Issue",VLOOKUP(Summary,Ref!$Y$13:$AC$18,2,FALSE),$P53),INDIRECT(U$6&VLOOKUP(Summary,Ref!$Y$13:$AC$18,4,FALSE)),0),VLOOKUP(U$10,Ref!$Y$61:$AA$63,2,FALSE)),0)))} | V53: {=IF($P53="","",IF(V$11="",0,IFERROR(INDEX(INDIRECT(V$6&VLOOKUP(Summary,Ref!$Y$13:$AC$18,3,FALSE)),MATCH(IF($P53="At Issue",VLOOKUP(Summary,Ref!$Y$13:$AC$18,2,FALSE),$P53),INDIRECT(V$6&VLOOKUP(Summary,Ref!$Y$13:$AC$18,4,FALSE)),0),VLOOKUP(V$10,Ref!$Y$61:$AA$63,2,FALSE)),0)))} | W53: {=IF($P53="","",IF(W$11="",0,IFERROR(INDEX(INDIRECT(W$6&VLOOKUP(Summary,Ref!$Y$13:$AC$18,3,FALSE)),MATCH(IF($P53="At Issue",VLOOKUP(Summary,Ref!$Y$13:$AC$18,2,FALSE),$P53),INDIRECT(W$6&VLOOKUP(Summary,Ref!$Y$13:$AC$18,4,FALSE)),0),VLOOKUP(W$10,Ref!$Y$61:$AA$63,2,FALSE)),0)))} | X53: =IF($P53="","",'Inputs & Summary'!S51) | Y53: =IF($P53="","",'Inputs & Summary'!T51) | Z53: =IF($P53="","",IF($Z$11="",0,'Inputs & Summary'!X51)) | AA53: =IF($P53="","",IF($AA$11="",0,IF(AND(LivBen<>"None",RIGHT(Category,2)<>"NY"),'Inputs & Summary'!AH51,""))) | AB53: =IF($P53="","",'Inputs & Summary'!Y51) | AC53: =IF($P53="","",IF(RIGHT(Category,2)="NY",'Inputs & Summary'!AH51,SUM('Inputs & Summary'!AB51,'Inputs & Summary'!AE51*('Inputs & Summary'!AD51="Yes"),'Inputs & Summary'!AG51))) | AD53: =IF($P53="","",'Inputs & Summary'!AI51) | AE53: =IF($P53="","",'Inputs & Summary'!Z51) | AF53: =IF($P53="","",'Inputs & Summary'!U51) | AG53: =IF($P53="","",'Inputs & Summary'!V51) | AH53: =IF($P53="","",'Inputs & Summary'!W51) | AI53: =IF($P53="","",IF($AI$11="",0,'Inputs & Summary'!AM51)) | AJ53: =IF($P53="","",IF($AJ$11="",0,IF(PTab="P7",'Inputs & Summary'!AQ51,'Inputs & Summary'!AA51))) | AK53: =IF($P53="","",'Inputs & Summary'!AJ51)
P54: =IF('Inputs & Summary'!O52="","",IF('Inputs & Summary'!O52=0,"At Issue",'Inputs & Summary'!P52)) | Q54: =IF($P54="","",'Inputs & Summary'!O52) | R54: =IF($P54="","",'Inputs & Summary'!Q52) | S54: {=IF($P54="","",IF(S$11="",0,IFERROR(INDEX(INDIRECT(S$6&VLOOKUP(Summary,Ref!$Y$13:$AC$18,3,FALSE)),MATCH(IF($P54="At Issue",VLOOKUP(Summary,Ref!$Y$13:$AC$18,2,FALSE),$P54),INDIRECT(S$6&VLOOKUP(Summary,Ref!$Y$13:$AC$18,4,FALSE)),0),VLOOKUP(S$10,Ref!$Y$61:$AA$63,2,FALSE)),0)))} | T54: {=IF($P54="","",IF(T$11="",0,IFERROR(INDEX(INDIRECT(T$6&VLOOKUP(Summary,Ref!$Y$13:$AC$18,3,FALSE)),MATCH(IF($P54="At Issue",VLOOKUP(Summary,Ref!$Y$13:$AC$18,2,FALSE),$P54),INDIRECT(T$6&VLOOKUP(Summary,Ref!$Y$13:$AC$18,4,FALSE)),0),VLOOKUP(T$10,Ref!$Y$61:$AA$63,2,FALSE)),0)))} | U54: {=IF($P54="","",IF(U$11="",0,IFERROR(INDEX(INDIRECT(U$6&VLOOKUP(Summary,Ref!$Y$13:$AC$18,3,FALSE)),MATCH(IF($P54="At Issue",VLOOKUP(Summary,Ref!$Y$13:$AC$18,2,FALSE),$P54),INDIRECT(U$6&VLOOKUP(Summary,Ref!$Y$13:$AC$18,4,FALSE)),0),VLOOKUP(U$10,Ref!$Y$61:$AA$63,2,FALSE)),0)))} | V54: {=IF($P54="","",IF(V$11="",0,IFERROR(INDEX(INDIRECT(V$6&VLOOKUP(Summary,Ref!$Y$13:$AC$18,3,FALSE)),MATCH(IF($P54="At Issue",VLOOKUP(Summary,Ref!$Y$13:$AC$18,2,FALSE),$P54),INDIRECT(V$6&VLOOKUP(Summary,Ref!$Y$13:$AC$18,4,FALSE)),0),VLOOKUP(V$10,Ref!$Y$61:$AA$63,2,FALSE)),0)))} | W54: {=IF($P54="","",IF(W$11="",0,IFERROR(INDEX(INDIRECT(W$6&VLOOKUP(Summary,Ref!$Y$13:$AC$18,3,FALSE)),MATCH(IF($P54="At Issue",VLOOKUP(Summary,Ref!$Y$13:$AC$18,2,FALSE),$P54),INDIRECT(W$6&VLOOKUP(Summary,Ref!$Y$13:$AC$18,4,FALSE)),0),VLOOKUP(W$10,Ref!$Y$61:$AA$63,2,FALSE)),0)))} | X54: =IF($P54="","",'Inputs & Summary'!S52) | Y54: =IF($P54="","",'Inputs & Summary'!T52) | Z54: =IF($P54="","",IF($Z$11="",0,'Inputs & Summary'!X52)) | AA54: =IF($P54="","",IF($AA$11="",0,IF(AND(LivBen<>"None",RIGHT(Category,2)<>"NY"),'Inputs & Summary'!AH52,""))) | AB54: =IF($P54="","",'Inputs & Summary'!Y52) | AC54: =IF($P54="","",IF(RIGHT(Category,2)="NY",'Inputs & Summary'!AH52,SUM('Inputs & Summary'!AB52,'Inputs & Summary'!AE52*('Inputs & Summary'!AD52="Yes"),'Inputs & Summary'!AG52))) | AD54: =IF($P54="","",'Inputs & Summary'!AI52) | AE54: =IF($P54="","",'Inputs & Summary'!Z52) | AF54: =IF($P54="","",'Inputs & Summary'!U52) | AG54: =IF($P54="","",'Inputs & Summary'!V52) | AH54: =IF($P54="","",'Inputs & Summary'!W52) | AI54: =IF($P54="","",IF($AI$11="",0,'Inputs & Summary'!AM52)) | AJ54: =IF($P54="","",IF($AJ$11="",0,IF(PTab="P7",'Inputs & Summary'!AQ52,'Inputs & Summary'!AA52))) | AK54: =IF($P54="","",'Inputs & Summary'!AJ52)
... P58: =IF('Inputs & Summary'!O56="","",IF('Inputs & Summary'!O56=0,"At Issue",'Inputs & Summary'!P56)) | Q58: =IF($P58="","",'Inputs & Summary'!O56) | R58: =IF($P58="","",'Inputs & Summary'!Q56) | S58: {=IF($P58="","",IF(S$11="",0,IFERROR(INDEX(INDIRECT(S$6&VLOOKUP(Summary,Ref!$Y$13:$AC$18,3,FALSE)),MATCH(IF($P58="At Issue",VLOOKUP(Summary,Ref!$Y$13:$AC$18,2,FALSE),$P58),INDIRECT(S$6&VLOOKUP(Summary,Ref!$Y$13:$AC$18,4,FALSE)),0),VLOOKUP(S$10,Ref!$Y$61:$AA$63,2,FALSE)),0)))} | T58: {=IF($P58="","",IF(T$11="",0,IFERROR(INDEX(INDIRECT(T$6&VLOOKUP(Summary,Ref!$Y$13:$AC$18,3,FALSE)),MATCH(IF($P58="At Issue",VLOOKUP(Summary,Ref!$Y$13:$AC$18,2,FALSE),$P58),INDIRECT(T$6&VLOOKUP(Summary,Ref!$Y$13:$AC$18,4,FALSE)),0),VLOOKUP(T$10,Ref!$Y$61:$AA$63,2,FALSE)),0)))} | U58: {=IF($P58="","",IF(U$11="",0,IFERROR(INDEX(INDIRECT(U$6&VLOOKUP(Summary,Ref!$Y$13:$AC$18,3,FALSE)),MATCH(IF($P58="At Issue",VLOOKUP(Summary,Ref!$Y$13:$AC$18,2,FALSE),$P58),INDIRECT(U$6&VLOOKUP(Summary,Ref!$Y$13:$AC$18,4,FALSE)),0),VLOOKUP(U$10,Ref!$Y$61:$AA$63,2,FALSE)),0)))} | V58: {=IF($P58="","",IF(V$11="",0,IFERROR(INDEX(INDIRECT(V$6&VLOOKUP(Summary,Ref!$Y$13:$AC$18,3,FALSE)),MATCH(IF($P58="At Issue",VLOOKUP(Summary,Ref!$Y$13:$AC$18,2,FALSE),$P58),INDIRECT(V$6&VLOOKUP(Summary,Ref!$Y$13:$AC$18,4,FALSE)),0),VLOOKUP(V$10,Ref!$Y$61:$AA$63,2,FALSE)),0)))} | W58: {=IF($P58="","",IF(W$11="",0,IFERROR(INDEX(INDIRECT(W$6&VLOOKUP(Summary,Ref!$Y$13:$AC$18,3,FALSE)),MATCH(IF($P58="At Issue",VLOOKUP(Summary,Ref!$Y$13:$AC$18,2,FALSE),$P58),INDIRECT(W$6&VLOOKUP(Summary,Ref!$Y$13:$AC$18,4,FALSE)),0),VLOOKUP(W$10,Ref!$Y$61:$AA$63,2,FALSE)),0)))} | X58: =IF($P58="","",'Inputs & Summary'!S56) | Y58: =IF($P58="","",'Inputs & Summary'!T56) | Z58: =IF($P58="","",IF($Z$11="",0,'Inputs & Summary'!X56)) | AA58: =IF($P58="","",IF($AA$11="",0,IF(AND(LivBen<>"None",RIGHT(Category,2)<>"NY"),'Inputs & Summary'!AH56,""))) | AB58: =IF($P58="","",'Inputs & Summary'!Y56) | AC58: =IF($P58="","",IF(RIGHT(Category,2)="NY",'Inputs & Summary'!AH56,SUM('Inputs & Summary'!AB56,'Inputs & Summary'!AE56*('Inputs & Summary'!AD56="Yes"),'Inputs & Summary'!AG56))) | AD58: =IF($P58="","",'Inputs & Summary'!AI56) | AE58: =IF($P58="","",'Inputs & Summary'!Z56) | AF58: =IF($P58="","",'Inputs & Summary'!U56) | AG58: =IF($P58="","",'Inputs & Summary'!V56) | AH58: =IF($P58="","",'Inputs & Summary'!W56) | AI58: =IF($P58="","",IF($AI$11="",0,'Inputs & Summary'!AM56)) | AJ58: =IF($P58="","",IF($AJ$11="",0,IF(PTab="P7",'Inputs & Summary'!AQ56,'Inputs & Summary'!AA56))) | AK58: =IF($P58="","",'Inputs & Summary'!AJ56)
P60: Totals | S60: {=TEXT(IFERROR(SUMPRODUCT(GEOMEAN(IF(IF(OR(Summary="Favorable",Summary="Unfavorable",Summary="Most Recent"),INDIRECT("S14:S"&(13+10)),INDIRECT("S14:S"&(13+Projection)))<>"-",IF(IF(OR(Summary="Favorable",Summary="Unfavorable",Summary="Most Recent"),INDIRECT("S14:S"&(13+10)),INDIRECT("S14:S"&(13+Projection)))<>"",IF(OR(Summary="Favorable",Summary="Unfavorable",Summary="Most Recent"),INDIRECT("S14:S"&(13+10)),INDIRECT("S14:S"&(13+Projection)))))+1)-1),"Examine"),"0.00%")&" Avg Annual"} -> Examine Avg Annual | T60: {=TEXT(IFERROR(SUMPRODUCT(GEOMEAN(IF(IF(OR(Summary="Favorable",Summary="Unfavorable",Summary="Most Recent"),INDIRECT("T14:T"&(13+10)),INDIRECT("T14:T"&(13+Projection)))<>"-",IF(IF(OR(Summary="Favorable",Summary="Unfavorable",Summary="Most Recent"),INDIRECT("T14:T"&(13+10)),INDIRECT("T14:T"&(13+Projection)))<>"",IF(OR(Summary="Favorable",Summary="Unfavorable",Summary="Most Recent"),INDIRECT("T14:T"&(13+10)),INDIRECT("T14:T"&(13+Projection)))))+1)-1),"Examine"),"0.00%")&" Avg Annual"} -> Examine Avg Annual | U60: {=TEXT(IFERROR(SUMPRODUCT(GEOMEAN(IF(IF(OR(Summary="Favorable",Summary="Unfavorable",Summary="Most Recent"),INDIRECT("U14:U"&(13+10)),INDIRECT("U14:U"&(13+Projection)))<>"-",IF(IF(OR(Summary="Favorable",Summary="Unfavorable",Summary="Most Recent"),INDIRECT("U14:U"&(13+10)),INDIRECT("U14:U"&(13+Projection)))<>"",IF(OR(Summary="Favorable",Summary="Unfavorable",Summary="Most Recent"),INDIRECT("U14:U"&(13+10)),INDIRECT("U14:U"&(13+Projection)))))+1)-1),"Examine"),"0.00%")&" Avg Annual"} -> Examine Avg Annual | V60: {=TEXT(IFERROR(SUMPRODUCT(GEOMEAN(IF(IF(OR(Summary="Favorable",Summary="Unfavorable",Summary="Most Recent"),INDIRECT("V14:V"&(13+10)),INDIRECT("X14:X"&(13+Projection)))<>"-",IF(IF(OR(Summary="Favorable",Summary="Unfavorable",Summary="Most Recent"),INDIRECT("V14:V"&(13+10)),INDIRECT("V14:V"&(13+Projection)))<>"",IF(OR(Summary="Favorable",Summary="Unfavorable",Summary="Most Recent"),INDIRECT("V14:V"&(13+10)),INDIRECT("V14:V"&(13+Projection)))))+1)-1),"Examine"),"0.00%")&" Avg Annual"} -> Examine Avg Annual | W60: {=TEXT(IFERROR(SUMPRODUCT(GEOMEAN(IF(IF(OR(Summary="Favorable",Summary="Unfavorable",Summary="Most Recent"),INDIRECT("W14:W"&(13+10)),INDIRECT("W14:W"&(13+Projection)))<>"-",IF(IF(OR(Summary="Favorable",Summary="Unfavorable",Summary="Most Recent"),INDIRECT("W14:W"&(13+10)),INDIRECT("W14:W"&(13+Projection)))<>"",IF(OR(Summary="Favorable",Summary="Unfavorable",Summary="Most Recent"),INDIRECT("W14:W"&(13+10)),INDIRECT("W14:W"&(13+Projection)))))+1)-1),"Examine"),"0.00%")&" Avg Annual"} -> Examine Avg Annual | X60: {=TEXT(IFERROR(SUMPRODUCT(GEOMEAN(IF(IF(OR(Summary="Favorable",Summary="Unfavorable",Summary="Most Recent"),INDIRECT("X14:X"&(13+10)),INDIRECT("X14:X"&(13+Projection)))<>"-",IF(IF(OR(Summary="Favorable",Summary="Unfavorable",Summary="Most Recent"),INDIRECT("X14:X"&(13+10)),INDIRECT("X14:X"&(13+Projection)))<>"",IF(OR(Summary="Favorable",Summary="Unfavorable",Summary="Most Recent"),INDIRECT("X14:X"&(13+10)),INDIRECT("X14:X"&(13+Projection)))))+1)-1),"Examine"),"0.00%")&" Avg Annual"} -> Examine Avg Annual | Y60: =SUM(Y13:Y58) -> #REF! | Z60: =INDEX(Z$13:Z$58,MATCH(MAX($R$13:$R$58),$R$13:$R$58,0),1) -> #REF! | AA60: =SUM(AA13:AA58) -> #REF! | AB60: =INDEX(AB$13:AB$58,MATCH(MAX($R$13:$R$58),$R$13:$R$58,0),1) -> #REF! | AC60: =SUM(AC13:AC58) -> #REF! | AD60: =INDEX(AD$13:AD$58,MATCH(MAX($R$13:$R$58),$R$13:$R$58,0),1) -> #REF! | AE60: =SUM(AE13:AE58) -> #REF! | AF60: =INDEX(AF$13:AF$58,MATCH(MAX($R$13:$R$58),$R$13:$R$58,0),1) -> #REF! | AG60: =INDEX(AG$13:AG$58,MATCH(MAX($R$13:$R$58),$R$13:$R$58,0),1) -> #REF! | AH60: =INDEX(AH$13:AH$58,MATCH(MAX($R$13:$R$58),$R$13:$R$58,0),1) -> #REF! | AK60: =INDEX(AK$13:AK$58,MATCH(MAX($R$13:$R$58),$R$13:$R$58,0),1) -> #REF!

Sheet Inputs & Summary
O2: <= Expand for Strategy Rate Override | AG2: <= Expand for Ehnanced Income | AW2: <= Expand for Additional Detail
B3: Results Output → | O3: =IF(COUNTIFS($B$142:$B$171,"")<>COUNTIFS($B$142:$B$171,"",$C$142:$C$171,0)+COUNTIFS($B$142:$B$171,"",$C$142:$C$171,""),"!!! Review Strategy Allocations !!!",Summary&" Summary") -> Specific Summary | AL3: PFW Amount | AM3: Supplemental EOP Values | AR3: Fees
O4: =IF(PTab="P3","EOP Contract Values", "Following Year BOP Contract Values") -> Following Year BOP Contract Values | X4: =IF(PTab="P7","Transactions","Guaranteed Retirement Income") -> Guaranteed Retirement Income | AJ4: Legacy
P5: =IFERROR(INDEX(INDIRECT(PTab&"!$B$4:$EH$4"),MATCH(P$6,INDIRECT(PTab&"!$B$10:$EH$10"),0)),"") | Q5: =IFERROR(INDEX(INDIRECT(PTab&"!$B$4:$EH$4"),MATCH(Q$6,INDIRECT(PTab&"!$B$10:$EH$10"),0)),"") | R5: =IFERROR(INDEX(INDIRECT(PTab&"!$B$4:$EH$4"),MATCH(R$6,INDIRECT(PTab&"!$B$10:$EH$10"),0)),"") | S5: =IFERROR(INDEX(INDIRECT(PTab&"!$B$4:$EH$4"),MATCH(S$6,INDIRECT(PTab&"!$B$10:$EH$10"),0)),"") | T5: =IFERROR(INDEX(INDIRECT(PTab&"!$B$4:$EH$4"),MATCH(T$6,INDIRECT(PTab&"!$B$10:$EH$10"),0)),"") | U5: =IF(RIGHT(Category,2)="NY",IFERROR(INDEX(INDIRECT(PTab&"!$AN$4:$EH$4"),MATCH(U$6,INDIRECT(PTab&"!$AN$10:$EH$10"),0)),""),IFERROR(INDEX(INDIRECT(PTab&"!$BB$4:$EH$4"),MATCH(U$6,INDIRECT(PTab&"!$BB$10:$EH$10"),0)),"")) | V5: =IF(RIGHT(Category,2)="NY",IFERROR(INDEX(INDIRECT(PTab&"!$AN$4:$EH$4"),MATCH(V$6,INDIRECT(PTab&"!$AN$10:$EH$10"),0)),""),IFERROR(INDEX(INDIRECT(PTab&"!$BB$4:$EH$4"),MATCH(V$6,INDIRECT(PTab&"!$BB$10:$EH$10"),0)),"")) | W5: =IF(RIGHT(Category,2)="NY",IFERROR(INDEX(INDIRECT(PTab&"!$AN$4:$EH$4"),MATCH(W$6,INDIRECT(PTab&"!$AN$10:$EH$10"),0)),""),IFERROR(INDEX(INDIRECT(PTab&"!$BB$4:$EH$4"),MATCH(W$6,INDIRECT(PTab&"!$BB$10:$EH$10"),0)),"")) | X5: =IFERROR(INDEX(INDIRECT(PTab&"!$BB$4:$EH$4"),MATCH(X$6,INDIRECT(PTab&"!$BB$10:$EH$10"),0)),"") | Y5: =IF(RIGHT(Category,2)="NY",IFERROR(INDEX(INDIRECT(PTab&"!$AN$4:$EH$4"),MATCH(Y$6,INDIRECT(PTab&"!$AN$10:$EH$10"),0)),""),IFERROR(INDEX(INDIRECT(PTab&"!$BB$4:$EH$4"),MATCH(Y$6,INDIRECT(PTab&"!$BB$10:$EH$10"),0)),"")) | AA5: =IFERROR(INDEX(INDIRECT(PTab&"!$BB$4:$EH$4"),MATCH(AA$6,INDIRECT(PTab&"!$BB$10:$EH$10"),0)),"") | AB5: =IFERROR(INDEX(INDIRECT(PTab&"!$B$4:$EH$4"),MATCH(AB$6,INDIRECT(PTab&"!$B$10:$EH$10"),0)),"") | AE5: =IFERROR(INDEX(INDIRECT(PTab&"!$BB$4:$EH$4"),MATCH(AE$6,INDIRECT(PTab&"!$BB$10:$EH$10"),0)),"") | AG5: =IF(RIGHT(Category,2)="NY",IFERROR(INDEX(INDIRECT(PTab&"!$AN$4:$EH$4"),MATCH(AG$6,INDIRECT(PTab&"!$AN$10:$EH$10"),0)),""),IFERROR(INDEX(INDIRECT(PTab&"!$BB$4:$EH$4"),MATCH(AG$6,INDIRECT(PTab&"!$BB$10:$EH$10"),0)),"")) | AH5: =IF(RIGHT(Category,2)="NY",IFERROR(INDEX(INDIRECT(PTab&"!$AN$4:$EH$4"),MATCH(AH$6,INDIRECT(PTab&"!$AN$10:$EH$10"),0)),""),IFERROR(INDEX(INDIRECT(PTab&"!$B$4:$EH$4"),MATCH(AH$6,INDIRECT(PTab&"!$B$10:$EH$10"),0)),"")) | AJ5: =IF(RIGHT(Category,2)="NY",IFERROR(INDEX(INDIRECT(PTab&"!$AN$4:$EH$4"),MATCH(AJ$6,INDIRECT(PTab&"!$AN$10:$EH$10"),0)),""),IFERROR(INDEX(INDIRECT(PTab&"!$BB$4:$EH$4"),MATCH(AJ$6,INDIRECT(PTab&"!$BB$10:$EH$10"),0)),"")) | AL5: =IFERROR(INDEX(INDIRECT(PTab&"!$B$4:$BA$4"),MATCH(AL$6,INDIRECT(PTab&"!$B$10:$BA$10"),0)),"") | AM5: =IF(PTab="P7",IFERROR(INDEX(INDIRECT(PTab&"!$CP$4:$EH$4"),MATCH(AM$6,INDIRECT(PTab&"!$CP$10:$EH$10"),0)),""),IF(Ref!$S$53="Y",IFERROR(INDEX(INDIRECT(PTab&"!$BO$4:$EE$4"),MATCH(AM$6,INDIRECT(PTab&"!$BO$10:$EE$10"),0)),""),"")) | AN5: =IF(PTab="P7",IFERROR(INDEX(INDIRECT(PTab&"!$CP$4:$EH$4"),MATCH(AN$6,INDIRECT(PTab&"!$CP$10:$EH$10"),0)),""),"") | AO5: =IF(PTab="P7",IFERROR(INDEX(INDIRECT(PTab&"!$CP$4:$EH$4"),MATCH(AO$6,INDIRECT(PTab&"!$CP$10:$EH$10"),0)),""),"") | AP5: =IF(PTab="P7",IFERROR(INDEX(INDIRECT(PTab&"!$CP$4:$EH$4"),MATCH(AP$6,INDIRECT(PTab&"!$CP$10:$EH$10"),0)),""),"") | AQ5: =IFERROR(INDEX(INDIRECT(PTab&"!$B$4:$EH$4"),MATCH(AQ$6,INDIRECT(PTab&"!$B$10:$EH$10"),0)),"") | AR5: =IFERROR(INDEX(INDIRECT(PTab&"!$BB$4:$EH$4"),MATCH(AR$6,INDIRECT(PTab&"!$BB$10:$EH$10"),0)),"") | AS5: =IFERROR(INDEX(INDIRECT(PTab&"!$BB$4:$EH$4"),MATCH(AS$6,INDIRECT(PTab&"!$BB$10:$EH$10"),0)),"") | AT5: =IFERROR(INDEX(INDIRECT(PTab&"!$BB$4:$EH$4"),MATCH(AT$6,INDIRECT(PTab&"!$BB$10:$EH$10"),0)),"") | AU5: =IFERROR(INDEX(INDIRECT(PTab&"!$BB$4:$EH$4"),MATCH(AU$6,INDIRECT(PTab&"!$BB$10:$EH$10"),0)),"")
P6: Illustrated Date | Q6: Attained Age | S6: Contract Credited Rate | T6: Interest Earned | U6: =IF(RIGHT(Category,2)="NY","Total Contract Value after Reset","Total Contract Value") -> Total Contract Value | V6: Cash Surrender Value | W6: =IF(RIGHT(Category,2)="NY","MAV after Reset","Minimum Withdrawal Value") -> Minimum Withdrawal Value | X6: Income Base | Y6: =IF(RIGHT(Category,2)="NY","GLIA","MAWA / Remaining MAWA") -> MAWA / Remaining MAWA | AA6: =IF(Ref!$S$53="Y","GMAB Amount","") -> GMAB Amount | AB6: =IF(PTab="P7","Withdrawal / Systematic Withdrawal","Pre-Activation / Systematic Withdrawal") -> Pre-Activation / Systematic Withdrawal | AE6: Enhanced Income (XS of MAWA) | AG6: =IF(RIGHT(Category,2)="NY","N/A for this Product","Lifetime Income Withdrawal") -> Lifetime Income Withdrawal | AH6: =IF(RIGHT(Category,2)="NY","Total Gross Withdrawals","Income Credit") -> Income Credit | AI6: Cumulative Withdrawals | AJ6: Death Benefit | AL6: =IF(PTab="P7","Free WD Allowance","Free WD Amount") -> Free WD Amount | AM6: =IF(PTab="P7","GROP Amount",IF(Ref!$S$53="Y","GMAB Value","")) -> GMAB Value | AN6: ROP Amount | AO6: Overlay Base | AP6: Overlay Value | AQ6: Total Contract Value | AR6: GMWB Fee | AS6: Advisory Fee | AT6: Strategy Fee | AU6: Product Fee
B7: Variables Input ↓ | O7: Year | P7: Illustrated Date | Q7: Attained Age | R7: GSPC | S7: {=IF(Summary="Favorable","Favorable Period: "&TEXT(INDIRECT($R$7&"!$G30"),"mm/dd/yyyy")&" - "&TEXT(INDIRECT($R$7&"!$I30"),"mm/dd/yyyy"),IF(Summary="Unfavorable","Unfavorable Period: "&TEXT(INDIRECT($R$7&"!$G31"),"mm/dd/yyyy")&" - "&TEXT(INDIRECT($R$7&"!$I31"),"mm/dd/yyyy"),""))} | U7: =IF(RIGHT(Category,2)="NY","Total Contract Value (Prior to Transaction)","Total Contract Value") -> Total Contract Value | V7: Cash Surrender Value | W7: Minimum Withdrawal Value | X7: =IF(OR(RIGHT(Category,2)="NY",PTab="P7"),"","Income Base") -> Income Base | Y7: =IF(AND(RIGHT(Category,2)="NY",LivBen<>"None"),"Initial Income Rate: "&TEXT(VLOOKUP(IF(Election="Joint Life", MIN(IssAge1,IssAge2),IssAge1),Ref!$BC$7:$BF$39,4,FALSE),"0.00%"), "") | Z7: Fees Total | AA7: =AA6 -> GMAB Amount | AB7: =IF(PTab="P7","Withdrawal","Pre-Activation Withdrawal") -> Pre-Activation Withdrawal | AC7: Enhanced Income Benefit Status Prior to CY Utilization | AD7: Claim Enhanced Income? (Yes / No) Manual Entry | AE7: Enhanced Income Amount XS of MAWA | AG7: =IF(OR(RIGHT(Category,2)="NY",LivBen="None"),"","Withdrawal Rate:") | AH7: =IF(RIGHT(Category,2)="NY","Total Gross Withdrawals",IF(PTab="P7","","Income Credit")) -> Income Credit | AI7: Cumulative Withdrawals | AJ7: Death Benefit | AL7: PFW Amount Avaliable Prior to Withdrawal | AM7: =AM6 -> GMAB Value | AN7: ROP Amount | AO7: Overlay Base | AP7: Overlay Value | AQ7: Overlay Credit | AR7: GMWB Fee | AS7: Advisory Fee | AT7: Strategy Fee | AU7: AICO Product Fee
R8: 1-Year | Y8: =IF(AND(RIGHT(Category,2)="NY",LivBen<>"None"),"Income % Increase: "&TEXT(IPI,"0.00%"),"") | AG8: =IF(OR(RIGHT(Category,2)="NY",LivBen="None"),"",VLOOKUP(WDAge,Ref!$BC$7:$BF$39,2))
R9: PTP Index Return (Select Index & Term Above) | S9: Contract Credited Rate | T9: =IF(OR(PTab="P7",AND(PTab="P2",Ref!$S$53="Y")),"Interest Earned including","Interest Earned") -> Interest Earned including | Y9: =IF(PTab="P7","", "Annual Income for Life") -> Annual Income for Life | AB9: Manual Entry as a positive amount | AG9: =IF(RIGHT(Category,2)="NY","","Systematic / Lifetime Income Withdrawal Amount / RMD") -> Systematic / Lifetime Income Withdrawal Amount / RMD
T10: {=IF(PTab="P7",IF(INDEX(INDIRECT(PTab&"!$B$11:$EH$563"),MATCH(6&"|"&1,INDIRECT(PTab&"!$D$11:$D$563")&"|"&INDIRECT(PTab&"!$C$11:$C$563"),0),MATCH("Overlay Credit",INDIRECT(PTab&"!$B$10:$EH$10"),0))=0,"Overlay Credit of zero","Overlay Credit of "&TEXT(INDEX(INDIRECT(PTab&"!$B$11:$EH$563"),MATCH(6&"|"&1,INDIRECT(PTab&"!$D$11:$D$563")&"|"&INDIRECT(PTab&"!$C$11:$C$563"),0),MATCH("Overlay Credit",INDIRECT(PTab&"!$B$10:$EH$10"),0)),"$#,###")), IF(Ref!$S$53="Y",IF(SUM($AA$11:$AA$56)=0,"Aggregate GMAB Amount of zero","Aggreagate GMAB Amount of "&TEXT(SUM($AA$11:$AA$56),"$#,###")),""))} -> #REF! | AC10: Enhanced Income Benefit Availability
B11: Primary Tool Levers | O11: 0 | P11: {=IF($O11="","",OFFSET(INDIRECT(PTab&"!"&CELL("address",$B$11)),12*$O11,0))} -> #REF! | Q11: =IF($O11="","",VLOOKUP($P11,INDIRECT(PTab&"!$B:$EH"),Q$5,FALSE)) -> #REF! | R11: =IF($O11="","",IF(MOD(O11,LEFT($R$8))=0,IFERROR(INDEX(INDIRECT(R$7&VLOOKUP(Summary,Ref!$Y$13:$AC$18,3,FALSE)),MATCH($P11,INDIRECT(R$7&VLOOKUP(Summary,Ref!$Y$13:$AC$18,4,FALSE)),0),MATCH(R$8,INDIRECT(R$7&VLOOKUP(Summary,Ref!$Y$13:$AC$18,5,FALSE)),0)),0),0)) -> 0 | S11: =IF($O11="","",VLOOKUP($P11,INDIRECT(PTab&"!$B:$EH"),S$5,FALSE)) -> #REF! | T11: {=IF($O11="","",VLOOKUP($P11,INDIRECT(PTab&"!$B:$EH"),T$5,FALSE)+IF(AND(PTab="P7",$O11=5),INDEX(INDIRECT(PTab&"!$B$11:$EH$563"),MATCH(6&"|"&1,INDIRECT(PTab&"!$D$11:$D$563")&"|"&INDIRECT(PTab&"!$C$11:$C$563"),0),MATCH("Overlay Credit",INDIRECT(PTab&"!$B$10:$EH$10"),0)),IF(AND(PTab="P2",Ref!$S$53="Y"),AA11,0)))} -> #REF! | U11: =IF($O11="","",VLOOKUP($P11,INDIRECT(PTab&"!$B:$EH"),U$5,FALSE)) -> #REF! | V11: =IF($O11="","",VLOOKUP($P11,INDIRECT(PTab&"!$B:$EH"),V$5,FALSE)) -> #REF! | W11: =IF($O11="","",VLOOKUP($P11,INDIRECT(PTab&"!$B:$EH"),W$5,FALSE)) -> #REF! | X11: =IF(OR($O11="",RIGHT(Category,2)="NY"),"",VLOOKUP($P11,INDIRECT(PTab&"!$B:$EH"),X$5,FALSE)) -> #REF! | Y11: =IF($O11="","",VLOOKUP($P11,INDIRECT(PTab&"!$B:$EH"),Y$5,FALSE)) -> #REF! | Z11: =IF($O11="","",SUM(AR11:AU11)) -> 0 | AA11: =IF(OR($O11="",RIGHT(Category,2)="NY"),"",VLOOKUP($P11,INDIRECT(PTab&"!$B:$EH"),AA$5,FALSE)) -> #REF! | AC11: =IF($O11="","",IF(EICRInd="Not Available","Not Available",IF(OR($O11<2,$Q11<WDAge),"Eligibility Criteria Not Met",VLOOKUP(COUNTIFS($AD10:$AD$11,"Yes"),Ref!$AL$58:$AM$63,2)))) -> Not Available | AD11: No | AE11: =IF($O11="","",IFERROR(VLOOKUP(EOMONTH($P11,11),INDIRECT(PTab&"!$B:$EH"),AE$5,FALSE),0)) -> 0 | AG11: =IF($O11="","",IFERROR(-VLOOKUP(EOMONTH($P11,11),INDIRECT(PTab&"!$B:$EH"),AG$5,FALSE)-IF(OR(RMDInd="Yes",SWInd="Yes"),VLOOKUP(EOMONTH($P11,11),INDIRECT(PTab&"!$B:$EH"),AB$5,FALSE)+AB11*(AB11<>""),0),0)) -> 0 | AH11: =IF($O11="","",IF(RIGHT(Category,2)="NY",IFERROR(-VLOOKUP($P11,INDIRECT(PTab&"!$B:$EH"),AH$5,FALSE),0),IFERROR(VLOOKUP($P11,INDIRECT(PTab&"!$B:$EH"),AH$5,FALSE),0))) -> 0 | AI11: =IF($O11="","",IF($O11=0,IF(RIGHT(Category,2)="NY",AH11,SUM(AB11,AG11)),IF(RIGHT(Category,2)="NY",SUM(AH11,AI10),SUM(AB11,AE11*(AD11="Yes"),AG11,AI10)))) -> 0 | AJ11: =IF($O11="","",VLOOKUP($P11,INDIRECT(PTab&"!$B:$EH"),AJ$5,FALSE)) -> #REF! | AL11: =IF($O11="","",IF(OR(PTab="P3",PTab="P7"),VLOOKUP($P11,INDIRECT(PTab&"!$B:$BA"),AL$5,FALSE),VLOOKUP(EOMONTH($P11,11),INDIRECT(PTab&"!$B:$BA"),AL$5,FALSE))) -> #REF! | AM11: =IF($O11="","",IF(OR(PTab="P7",Ref!$S$53="Y"),VLOOKUP($P11,INDIRECT(PTab&"!$B:$EH"),AM$5,FALSE),"")) -> #REF! | AN11: =IF($O11="","",IF(PTab="P7",VLOOKUP($P11,INDIRECT(PTab&"!$B:$EH"),AN$5,FALSE),"")) | AO11: =IF($O11="","",IF(PTab="P7",VLOOKUP($P11,INDIRECT(PTab&"!$B:$EH"),AO$5,FALSE),"")) | AP11: =IF($O11="","",IF(PTab="P7",VLOOKUP($P11,INDIRECT(PTab&"!$B:$EH"),AP$5,FALSE),"")) | AQ11: =IF($O11="","", IF(PTab="P7",IF($P11=$P$11,0,MAX(AP11-(VLOOKUP($P11,INDIRECT(PTab&"!$B:$EH"),AQ$5,FALSE)-AU11),0)),"")) | AR11: =IF($O11="","",IFERROR(-VLOOKUP($P11,INDIRECT(PTab&"!$B:$EH"),AR$5,FALSE),0)) -> 0 | AS11: =IF($O11="","",IFERROR(-VLOOKUP($P11,INDIRECT(PTab&"!$B:$EH"),AS$5,FALSE),0)) -> 0 | AT11: =IF($O11="","",IFERROR(-VLOOKUP($P11,INDIRECT(PTab&"!$B:$EH"),AT$5,FALSE),0)) -> 0 | AU11: =IF($O11="","",IFERROR(-VLOOKUP($P11,INDIRECT(PTab&"!$B:$EH"),AU$5,FALSE),0)) -> 0
B12: Product Category | C12: Index Series | O12: =IFERROR(IF(AND(OR(Summary="Favorable",Summary="Unfavorable",Summary="Most Recent"),OR(($O11+1)>10,$O11="")),"",IF(OR(($O11+1)>Projection,$O11=""),"",$O11+1)),"") -> 1 | P12: {=IF($O12="","",OFFSET(INDIRECT(PTab&"!"&CELL("address",$B$11)),12*$O12,0))} -> #REF! | Q12: =IF($O12="","",VLOOKUP($P12,INDIRECT(PTab&"!$B:$EH"),Q$5,FALSE)) -> #REF! | R12: =IF($O12="","",IF(MOD(O12,LEFT($R$8))=0,IFERROR(INDEX(INDIRECT(R$7&VLOOKUP(Summary,Ref!$Y$13:$AC$18,3,FALSE)),MATCH($P12,INDIRECT(R$7&VLOOKUP(Summary,Ref!$Y$13:$AC$18,4,FALSE)),0),MATCH(R$8,INDIRECT(R$7&VLOOKUP(Summary,Ref!$Y$13:$AC$18,5,FALSE)),0)),0),0)) -> 0 | S12: =IF($O12="","",VLOOKUP($P12,INDIRECT(PTab&"!$B:$EH"),S$5,FALSE)) -> #REF! | T12: {=IF($O12="","",VLOOKUP($P12,INDIRECT(PTab&"!$B:$EH"),T$5,FALSE)+IF(AND(PTab="P7",$O12=5),INDEX(INDIRECT(PTab&"!$B$11:$EH$563"),MATCH(6&"|"&1,INDIRECT(PTab&"!$D$11:$D$563")&"|"&INDIRECT(PTab&"!$C$11:$C$563"),0),MATCH("Overlay Credit",INDIRECT(PTab&"!$B$10:$EH$10"),0)),IF(AND(PTab="P2",Ref!$S$53="Y"),AA12,0)))} -> #REF! | U12: =IF($O12="","",VLOOKUP($P12,INDIRECT(PTab&"!$B:$EH"),U$5,FALSE)) -> #REF! | V12: =IF($O12="","",VLOOKUP($P12,INDIRECT(PTab&"!$B:$EH"),V$5,FALSE)) -> #REF! | W12: =IF($O12="","",VLOOKUP($P12,INDIRECT(PTab&"!$B:$EH"),W$5,FALSE)) -> #REF! | X12: =IF(OR($O12="",RIGHT(Category,2)="NY"),"",VLOOKUP($P12,INDIRECT(PTab&"!$B:$EH"),X$5,FALSE)) -> #REF! | Y12: =IF($O12="","",VLOOKUP($P12,INDIRECT(PTab&"!$B:$EH"),Y$5,FALSE)) -> #REF! | Z12: =IF($O12="","",SUM(AR12:AU12)) -> 0 | AA12: =IF(OR($O12="",RIGHT(Category,2)="NY"),"",VLOOKUP($P12,INDIRECT(PTab&"!$B:$EH"),AA$5,FALSE)) -> #REF! | AC12: =IF($O12="","",IF(EICRInd="Not Available","Not Available",IF(OR($O12<2,$Q12<WDAge),"Eligibility Criteria Not Met",VLOOKUP(COUNTIFS($AD11:$AD$11,"Yes"),Ref!$AL$58:$AM$63,2)))) -> Not Available | AD12: No | AE12: =IF($O12="","",IFERROR(VLOOKUP(EOMONTH($P12,11),INDIRECT(PTab&"!$B:$EH"),AE$5,FALSE),0)) -> 0 | AG12: =IF($O12="","",IFERROR(-VLOOKUP(EOMONTH($P12,11),INDIRECT(PTab&"!$B:$EH"),AG$5,FALSE)-IF(OR(RMDInd="Yes",SWInd="Yes"),VLOOKUP(EOMONTH($P12,11),INDIRECT(PTab&"!$B:$EH"),AB$5,FALSE)+AB12*(AB12<>""),0),0)) -> 0 | AH12: =IF($O12="","",IF(RIGHT(Category,2)="NY",IFERROR(-VLOOKUP($P12,INDIRECT(PTab&"!$B:$EH"),AH$5,FALSE),0),IFERROR(VLOOKUP($P12,INDIRECT(PTab&"!$B:$EH"),AH$5,FALSE),0))) -> 0 | AI12: =IF($O12="","",IF($O12=0,IF(RIGHT(Category,2)="NY",AH12,SUM(AB12,AG12)),IF(RIGHT(Category,2)="NY",SUM(AH12,AI11),SUM(AB12,AE12*(AD12="Yes"),AG12,AI11)))) -> 0 | AJ12: =IF($O12="","",VLOOKUP($P12,INDIRECT(PTab&"!$B:$EH"),AJ$5,FALSE)) -> #REF! | AL12: =IF($O12="","",IF(OR(PTab="P3",PTab="P7"),VLOOKUP($P12,INDIRECT(PTab&"!$B:$BA"),AL$5,FALSE),VLOOKUP(EOMONTH($P12,11),INDIRECT(PTab&"!$B:$BA"),AL$5,FALSE))) -> #REF! | AM12: =IF($O12="","",IF(OR(PTab="P7",Ref!$S$53="Y"),VLOOKUP($P12,INDIRECT(PTab&"!$B:$EH"),AM$5,FALSE),"")) -> #REF! | AN12: =IF($O12="","",IF(PTab="P7",VLOOKUP($P12,INDIRECT(PTab&"!$B:$EH"),AN$5,FALSE),"")) | AO12: =IF($O12="","",IF(PTab="P7",VLOOKUP($P12,INDIRECT(PTab&"!$B:$EH"),AO$5,FALSE),"")) | AP12: =IF($O12="","",IF(PTab="P7",VLOOKUP($P12,INDIRECT(PTab&"!$B:$EH"),AP$5,FALSE),"")) | AQ12: =IF($O12="","", IF(PTab="P7",IF($P12=$P$11,0,MAX(AP12-(VLOOKUP($P12,INDIRECT(PTab&"!$B:$EH"),AQ$5,FALSE)-AU12),0)),"")) | AR12: =IF($O12="","",IFERROR(-VLOOKUP($P12,INDIRECT(PTab&"!$B:$EH"),AR$5,FALSE),0)) -> 0 | AS12: =IF($O12="","",IFERROR(-VLOOKUP($P12,INDIRECT(PTab&"!$B:$EH"),AS$5,FALSE),0)) -> 0 | AT12: =IF($O12="","",IFERROR(-VLOOKUP($P12,INDIRECT(PTab&"!$B:$EH"),AT$5,FALSE),0)) -> 0 | AU12: =IF($O12="","",IFERROR(-VLOOKUP($P12,INDIRECT(PTab&"!$B:$EH"),AU$5,FALSE),0)) -> 0
B13: Period Tab Reference | C13: =VLOOKUP(Category,Ref!$AG$3:$AI$51,3,FALSE) -> P2 | O13: =IFERROR(IF(AND(OR(Summary="Favorable",Summary="Unfavorable",Summary="Most Recent"),OR(($O12+1)>10,$O12="")),"",IF(OR(($O12+1)>Projection,$O12=""),"",$O12+1)),"") -> 2 | P13: {=IF($O13="","",OFFSET(INDIRECT(PTab&"!"&CELL("address",$B$11)),12*$O13,0))} -> #REF! | Q13: =IF($O13="","",VLOOKUP($P13,INDIRECT(PTab&"!$B:$EH"),Q$5,FALSE)) -> #REF! | R13: =IF($O13="","",IF(MOD(O13,LEFT($R$8))=0,IFERROR(INDEX(INDIRECT("'"&R$7&"'"&VLOOKUP(Summary,Ref!$Y$13:$AC$18,3,FALSE)),MATCH($P13,INDIRECT(R$7&VLOOKUP(Summary,Ref!$Y$13:$AC$18,4,FALSE)),0),MATCH(R$8,INDIRECT(R$7&VLOOKUP(Summary,Ref!$Y$13:$AC$18,5,FALSE)),0)),0),0)) -> 0 | S13: =IF($O13="","",VLOOKUP($P13,INDIRECT(PTab&"!$B:$EH"),S$5,FALSE)) -> #REF! | T13: {=IF($O13="","",VLOOKUP($P13,INDIRECT(PTab&"!$B:$EH"),T$5,FALSE)+IF(AND(PTab="P7",$O13=5),INDEX(INDIRECT(PTab&"!$B$11:$EH$563"),MATCH(6&"|"&1,INDIRECT(PTab&"!$D$11:$D$563")&"|"&INDIRECT(PTab&"!$C$11:$C$563"),0),MATCH("Overlay Credit",INDIRECT(PTab&"!$B$10:$EH$10"),0)),IF(AND(PTab="P2",Ref!$S$53="Y"),AA13,0)))} -> #REF! | U13: =IF($O13="","",VLOOKUP($P13,INDIRECT(PTab&"!$B:$EH"),U$5,FALSE)) -> #REF! | V13: =IF($O13="","",VLOOKUP($P13,INDIRECT(PTab&"!$B:$EH"),V$5,FALSE)) -> #REF! | W13: =IF($O13="","",VLOOKUP($P13,INDIRECT(PTab&"!$B:$EH"),W$5,FALSE)) -> #REF! | X13: =IF(OR($O13="",RIGHT(Category,2)="NY"),"",VLOOKUP($P13,INDIRECT(PTab&"!$B:$EH"),X$5,FALSE)) -> #REF! | Y13: =IF($O13="","",VLOOKUP($P13,INDIRECT(PTab&"!$B:$EH"),Y$5,FALSE)) -> #REF! | Z13: =IF($O13="","",SUM(AR13:AU13)) -> 0 | AA13: =IF(OR($O13="",RIGHT(Category,2)="NY"),"",VLOOKUP($P13,INDIRECT(PTab&"!$B:$EH"),AA$5,FALSE)) -> #REF! | AC13: =IF($O13="","",IF(EICRInd="Not Available","Not Available",IF(OR($O13<2,$Q13<WDAge),"Eligibility Criteria Not Met",VLOOKUP(COUNTIFS($AD$11:$AD12,"Yes"),Ref!$AL$58:$AM$63,2)))) -> Not Available | AD13: No | AE13: =IF($O13="","",IFERROR(VLOOKUP(EOMONTH($P13,11),INDIRECT(PTab&"!$B:$EH"),AE$5,FALSE),0)) -> 0 | AG13: =IF($O13="","",IFERROR(-VLOOKUP(EOMONTH($P13,11),INDIRECT(PTab&"!$B:$EH"),AG$5,FALSE)-IF(OR(RMDInd="Yes",SWInd="Yes"),VLOOKUP(EOMONTH($P13,11),INDIRECT(PTab&"!$B:$EH"),AB$5,FALSE)+AB13*(AB13<>""),0),0)) -> 0 | AH13: =IF($O13="","",IF(RIGHT(Category,2)="NY",IFERROR(-VLOOKUP($P13,INDIRECT(PTab&"!$B:$EH"),AH$5,FALSE),0),IFERROR(VLOOKUP($P13,INDIRECT(PTab&"!$B:$EH"),AH$5,FALSE),0))) -> 0 | AI13: =IF($O13="","",IF($O13=0,IF(RIGHT(Category,2)="NY",AH13,SUM(AB13,AG13)),IF(RIGHT(Category,2)="NY",SUM(AH13,AI12),SUM(AB13,AE13*(AD13="Yes"),AG13,AI12)))) -> 0 | AJ13: =IF($O13="","",VLOOKUP($P13,INDIRECT(PTab&"!$B:$EH"),AJ$5,FALSE)) -> #REF! | AL13: =IF($O13="","",IF(OR(PTab="P3",PTab="P7"),VLOOKUP($P13,INDIRECT(PTab&"!$B:$BA"),AL$5,FALSE),VLOOKUP(EOMONTH($P13,11),INDIRECT(PTab&"!$B:$BA"),AL$5,FALSE))) -> #REF! | AM13: =IF($O13="","",IF(OR(PTab="P7",Ref!$S$53="Y"),VLOOKUP($P13,INDIRECT(PTab&"!$B:$EH"),AM$5,FALSE),"")) -> #REF! | AN13: =IF($O13="","",IF(PTab="P7",VLOOKUP($P13,INDIRECT(PTab&"!$B:$EH"),AN$5,FALSE),"")) | AO13: =IF($O13="","",IF(PTab="P7",VLOOKUP($P13,INDIRECT(PTab&"!$B:$EH"),AO$5,FALSE),"")) | AP13: =IF($O13="","",IF(PTab="P7",VLOOKUP($P13,INDIRECT(PTab&"!$B:$EH"),AP$5,FALSE),"")) | AQ13: =IF($O13="","", IF(PTab="P7",IF($P13=$P$11,0,MAX(AP13-(VLOOKUP($P13,INDIRECT(PTab&"!$B:$EH"),AQ$5,FALSE)-AU13),0)),"")) | AR13: =IF($O13="","",IFERROR(-VLOOKUP($P13,INDIRECT(PTab&"!$B:$EH"),AR$5,FALSE),0)) -> 0 | AS13: =IF($O13="","",IFERROR(-VLOOKUP($P13,INDIRECT(PTab&"!$B:$EH"),AS$5,FALSE),0)) -> 0 | AT13: =IF($O13="","",IFERROR(-VLOOKUP($P13,INDIRECT(PTab&"!$B:$EH"),AT$5,FALSE),0)) -> 0 | AU13: =IF($O13="","",IFERROR(-VLOOKUP($P13,INDIRECT(PTab&"!$B:$EH"),AU$5,FALSE),0)) -> 0
B14: Product | C14: Power Index Plus | O14: =IFERROR(IF(AND(OR(Summary="Favorable",Summary="Unfavorable",Summary="Most Recent"),OR(($O13+1)>10,$O13="")),"",IF(OR(($O13+1)>Projection,$O13=""),"",$O13+1)),"") -> 3 | P14: {=IF($O14="","",OFFSET(INDIRECT(PTab&"!"&CELL("address",$B$11)),12*$O14,0))} -> #REF! | Q14: =IF($O14="","",VLOOKUP($P14,INDIRECT(PTab&"!$B:$EH"),Q$5,FALSE)) -> #REF! | R14: =IF($O14="","",IF(MOD(O14,LEFT($R$8))=0,IFERROR(INDEX(INDIRECT(R$7&VLOOKUP(Summary,Ref!$Y$13:$AC$18,3,FALSE)),MATCH($P14,INDIRECT(R$7&VLOOKUP(Summary,Ref!$Y$13:$AC$18,4,FALSE)),0),MATCH(R$8,INDIRECT(R$7&VLOOKUP(Summary,Ref!$Y$13:$AC$18,5,FALSE)),0)),0),0)) -> 0 | S14: =IF($O14="","",VLOOKUP($P14,INDIRECT(PTab&"!$B:$EH"),S$5,FALSE)) -> #REF! | T14: {=IF($O14="","",VLOOKUP($P14,INDIRECT(PTab&"!$B:$EH"),T$5,FALSE)+IF(AND(PTab="P7",$O14=5),INDEX(INDIRECT(PTab&"!$B$11:$EH$563"),MATCH(6&"|"&1,INDIRECT(PTab&"!$D$11:$D$563")&"|"&INDIRECT(PTab&"!$C$11:$C$563"),0),MATCH("Overlay Credit",INDIRECT(PTab&"!$B$10:$EH$10"),0)),IF(AND(PTab="P2",Ref!$S$53="Y"),AA14,0)))} -> #REF! | U14: =IF($O14="","",VLOOKUP($P14,INDIRECT(PTab&"!$B:$EH"),U$5,FALSE)) -> #REF! | V14: =IF($O14="","",VLOOKUP($P14,INDIRECT(PTab&"!$B:$EH"),V$5,FALSE)) -> #REF! | W14: =IF($O14="","",VLOOKUP($P14,INDIRECT(PTab&"!$B:$EH"),W$5,FALSE)) -> #REF! | X14: =IF(OR($O14="",RIGHT(Category,2)="NY"),"",VLOOKUP($P14,INDIRECT(PTab&"!$B:$EH"),X$5,FALSE)) -> #REF! | Y14: =IF($O14="","",VLOOKUP($P14,INDIRECT(PTab&"!$B:$EH"),Y$5,FALSE)) -> #REF! | Z14: =IF($O14="","",SUM(AR14:AU14)) -> 0 | AA14: =IF(OR($O14="",RIGHT(Category,2)="NY"),"",VLOOKUP($P14,INDIRECT(PTab&"!$B:$EH"),AA$5,FALSE)) -> #REF! | AC14: =IF($O14="","",IF(EICRInd="Not Available","Not Available",IF(OR($O14<2,$Q14<WDAge),"Eligibility Criteria Not Met",VLOOKUP(COUNTIFS($AD$11:$AD13,"Yes"),Ref!$AL$58:$AM$63,2)))) -> Not Available | AE14: =IF($O14="","",IFERROR(VLOOKUP(EOMONTH($P14,11),INDIRECT(PTab&"!$B:$EH"),AE$5,FALSE),0)) -> 0 | AG14: =IF($O14="","",IFERROR(-VLOOKUP(EOMONTH($P14,11),INDIRECT(PTab&"!$B:$EH"),AG$5,FALSE)-IF(OR(RMDInd="Yes",SWInd="Yes"),VLOOKUP(EOMONTH($P14,11),INDIRECT(PTab&"!$B:$EH"),AB$5,FALSE)+AB14*(AB14<>""),0),0)) -> 0 | AH14: =IF($O14="","",IF(RIGHT(Category,2)="NY",IFERROR(-VLOOKUP($P14,INDIRECT(PTab&"!$B:$EH"),AH$5,FALSE),0),IFERROR(VLOOKUP($P14,INDIRECT(PTab&"!$B:$EH"),AH$5,FALSE),0))) -> 0 | AI14: =IF($O14="","",IF($O14=0,IF(RIGHT(Category,2)="NY",AH14,SUM(AB14,AG14)),IF(RIGHT(Category,2)="NY",SUM(AH14,AI13),SUM(AB14,AE14*(AD14="Yes"),AG14,AI13)))) -> 0 | AJ14: =IF($O14="","",VLOOKUP($P14,INDIRECT(PTab&"!$B:$EH"),AJ$5,FALSE)) -> #REF! | AL14: =IF($O14="","",IF(OR(PTab="P3",PTab="P7"),VLOOKUP($P14,INDIRECT(PTab&"!$B:$BA"),AL$5,FALSE),VLOOKUP(EOMONTH($P14,11),INDIRECT(PTab&"!$B:$BA"),AL$5,FALSE))) -> #REF! | AM14: =IF($O14="","",IF(OR(PTab="P7",Ref!$S$53="Y"),VLOOKUP($P14,INDIRECT(PTab&"!$B:$EH"),AM$5,FALSE),"")) -> #REF! | AN14: =IF($O14="","",IF(PTab="P7",VLOOKUP($P14,INDIRECT(PTab&"!$B:$EH"),AN$5,FALSE),"")) | AO14: =IF($O14="","",IF(PTab="P7",VLOOKUP($P14,INDIRECT(PTab&"!$B:$EH"),AO$5,FALSE),"")) | AP14: =IF($O14="","",IF(PTab="P7",VLOOKUP($P14,INDIRECT(PTab&"!$B:$EH"),AP$5,FALSE),"")) | AQ14: =IF($O14="","", IF(PTab="P7",IF($P14=$P$11,0,MAX(AP14-(VLOOKUP($P14,INDIRECT(PTab&"!$B:$EH"),AQ$5,FALSE)-AU14),0)),"")) | AR14: =IF($O14="","",IFERROR(-VLOOKUP($P14,INDIRECT(PTab&"!$B:$EH"),AR$5,FALSE),0)) -> 0 | AS14: =IF($O14="","",IFERROR(-VLOOKUP($P14,INDIRECT(PTab&"!$B:$EH"),AS$5,FALSE),0)) -> 0 | AT14: =IF($O14="","",IFERROR(-VLOOKUP($P14,INDIRECT(PTab&"!$B:$EH"),AT$5,FALSE),0)) -> 0 | AU14: =IF($O14="","",IFERROR(-VLOOKUP($P14,INDIRECT(PTab&"!$B:$EH"),AU$5,FALSE),0)) -> 0
B15: CDSC Period | C15: 5 | O15: =IFERROR(IF(AND(OR(Summary="Favorable",Summary="Unfavorable",Summary="Most Recent"),OR(($O14+1)>10,$O14="")),"",IF(OR(($O14+1)>Projection,$O14=""),"",$O14+1)),"") -> 4 | P15: {=IF($O15="","",OFFSET(INDIRECT(PTab&"!"&CELL("address",$B$11)),12*$O15,0))} -> #REF! | Q15: =IF($O15="","",VLOOKUP($P15,INDIRECT(PTab&"!$B:$EH"),Q$5,FALSE)) -> #REF! | R15: =IF($O15="","",IF(MOD(O15,LEFT($R$8))=0,IFERROR(INDEX(INDIRECT(R$7&VLOOKUP(Summary,Ref!$Y$13:$AC$18,3,FALSE)),MATCH($P15,INDIRECT(R$7&VLOOKUP(Summary,Ref!$Y$13:$AC$18,4,FALSE)),0),MATCH(R$8,INDIRECT(R$7&VLOOKUP(Summary,Ref!$Y$13:$AC$18,5,FALSE)),0)),0),0)) -> 0 | S15: =IF($O15="","",VLOOKUP($P15,INDIRECT(PTab&"!$B:$EH"),S$5,FALSE)) -> #REF! | T15: {=IF($O15="","",VLOOKUP($P15,INDIRECT(PTab&"!$B:$EH"),T$5,FALSE)+IF(AND(PTab="P7",$O15=5),INDEX(INDIRECT(PTab&"!$B$11:$EH$563"),MATCH(6&"|"&1,INDIRECT(PTab&"!$D$11:$D$563")&"|"&INDIRECT(PTab&"!$C$11:$C$563"),0),MATCH("Overlay Credit",INDIRECT(PTab&"!$B$10:$EH$10"),0)),IF(AND(PTab="P2",Ref!$S$53="Y"),AA15,0)))} -> #REF! | U15: =IF($O15="","",VLOOKUP($P15,INDIRECT(PTab&"!$B:$EH"),U$5,FALSE)) -> #REF! | V15: =IF($O15="","",VLOOKUP($P15,INDIRECT(PTab&"!$B:$EH"),V$5,FALSE)) -> #REF! | W15: =IF($O15="","",VLOOKUP($P15,INDIRECT(PTab&"!$B:$EH"),W$5,FALSE)) -> #REF! | X15: =IF(OR($O15="",RIGHT(Category,2)="NY"),"",VLOOKUP($P15,INDIRECT(PTab&"!$B:$EH"),X$5,FALSE)) -> #REF! | Y15: =IF($O15="","",VLOOKUP($P15,INDIRECT(PTab&"!$B:$EH"),Y$5,FALSE)) -> #REF! | Z15: =IF($O15="","",SUM(AR15:AU15)) -> 0 | AA15: =IF(OR($O15="",RIGHT(Category,2)="NY"),"",VLOOKUP($P15,INDIRECT(PTab&"!$B:$EH"),AA$5,FALSE)) -> #REF! | AC15: =IF($O15="","",IF(EICRInd="Not Available","Not Available",IF(OR($O15<2,$Q15<WDAge),"Eligibility Criteria Not Met",VLOOKUP(COUNTIFS($AD$11:$AD14,"Yes"),Ref!$AL$58:$AM$63,2)))) -> Not Available | AE15: =IF($O15="","",IFERROR(VLOOKUP(EOMONTH($P15,11),INDIRECT(PTab&"!$B:$EH"),AE$5,FALSE),0)) -> 0 | AG15: =IF($O15="","",IFERROR(-VLOOKUP(EOMONTH($P15,11),INDIRECT(PTab&"!$B:$EH"),AG$5,FALSE)-IF(OR(RMDInd="Yes",SWInd="Yes"),VLOOKUP(EOMONTH($P15,11),INDIRECT(PTab&"!$B:$EH"),AB$5,FALSE)+AB15*(AB15<>""),0),0)) -> 0 | AH15: =IF($O15="","",IF(RIGHT(Category,2)="NY",IFERROR(-VLOOKUP($P15,INDIRECT(PTab&"!$B:$EH"),AH$5,FALSE),0),IFERROR(VLOOKUP($P15,INDIRECT(PTab&"!$B:$EH"),AH$5,FALSE),0))) -> 0 | AI15: =IF($O15="","",IF($O15=0,IF(RIGHT(Category,2)="NY",AH15,SUM(AB15,AG15)),IF(RIGHT(Category,2)="NY",SUM(AH15,AI14),SUM(AB15,AE15*(AD15="Yes"),AG15,AI14)))) -> 0 | AJ15: =IF($O15="","",VLOOKUP($P15,INDIRECT(PTab&"!$B:$EH"),AJ$5,FALSE)) -> #REF! | AL15: =IF($O15="","",IF(OR(PTab="P3",PTab="P7"),VLOOKUP($P15,INDIRECT(PTab&"!$B:$BA"),AL$5,FALSE),VLOOKUP(EOMONTH($P15,11),INDIRECT(PTab&"!$B:$BA"),AL$5,FALSE))) -> #REF! | AM15: =IF($O15="","",IF(OR(PTab="P7",Ref!$S$53="Y"),VLOOKUP($P15,INDIRECT(PTab&"!$B:$EH"),AM$5,FALSE),"")) -> #REF! | AN15: =IF($O15="","",IF(PTab="P7",VLOOKUP($P15,INDIRECT(PTab&"!$B:$EH"),AN$5,FALSE),"")) | AO15: =IF($O15="","",IF(PTab="P7",VLOOKUP($P15,INDIRECT(PTab&"!$B:$EH"),AO$5,FALSE),"")) | AP15: =IF($O15="","",IF(PTab="P7",VLOOKUP($P15,INDIRECT(PTab&"!$B:$EH"),AP$5,FALSE),"")) | AQ15: =IF($O15="","", IF(PTab="P7",IF($P15=$P$11,0,MAX(AP15-(VLOOKUP($P15,INDIRECT(PTab&"!$B:$EH"),AQ$5,FALSE)-AU15),0)),"")) | AR15: =IF($O15="","",IFERROR(-VLOOKUP($P15,INDIRECT(PTab&"!$B:$EH"),AR$5,FALSE),0)) -> 0 | AS15: =IF($O15="","",IFERROR(-VLOOKUP($P15,INDIRECT(PTab&"!$B:$EH"),AS$5,FALSE),0)) -> 0 | AT15: =IF($O15="","",IFERROR(-VLOOKUP($P15,INDIRECT(PTab&"!$B:$EH"),AT$5,FALSE),0)) -> 0 | AU15: =IF($O15="","",IFERROR(-VLOOKUP($P15,INDIRECT(PTab&"!$B:$EH"),AU$5,FALSE),0)) -> 0
C16: =COUNTIFS(Ref!$C$56:$C$70,">0") -> 7 | O16: =IFERROR(IF(AND(OR(Summary="Favorable",Summary="Unfavorable",Summary="Most Recent"),OR(($O15+1)>10,$O15="")),"",IF(OR(($O15+1)>Projection,$O15=""),"",$O15+1)),"") -> 5 | P16: {=IF($O16="","",OFFSET(INDIRECT(PTab&"!"&CELL("address",$B$11)),12*$O16,0))} -> #REF! | Q16: =IF($O16="","",VLOOKUP($P16,INDIRECT(PTab&"!$B:$EH"),Q$5,FALSE)) -> #REF! | R16: =IF($O16="","",IF(MOD(O16,LEFT($R$8))=0,IFERROR(INDEX(INDIRECT(R$7&VLOOKUP(Summary,Ref!$Y$13:$AC$18,3,FALSE)),MATCH($P16,INDIRECT(R$7&VLOOKUP(Summary,Ref!$Y$13:$AC$18,4,FALSE)),0),MATCH(R$8,INDIRECT(R$7&VLOOKUP(Summary,Ref!$Y$13:$AC$18,5,FALSE)),0)),0),0)) -> 0 | S16: =IF($O16="","",VLOOKUP($P16,INDIRECT(PTab&"!$B:$EH"),S$5,FALSE)) -> #REF! | T16: {=IF($O16="","",VLOOKUP($P16,INDIRECT(PTab&"!$B:$EH"),T$5,FALSE)+IF(AND(PTab="P7",$O16=5),INDEX(INDIRECT(PTab&"!$B$11:$EH$563"),MATCH(6&"|"&1,INDIRECT(PTab&"!$D$11:$D$563")&"|"&INDIRECT(PTab&"!$C$11:$C$563"),0),MATCH("Overlay Credit",INDIRECT(PTab&"!$B$10:$EH$10"),0)),IF(AND(PTab="P2",Ref!$S$53="Y"),AA16,0)))} -> #REF! | U16: =IF($O16="","",VLOOKUP($P16,INDIRECT(PTab&"!$B:$EH"),U$5,FALSE)) -> #REF! | V16: =IF($O16="","",VLOOKUP($P16,INDIRECT(PTab&"!$B:$EH"),V$5,FALSE)) -> #REF! | W16: =IF($O16="","",VLOOKUP($P16,INDIRECT(PTab&"!$B:$EH"),W$5,FALSE)) -> #REF! | X16: =IF(OR($O16="",RIGHT(Category,2)="NY"),"",VLOOKUP($P16,INDIRECT(PTab&"!$B:$EH"),X$5,FALSE)) -> #REF! | Y16: =IF($O16="","",VLOOKUP($P16,INDIRECT(PTab&"!$B:$EH"),Y$5,FALSE)) -> #REF! | Z16: =IF($O16="","",SUM(AR16:AU16)) -> 0 | AA16: =IF(OR($O16="",RIGHT(Category,2)="NY"),"",VLOOKUP($P16,INDIRECT(PTab&"!$B:$EH"),AA$5,FALSE)) -> #REF! | AC16: =IF($O16="","",IF(EICRInd="Not Available","Not Available",IF(OR($O16<2,$Q16<WDAge),"Eligibility Criteria Not Met",VLOOKUP(COUNTIFS($AD$11:$AD15,"Yes"),Ref!$AL$58:$AM$63,2)))) -> Not Available | AE16: =IF($O16="","",IFERROR(VLOOKUP(EOMONTH($P16,11),INDIRECT(PTab&"!$B:$EH"),AE$5,FALSE),0)) -> 0 | AG16: =IF($O16="","",IFERROR(-VLOOKUP(EOMONTH($P16,11),INDIRECT(PTab&"!$B:$EH"),AG$5,FALSE)-IF(OR(RMDInd="Yes",SWInd="Yes"),VLOOKUP(EOMONTH($P16,11),INDIRECT(PTab&"!$B:$EH"),AB$5,FALSE)+AB16*(AB16<>""),0),0)) -> 0 | AH16: =IF($O16="","",IF(RIGHT(Category,2)="NY",IFERROR(-VLOOKUP($P16,INDIRECT(PTab&"!$B:$EH"),AH$5,FALSE),0),IFERROR(VLOOKUP($P16,INDIRECT(PTab&"!$B:$EH"),AH$5,FALSE),0))) -> 0 | AI16: =IF($O16="","",IF($O16=0,IF(RIGHT(Category,2)="NY",AH16,SUM(AB16,AG16)),IF(RIGHT(Category,2)="NY",SUM(AH16,AI15),SUM(AB16,AE16*(AD16="Yes"),AG16,AI15)))) -> 0 | AJ16: =IF($O16="","",VLOOKUP($P16,INDIRECT(PTab&"!$B:$EH"),AJ$5,FALSE)) -> #REF! | AL16: =IF($O16="","",IF(OR(PTab="P3",PTab="P7"),VLOOKUP($P16,INDIRECT(PTab&"!$B:$BA"),AL$5,FALSE),VLOOKUP(EOMONTH($P16,11),INDIRECT(PTab&"!$B:$BA"),AL$5,FALSE))) -> #REF! | AM16: =IF($O16="","",IF(OR(PTab="P7",Ref!$S$53="Y"),VLOOKUP($P16,INDIRECT(PTab&"!$B:$EH"),AM$5,FALSE),"")) -> #REF! | AN16: =IF($O16="","",IF(PTab="P7",VLOOKUP($P16,INDIRECT(PTab&"!$B:$EH"),AN$5,FALSE),"")) | AO16: =IF($O16="","",IF(PTab="P7",VLOOKUP($P16,INDIRECT(PTab&"!$B:$EH"),AO$5,FALSE),"")) | AP16: =IF($O16="","",IF(PTab="P7",VLOOKUP($P16,INDIRECT(PTab&"!$B:$EH"),AP$5,FALSE),"")) | AQ16: =IF($O16="","", IF(PTab="P7",IF($P16=$P$11,0,MAX(AP16-(VLOOKUP($P16,INDIRECT(PTab&"!$B:$EH"),AQ$5,FALSE)-AU16),0)),"")) | AR16: =IF($O16="","",IFERROR(-VLOOKUP($P16,INDIRECT(PTab&"!$B:$EH"),AR$5,FALSE),0)) -> 0 | AS16: =IF($O16="","",IFERROR(-VLOOKUP($P16,INDIRECT(PTab&"!$B:$EH"),AS$5,FALSE),0)) -> 0 | AT16: =IF($O16="","",IFERROR(-VLOOKUP($P16,INDIRECT(PTab&"!$B:$EH"),AT$5,FALSE),0)) -> 0 | AU16: =IF($O16="","",IFERROR(-VLOOKUP($P16,INDIRECT(PTab&"!$B:$EH"),AU$5,FALSE),0)) -> 0
B17: Living Benefit | C17: None | O17: =IFERROR(IF(AND(OR(Summary="Favorable",Summary="Unfavorable",Summary="Most Recent"),OR(($O16+1)>10,$O16="")),"",IF(OR(($O16+1)>Projection,$O16=""),"",$O16+1)),"") -> 6 | P17: {=IF($O17="","",OFFSET(INDIRECT(PTab&"!"&CELL("address",$B$11)),12*$O17,0))} -> #REF! | Q17: =IF($O17="","",VLOOKUP($P17,INDIRECT(PTab&"!$B:$EH"),Q$5,FALSE)) -> #REF! | R17: =IF($O17="","",IF(MOD(O17,LEFT($R$8))=0,IFERROR(INDEX(INDIRECT(R$7&VLOOKUP(Summary,Ref!$Y$13:$AC$18,3,FALSE)),MATCH($P17,INDIRECT(R$7&VLOOKUP(Summary,Ref!$Y$13:$AC$18,4,FALSE)),0),MATCH(R$8,INDIRECT(R$7&VLOOKUP(Summary,Ref!$Y$13:$AC$18,5,FALSE)),0)),0),0)) -> 0 | S17: =IF($O17="","",VLOOKUP($P17,INDIRECT(PTab&"!$B:$EH"),S$5,FALSE)) -> #REF! | T17: {=IF($O17="","",VLOOKUP($P17,INDIRECT(PTab&"!$B:$EH"),T$5,FALSE)+IF(AND(PTab="P7",$O17=5),INDEX(INDIRECT(PTab&"!$B$11:$EH$563"),MATCH(6&"|"&1,INDIRECT(PTab&"!$D$11:$D$563")&"|"&INDIRECT(PTab&"!$C$11:$C$563"),0),MATCH("Overlay Credit",INDIRECT(PTab&"!$B$10:$EH$10"),0)),IF(AND(PTab="P2",Ref!$S$53="Y"),AA17,0)))} -> #REF! | U17: =IF($O17="","",VLOOKUP($P17,INDIRECT(PTab&"!$B:$EH"),U$5,FALSE)) -> #REF! | V17: =IF($O17="","",VLOOKUP($P17,INDIRECT(PTab&"!$B:$EH"),V$5,FALSE)) -> #REF! | W17: =IF($O17="","",VLOOKUP($P17,INDIRECT(PTab&"!$B:$EH"),W$5,FALSE)) -> #REF! | X17: =IF(OR($O17="",RIGHT(Category,2)="NY"),"",VLOOKUP($P17,INDIRECT(PTab&"!$B:$EH"),X$5,FALSE)) -> #REF! | Y17: =IF($O17="","",VLOOKUP($P17,INDIRECT(PTab&"!$B:$EH"),Y$5,FALSE)) -> #REF! | Z17: =IF($O17="","",SUM(AR17:AU17)) -> 0 | AA17: =IF(OR($O17="",RIGHT(Category,2)="NY"),"",VLOOKUP($P17,INDIRECT(PTab&"!$B:$EH"),AA$5,FALSE)) -> #REF! | AC17: =IF($O17="","",IF(EICRInd="Not Available","Not Available",IF(OR($O17<2,$Q17<WDAge),"Eligibility Criteria Not Met",VLOOKUP(COUNTIFS($AD$11:$AD16,"Yes"),Ref!$AL$58:$AM$63,2)))) -> Not Available | AE17: =IF($O17="","",IFERROR(VLOOKUP(EOMONTH($P17,11),INDIRECT(PTab&"!$B:$EH"),AE$5,FALSE),0)) -> 0 | AG17: =IF($O17="","",IFERROR(-VLOOKUP(EOMONTH($P17,11),INDIRECT(PTab&"!$B:$EH"),AG$5,FALSE)-IF(OR(RMDInd="Yes",SWInd="Yes"),VLOOKUP(EOMONTH($P17,11),INDIRECT(PTab&"!$B:$EH"),AB$5,FALSE)+AB17*(AB17<>""),0),0)) -> 0 | AH17: =IF($O17="","",IF(RIGHT(Category,2)="NY",IFERROR(-VLOOKUP($P17,INDIRECT(PTab&"!$B:$EH"),AH$5,FALSE),0),IFERROR(VLOOKUP($P17,INDIRECT(PTab&"!$B:$EH"),AH$5,FALSE),0))) -> 0 | AI17: =IF($O17="","",IF($O17=0,IF(RIGHT(Category,2)="NY",AH17,SUM(AB17,AG17)),IF(RIGHT(Category,2)="NY",SUM(AH17,AI16),SUM(AB17,AE17*(AD17="Yes"),AG17,AI16)))) -> 0 | AJ17: =IF($O17="","",VLOOKUP($P17,INDIRECT(PTab&"!$B:$EH"),AJ$5,FALSE)) -> #REF! | AL17: =IF($O17="","",IF(OR(PTab="P3",PTab="P7"),VLOOKUP($P17,INDIRECT(PTab&"!$B:$BA"),AL$5,FALSE),VLOOKUP(EOMONTH($P17,11),INDIRECT(PTab&"!$B:$BA"),AL$5,FALSE))) -> #REF! | AM17: =IF($O17="","",IF(OR(PTab="P7",Ref!$S$53="Y"),VLOOKUP($P17,INDIRECT(PTab&"!$B:$EH"),AM$5,FALSE),"")) -> #REF! | AN17: =IF($O17="","",IF(PTab="P7",VLOOKUP($P17,INDIRECT(PTab&"!$B:$EH"),AN$5,FALSE),"")) | AO17: =IF($O17="","",IF(PTab="P7",VLOOKUP($P17,INDIRECT(PTab&"!$B:$EH"),AO$5,FALSE),"")) | AP17: =IF($O17="","",IF(PTab="P7",VLOOKUP($P17,INDIRECT(PTab&"!$B:$EH"),AP$5,FALSE),"")) | AQ17: =IF($O17="","", IF(PTab="P7",IF($P17=$P$11,0,MAX(AP17-(VLOOKUP($P17,INDIRECT(PTab&"!$B:$EH"),AQ$5,FALSE)-AU17),0)),"")) | AR17: =IF($O17="","",IFERROR(-VLOOKUP($P17,INDIRECT(PTab&"!$B:$EH"),AR$5,FALSE),0)) -> 0 | AS17: =IF($O17="","",IFERROR(-VLOOKUP($P17,INDIRECT(PTab&"!$B:$EH"),AS$5,FALSE),0)) -> 0 | AT17: =IF($O17="","",IFERROR(-VLOOKUP($P17,INDIRECT(PTab&"!$B:$EH"),AT$5,FALSE),0)) -> 0 | AU17: =IF($O17="","",IFERROR(-VLOOKUP($P17,INDIRECT(PTab&"!$B:$EH"),AU$5,FALSE),0)) -> 0
B18: Summary | C18: Specific | O18: =IFERROR(IF(AND(OR(Summary="Favorable",Summary="Unfavorable",Summary="Most Recent"),OR(($O17+1)>10,$O17="")),"",IF(OR(($O17+1)>Projection,$O17=""),"",$O17+1)),"") -> 7 | P18: {=IF($O18="","",OFFSET(INDIRECT(PTab&"!"&CELL("address",$B$11)),12*$O18,0))} -> #REF! | Q18: =IF($O18="","",VLOOKUP($P18,INDIRECT(PTab&"!$B:$EH"),Q$5,FALSE)) -> #REF! | R18: =IF($O18="","",IF(MOD(O18,LEFT($R$8))=0,IFERROR(INDEX(INDIRECT(R$7&VLOOKUP(Summary,Ref!$Y$13:$AC$18,3,FALSE)),MATCH($P18,INDIRECT(R$7&VLOOKUP(Summary,Ref!$Y$13:$AC$18,4,FALSE)),0),MATCH(R$8,INDIRECT(R$7&VLOOKUP(Summary,Ref!$Y$13:$AC$18,5,FALSE)),0)),0),0)) -> 0 | S18: =IF($O18="","",VLOOKUP($P18,INDIRECT(PTab&"!$B:$EH"),S$5,FALSE)) -> #REF! | T18: {=IF($O18="","",VLOOKUP($P18,INDIRECT(PTab&"!$B:$EH"),T$5,FALSE)+IF(AND(PTab="P7",$O18=5),INDEX(INDIRECT(PTab&"!$B$11:$EH$563"),MATCH(6&"|"&1,INDIRECT(PTab&"!$D$11:$D$563")&"|"&INDIRECT(PTab&"!$C$11:$C$563"),0),MATCH("Overlay Credit",INDIRECT(PTab&"!$B$10:$EH$10"),0)),IF(AND(PTab="P2",Ref!$S$53="Y"),AA18,0)))} -> #REF! | U18: =IF($O18="","",VLOOKUP($P18,INDIRECT(PTab&"!$B:$EH"),U$5,FALSE)) -> #REF! | V18: =IF($O18="","",VLOOKUP($P18,INDIRECT(PTab&"!$B:$EH"),V$5,FALSE)) -> #REF! | W18: =IF($O18="","",VLOOKUP($P18,INDIRECT(PTab&"!$B:$EH"),W$5,FALSE)) -> #REF! | X18: =IF(OR($O18="",RIGHT(Category,2)="NY"),"",VLOOKUP($P18,INDIRECT(PTab&"!$B:$EH"),X$5,FALSE)) -> #REF! | Y18: =IF($O18="","",VLOOKUP($P18,INDIRECT(PTab&"!$B:$EH"),Y$5,FALSE)) -> #REF! | Z18: =IF($O18="","",SUM(AR18:AU18)) -> 0 | AA18: =IF(OR($O18="",RIGHT(Category,2)="NY"),"",VLOOKUP($P18,INDIRECT(PTab&"!$B:$EH"),AA$5,FALSE)) -> #REF! | AC18: =IF($O18="","",IF(EICRInd="Not Available","Not Available",IF(OR($O18<2,$Q18<WDAge),"Eligibility Criteria Not Met",VLOOKUP(COUNTIFS($AD$11:$AD17,"Yes"),Ref!$AL$58:$AM$63,2)))) -> Not Available | AE18: =IF($O18="","",IFERROR(VLOOKUP(EOMONTH($P18,11),INDIRECT(PTab&"!$B:$EH"),AE$5,FALSE),0)) -> 0 | AG18: =IF($O18="","",IFERROR(-VLOOKUP(EOMONTH($P18,11),INDIRECT(PTab&"!$B:$EH"),AG$5,FALSE)-IF(OR(RMDInd="Yes",SWInd="Yes"),VLOOKUP(EOMONTH($P18,11),INDIRECT(PTab&"!$B:$EH"),AB$5,FALSE)+AB18*(AB18<>""),0),0)) -> 0 | AH18: =IF($O18="","",IF(RIGHT(Category,2)="NY",IFERROR(-VLOOKUP($P18,INDIRECT(PTab&"!$B:$EH"),AH$5,FALSE),0),IFERROR(VLOOKUP($P18,INDIRECT(PTab&"!$B:$EH"),AH$5,FALSE),0))) -> 0 | AI18: =IF($O18="","",IF($O18=0,IF(RIGHT(Category,2)="NY",AH18,SUM(AB18,AG18)),IF(RIGHT(Category,2)="NY",SUM(AH18,AI17),SUM(AB18,AE18*(AD18="Yes"),AG18,AI17)))) -> 0 | AJ18: =IF($O18="","",VLOOKUP($P18,INDIRECT(PTab&"!$B:$EH"),AJ$5,FALSE)) -> #REF! | AL18: =IF($O18="","",IF(OR(PTab="P3",PTab="P7"),VLOOKUP($P18,INDIRECT(PTab&"!$B:$BA"),AL$5,FALSE),VLOOKUP(EOMONTH($P18,11),INDIRECT(PTab&"!$B:$BA"),AL$5,FALSE))) -> #REF! | AM18: =IF($O18="","",IF(OR(PTab="P7",Ref!$S$53="Y"),VLOOKUP($P18,INDIRECT(PTab&"!$B:$EH"),AM$5,FALSE),"")) -> #REF! | AN18: =IF($O18="","",IF(PTab="P7",VLOOKUP($P18,INDIRECT(PTab&"!$B:$EH"),AN$5,FALSE),"")) | AO18: =IF($O18="","",IF(PTab="P7",VLOOKUP($P18,INDIRECT(PTab&"!$B:$EH"),AO$5,FALSE),"")) | AP18: =IF($O18="","",IF(PTab="P7",VLOOKUP($P18,INDIRECT(PTab&"!$B:$EH"),AP$5,FALSE),"")) | AQ18: =IF($O18="","", IF(PTab="P7",IF($P18=$P$11,0,MAX(AP18-(VLOOKUP($P18,INDIRECT(PTab&"!$B:$EH"),AQ$5,FALSE)-AU18),0)),"")) | AR18: =IF($O18="","",IFERROR(-VLOOKUP($P18,INDIRECT(PTab&"!$B:$EH"),AR$5,FALSE),0)) -> 0 | AS18: =IF($O18="","",IFERROR(-VLOOKUP($P18,INDIRECT(PTab&"!$B:$EH"),AS$5,FALSE),0)) -> 0 | AT18: =IF($O18="","",IFERROR(-VLOOKUP($P18,INDIRECT(PTab&"!$B:$EH"),AT$5,FALSE),0)) -> 0 | AU18: =IF($O18="","",IFERROR(-VLOOKUP($P18,INDIRECT(PTab&"!$B:$EH"),AU$5,FALSE),0)) -> 0
B19: Summary Subcategory* | C19: Standard | O19: =IFERROR(IF(AND(OR(Summary="Favorable",Summary="Unfavorable",Summary="Most Recent"),OR(($O18+1)>10,$O18="")),"",IF(OR(($O18+1)>Projection,$O18=""),"",$O18+1)),"") -> 8 | P19: {=IF($O19="","",OFFSET(INDIRECT(PTab&"!"&CELL("address",$B$11)),12*$O19,0))} -> #REF! | Q19: =IF($O19="","",VLOOKUP($P19,INDIRECT(PTab&"!$B:$EH"),Q$5,FALSE)) -> #REF! | R19: =IF($O19="","",IF(MOD(O19,LEFT($R$8))=0,IFERROR(INDEX(INDIRECT(R$7&VLOOKUP(Summary,Ref!$Y$13:$AC$18,3,FALSE)),MATCH($P19,INDIRECT(R$7&VLOOKUP(Summary,Ref!$Y$13:$AC$18,4,FALSE)),0),MATCH(R$8,INDIRECT(R$7&VLOOKUP(Summary,Ref!$Y$13:$AC$18,5,FALSE)),0)),0),0)) -> 0 | S19: =IF($O19="","",VLOOKUP($P19,INDIRECT(PTab&"!$B:$EH"),S$5,FALSE)) -> #REF! | T19: {=IF($O19="","",VLOOKUP($P19,INDIRECT(PTab&"!$B:$EH"),T$5,FALSE)+IF(AND(PTab="P7",$O19=5),INDEX(INDIRECT(PTab&"!$B$11:$EH$563"),MATCH(6&"|"&1,INDIRECT(PTab&"!$D$11:$D$563")&"|"&INDIRECT(PTab&"!$C$11:$C$563"),0),MATCH("Overlay Credit",INDIRECT(PTab&"!$B$10:$EH$10"),0)),IF(AND(PTab="P2",Ref!$S$53="Y"),AA19,0)))} -> #REF! | U19: =IF($O19="","",VLOOKUP($P19,INDIRECT(PTab&"!$B:$EH"),U$5,FALSE)) -> #REF! | V19: =IF($O19="","",VLOOKUP($P19,INDIRECT(PTab&"!$B:$EH"),V$5,FALSE)) -> #REF! | W19: =IF($O19="","",VLOOKUP($P19,INDIRECT(PTab&"!$B:$EH"),W$5,FALSE)) -> #REF! | X19: =IF(OR($O19="",RIGHT(Category,2)="NY"),"",VLOOKUP($P19,INDIRECT(PTab&"!$B:$EH"),X$5,FALSE)) -> #REF! | Y19: =IF($O19="","",VLOOKUP($P19,INDIRECT(PTab&"!$B:$EH"),Y$5,FALSE)) -> #REF! | Z19: =IF($O19="","",SUM(AR19:AU19)) -> 0 | AA19: =IF(OR($O19="",RIGHT(Category,2)="NY"),"",VLOOKUP($P19,INDIRECT(PTab&"!$B:$EH"),AA$5,FALSE)) -> #REF! | AC19: =IF($O19="","",IF(EICRInd="Not Available","Not Available",IF(OR($O19<2,$Q19<WDAge),"Eligibility Criteria Not Met",VLOOKUP(COUNTIFS($AD$11:$AD18,"Yes"),Ref!$AL$58:$AM$63,2)))) -> Not Available | AE19: =IF($O19="","",IFERROR(VLOOKUP(EOMONTH($P19,11),INDIRECT(PTab&"!$B:$EH"),AE$5,FALSE),0)) -> 0 | AG19: =IF($O19="","",IFERROR(-VLOOKUP(EOMONTH($P19,11),INDIRECT(PTab&"!$B:$EH"),AG$5,FALSE)-IF(OR(RMDInd="Yes",SWInd="Yes"),VLOOKUP(EOMONTH($P19,11),INDIRECT(PTab&"!$B:$EH"),AB$5,FALSE)+AB19*(AB19<>""),0),0)) -> 0 | AH19: =IF($O19="","",IF(RIGHT(Category,2)="NY",IFERROR(-VLOOKUP($P19,INDIRECT(PTab&"!$B:$EH"),AH$5,FALSE),0),IFERROR(VLOOKUP($P19,INDIRECT(PTab&"!$B:$EH"),AH$5,FALSE),0))) -> 0 | AI19: =IF($O19="","",IF($O19=0,IF(RIGHT(Category,2)="NY",AH19,SUM(AB19,AG19)),IF(RIGHT(Category,2)="NY",SUM(AH19,AI18),SUM(AB19,AE19*(AD19="Yes"),AG19,AI18)))) -> 0 | AJ19: =IF($O19="","",VLOOKUP($P19,INDIRECT(PTab&"!$B:$EH"),AJ$5,FALSE)) -> #REF! | AL19: =IF($O19="","",IF(OR(PTab="P3",PTab="P7"),VLOOKUP($P19,INDIRECT(PTab&"!$B:$BA"),AL$5,FALSE),VLOOKUP(EOMONTH($P19,11),INDIRECT(PTab&"!$B:$BA"),AL$5,FALSE))) -> #REF! | AM19: =IF($O19="","",IF(OR(PTab="P7",Ref!$S$53="Y"),VLOOKUP($P19,INDIRECT(PTab&"!$B:$EH"),AM$5,FALSE),"")) -> #REF! | AN19: =IF($O19="","",IF(PTab="P7",VLOOKUP($P19,INDIRECT(PTab&"!$B:$EH"),AN$5,FALSE),"")) | AO19: =IF($O19="","",IF(PTab="P7",VLOOKUP($P19,INDIRECT(PTab&"!$B:$EH"),AO$5,FALSE),"")) | AP19: =IF($O19="","",IF(PTab="P7",VLOOKUP($P19,INDIRECT(PTab&"!$B:$EH"),AP$5,FALSE),"")) | AQ19: =IF($O19="","", IF(PTab="P7",IF($P19=$P$11,0,MAX(AP19-(VLOOKUP($P19,INDIRECT(PTab&"!$B:$EH"),AQ$5,FALSE)-AU19),0)),"")) | AR19: =IF($O19="","",IFERROR(-VLOOKUP($P19,INDIRECT(PTab&"!$B:$EH"),AR$5,FALSE),0)) -> 0 | AS19: =IF($O19="","",IFERROR(-VLOOKUP($P19,INDIRECT(PTab&"!$B:$EH"),AS$5,FALSE),0)) -> 0 | AT19: =IF($O19="","",IFERROR(-VLOOKUP($P19,INDIRECT(PTab&"!$B:$EH"),AT$5,FALSE),0)) -> 0 | AU19: =IF($O19="","",IFERROR(-VLOOKUP($P19,INDIRECT(PTab&"!$B:$EH"),AU$5,FALSE),0)) -> 0
B20: Apply Maximum Credited Interest Rate** | C20: No | O20: =IFERROR(IF(AND(OR(Summary="Favorable",Summary="Unfavorable",Summary="Most Recent"),OR(($O19+1)>10,$O19="")),"",IF(OR(($O19+1)>Projection,$O19=""),"",$O19+1)),"") -> 9 | P20: {=IF($O20="","",OFFSET(INDIRECT(PTab&"!"&CELL("address",$B$11)),12*$O20,0))} -> #REF! | Q20: =IF($O20="","",VLOOKUP($P20,INDIRECT(PTab&"!$B:$EH"),Q$5,FALSE)) -> #REF! | R20: =IF($O20="","",IF(MOD(O20,LEFT($R$8))=0,IFERROR(INDEX(INDIRECT(R$7&VLOOKUP(Summary,Ref!$Y$13:$AC$18,3,FALSE)),MATCH($P20,INDIRECT(R$7&VLOOKUP(Summary,Ref!$Y$13:$AC$18,4,FALSE)),0),MATCH(R$8,INDIRECT(R$7&VLOOKUP(Summary,Ref!$Y$13:$AC$18,5,FALSE)),0)),0),0)) -> 0 | S20: =IF($O20="","",VLOOKUP($P20,INDIRECT(PTab&"!$B:$EH"),S$5,FALSE)) -> #REF! | T20: {=IF($O20="","",VLOOKUP($P20,INDIRECT(PTab&"!$B:$EH"),T$5,FALSE)+IF(AND(PTab="P7",$O20=5),INDEX(INDIRECT(PTab&"!$B$11:$EH$563"),MATCH(6&"|"&1,INDIRECT(PTab&"!$D$11:$D$563")&"|"&INDIRECT(PTab&"!$C$11:$C$563"),0),MATCH("Overlay Credit",INDIRECT(PTab&"!$B$10:$EH$10"),0)),IF(AND(PTab="P2",Ref!$S$53="Y"),AA20,0)))} -> #REF! | U20: =IF($O20="","",VLOOKUP($P20,INDIRECT(PTab&"!$B:$EH"),U$5,FALSE)) -> #REF! | V20: =IF($O20="","",VLOOKUP($P20,INDIRECT(PTab&"!$B:$EH"),V$5,FALSE)) -> #REF! | W20: =IF($O20="","",VLOOKUP($P20,INDIRECT(PTab&"!$B:$EH"),W$5,FALSE)) -> #REF! | X20: =IF(OR($O20="",RIGHT(Category,2)="NY"),"",VLOOKUP($P20,INDIRECT(PTab&"!$B:$EH"),X$5,FALSE)) -> #REF! | Y20: =IF($O20="","",VLOOKUP($P20,INDIRECT(PTab&"!$B:$EH"),Y$5,FALSE)) -> #REF! | Z20: =IF($O20="","",SUM(AR20:AU20)) -> 0 | AA20: =IF(OR($O20="",RIGHT(Category,2)="NY"),"",VLOOKUP($P20,INDIRECT(PTab&"!$B:$EH"),AA$5,FALSE)) -> #REF! | AC20: =IF($O20="","",IF(EICRInd="Not Available","Not Available",IF(OR($O20<2,$Q20<WDAge),"Eligibility Criteria Not Met",VLOOKUP(COUNTIFS($AD$11:$AD19,"Yes"),Ref!$AL$58:$AM$63,2)))) -> Not Available | AE20: =IF($O20="","",IFERROR(VLOOKUP(EOMONTH($P20,11),INDIRECT(PTab&"!$B:$EH"),AE$5,FALSE),0)) -> 0 | AG20: =IF($O20="","",IFERROR(-VLOOKUP(EOMONTH($P20,11),INDIRECT(PTab&"!$B:$EH"),AG$5,FALSE)-IF(OR(RMDInd="Yes",SWInd="Yes"),VLOOKUP(EOMONTH($P20,11),INDIRECT(PTab&"!$B:$EH"),AB$5,FALSE)+AB20*(AB20<>""),0),0)) -> 0 | AH20: =IF($O20="","",IF(RIGHT(Category,2)="NY",IFERROR(-VLOOKUP($P20,INDIRECT(PTab&"!$B:$EH"),AH$5,FALSE),0),IFERROR(VLOOKUP($P20,INDIRECT(PTab&"!$B:$EH"),AH$5,FALSE),0))) -> 0 | AI20: =IF($O20="","",IF($O20=0,IF(RIGHT(Category,2)="NY",AH20,SUM(AB20,AG20)),IF(RIGHT(Category,2)="NY",SUM(AH20,AI19),SUM(AB20,AE20*(AD20="Yes"),AG20,AI19)))) -> 0 | AJ20: =IF($O20="","",VLOOKUP($P20,INDIRECT(PTab&"!$B:$EH"),AJ$5,FALSE)) -> #REF! | AL20: =IF($O20="","",IF(OR(PTab="P3",PTab="P7"),VLOOKUP($P20,INDIRECT(PTab&"!$B:$BA"),AL$5,FALSE),VLOOKUP(EOMONTH($P20,11),INDIRECT(PTab&"!$B:$BA"),AL$5,FALSE))) -> #REF! | AM20: =IF($O20="","",IF(OR(PTab="P7",Ref!$S$53="Y"),VLOOKUP($P20,INDIRECT(PTab&"!$B:$EH"),AM$5,FALSE),"")) -> #REF! | AN20: =IF($O20="","",IF(PTab="P7",VLOOKUP($P20,INDIRECT(PTab&"!$B:$EH"),AN$5,FALSE),"")) | AO20: =IF($O20="","",IF(PTab="P7",VLOOKUP($P20,INDIRECT(PTab&"!$B:$EH"),AO$5,FALSE),"")) | AP20: =IF($O20="","",IF(PTab="P7",VLOOKUP($P20,INDIRECT(PTab&"!$B:$EH"),AP$5,FALSE),"")) | AQ20: =IF($O20="","", IF(PTab="P7",IF($P20=$P$11,0,MAX(AP20-(VLOOKUP($P20,INDIRECT(PTab&"!$B:$EH"),AQ$5,FALSE)-AU20),0)),"")) | AR20: =IF($O20="","",IFERROR(-VLOOKUP($P20,INDIRECT(PTab&"!$B:$EH"),AR$5,FALSE),0)) -> 0 | AS20: =IF($O20="","",IFERROR(-VLOOKUP($P20,INDIRECT(PTab&"!$B:$EH"),AS$5,FALSE),0)) -> 0 | AT20: =IF($O20="","",IFERROR(-VLOOKUP($P20,INDIRECT(PTab&"!$B:$EH"),AT$5,FALSE),0)) -> 0 | AU20: =IF($O20="","",IFERROR(-VLOOKUP($P20,INDIRECT(PTab&"!$B:$EH"),AU$5,FALSE),0)) -> 0
B21: Maximum Credited Interest Rate** | C21: =IF(OR(Ref!$R$53="N",MCIRInd="No"),999%,[1]GSPC!$J$33) -> 9.99 | O21: =IFERROR(IF(AND(OR(Summary="Favorable",Summary="Unfavorable",Summary="Most Recent"),OR(($O20+1)>10,$O20="")),"",IF(OR(($O20+1)>Projection,$O20=""),"",$O20+1)),"") -> 10 | P21: {=IF($O21="","",OFFSET(INDIRECT(PTab&"!"&CELL("address",$B$11)),12*$O21,0))} -> #REF! | Q21: =IF($O21="","",VLOOKUP($P21,INDIRECT(PTab&"!$B:$EH"),Q$5,FALSE)) -> #REF! | R21: =IF($O21="","",IF(MOD(O21,LEFT($R$8))=0,IFERROR(INDEX(INDIRECT(R$7&VLOOKUP(Summary,Ref!$Y$13:$AC$18,3,FALSE)),MATCH($P21,INDIRECT(R$7&VLOOKUP(Summary,Ref!$Y$13:$AC$18,4,FALSE)),0),MATCH(R$8,INDIRECT(R$7&VLOOKUP(Summary,Ref!$Y$13:$AC$18,5,FALSE)),0)),0),0)) -> 0 | S21: =IF($O21="","",VLOOKUP($P21,INDIRECT(PTab&"!$B:$EH"),S$5,FALSE)) -> #REF! | T21: {=IF($O21="","",VLOOKUP($P21,INDIRECT(PTab&"!$B:$EH"),T$5,FALSE)+IF(AND(PTab="P7",$O21=5),INDEX(INDIRECT(PTab&"!$B$11:$EH$563"),MATCH(6&"|"&1,INDIRECT(PTab&"!$D$11:$D$563")&"|"&INDIRECT(PTab&"!$C$11:$C$563"),0),MATCH("Overlay Credit",INDIRECT(PTab&"!$B$10:$EH$10"),0)),IF(AND(PTab="P2",Ref!$S$53="Y"),AA21,0)))} -> #REF! | U21: =IF($O21="","",VLOOKUP($P21,INDIRECT(PTab&"!$B:$EH"),U$5,FALSE)) -> #REF! | V21: =IF($O21="","",VLOOKUP($P21,INDIRECT(PTab&"!$B:$EH"),V$5,FALSE)) -> #REF! | W21: =IF($O21="","",VLOOKUP($P21,INDIRECT(PTab&"!$B:$EH"),W$5,FALSE)) -> #REF! | X21: =IF(OR($O21="",RIGHT(Category,2)="NY"),"",VLOOKUP($P21,INDIRECT(PTab&"!$B:$EH"),X$5,FALSE)) -> #REF! | Y21: =IF($O21="","",VLOOKUP($P21,INDIRECT(PTab&"!$B:$EH"),Y$5,FALSE)) -> #REF! | Z21: =IF($O21="","",SUM(AR21:AU21)) -> 0 | AA21: =IF(OR($O21="",RIGHT(Category,2)="NY"),"",VLOOKUP($P21,INDIRECT(PTab&"!$B:$EH"),AA$5,FALSE)) -> #REF! | AC21: =IF($O21="","",IF(EICRInd="Not Available","Not Available",IF(OR($O21<2,$Q21<WDAge),"Eligibility Criteria Not Met",VLOOKUP(COUNTIFS($AD$11:$AD20,"Yes"),Ref!$AL$58:$AM$63,2)))) -> Not Available | AE21: =IF($O21="","",IFERROR(VLOOKUP(EOMONTH($P21,11),INDIRECT(PTab&"!$B:$EH"),AE$5,FALSE),0)) -> 0 | AG21: =IF($O21="","",IFERROR(-VLOOKUP(EOMONTH($P21,11),INDIRECT(PTab&"!$B:$EH"),AG$5,FALSE)-IF(OR(RMDInd="Yes",SWInd="Yes"),VLOOKUP(EOMONTH($P21,11),INDIRECT(PTab&"!$B:$EH"),AB$5,FALSE)+AB21*(AB21<>""),0),0)) -> 0 | AH21: =IF($O21="","",IF(RIGHT(Category,2)="NY",IFERROR(-VLOOKUP($P21,INDIRECT(PTab&"!$B:$EH"),AH$5,FALSE),0),IFERROR(VLOOKUP($P21,INDIRECT(PTab&"!$B:$EH"),AH$5,FALSE),0))) -> 0 | AI21: =IF($O21="","",IF($O21=0,IF(RIGHT(Category,2)="NY",AH21,SUM(AB21,AG21)),IF(RIGHT(Category,2)="NY",SUM(AH21,AI20),SUM(AB21,AE21*(AD21="Yes"),AG21,AI20)))) -> 0 | AJ21: =IF($O21="","",VLOOKUP($P21,INDIRECT(PTab&"!$B:$EH"),AJ$5,FALSE)) -> #REF! | AL21: =IF($O21="","",IF(OR(PTab="P3",PTab="P7"),VLOOKUP($P21,INDIRECT(PTab&"!$B:$BA"),AL$5,FALSE),VLOOKUP(EOMONTH($P21,11),INDIRECT(PTab&"!$B:$BA"),AL$5,FALSE))) -> #REF! | AM21: =IF($O21="","",IF(OR(PTab="P7",Ref!$S$53="Y"),VLOOKUP($P21,INDIRECT(PTab&"!$B:$EH"),AM$5,FALSE),"")) -> #REF! | AN21: =IF($O21="","",IF(PTab="P7",VLOOKUP($P21,INDIRECT(PTab&"!$B:$EH"),AN$5,FALSE),"")) | AO21: =IF($O21="","",IF(PTab="P7",VLOOKUP($P21,INDIRECT(PTab&"!$B:$EH"),AO$5,FALSE),"")) | AP21: =IF($O21="","",IF(PTab="P7",VLOOKUP($P21,INDIRECT(PTab&"!$B:$EH"),AP$5,FALSE),"")) | AQ21: =IF($O21="","", IF(PTab="P7",IF($P21=$P$11,0,MAX(AP21-(VLOOKUP($P21,INDIRECT(PTab&"!$B:$EH"),AQ$5,FALSE)-AU21),0)),"")) | AR21: =IF($O21="","",IFERROR(-VLOOKUP($P21,INDIRECT(PTab&"!$B:$EH"),AR$5,FALSE),0)) -> 0 | AS21: =IF($O21="","",IFERROR(-VLOOKUP($P21,INDIRECT(PTab&"!$B:$EH"),AS$5,FALSE),0)) -> 0 | AT21: =IF($O21="","",IFERROR(-VLOOKUP($P21,INDIRECT(PTab&"!$B:$EH"),AT$5,FALSE),0)) -> 0 | AU21: =IF($O21="","",IFERROR(-VLOOKUP($P21,INDIRECT(PTab&"!$B:$EH"),AU$5,FALSE),0)) -> 0
